Workbook

Sheet Contrato
C2: COMPARATIVO FACUTACION FOTOCOPIADORAS 2022
D4: 44470 | E4: 44501
C5: CONCEPTO | D5: ANTIGUA | E5: ACTUAL | G5: Dif | H5: %
C7: ALQUILER | D7: 563.8 | E7: 390.6 | G7: =D7-E7 -> 173.2 | H7: =+E7/D7-1 -> -0.30720114
B8: COSTO POR COPIA | C8: MODELO WF-5790 - BN | D8: 0.0198 | E8: 0.0198 | G8: =D8-E8 -> 0 | H8: =+E8/D8-1 -> 0
C9: MODELO WF-5790 - COLOR | D9: 0.0504 | E9: 0.0501 | G9: =D9-E9 -> 0.0003 | H9: =+E9/D9-1 -> -0.005952381
C10: MODELO IR-1730i | D10: 0.0111 | E10: 0.0111 | G10: =D10-E10 -> 0 | H10: =+E10/D10-1 -> 0
C11: MODELO MXC-300A - BN | D11: 0.0195 | E11: 0.0193 | G11: =D11-E11 -> 0.0002 | H11: =+E11/D11-1 -> -0.01025641
C12: MODELO MXC-300A - COLOR | D12: 0.0877 | E12: 0.0875 | G12: =D12-E12 -> 0.0002 | H12: =+E12/D12-1 -> -0.0022805017
C13: MODELO WF-5710 BN | D13: 0.0207 | E13: 0.0202 | G13: =D13-E13 -> 0.0005 | H13: =+E13/D13-1 -> -0.024154589
C14: MODELO WF-5710 COLOR | D14: 0.0524 | E14: 0.0519 | G14: =D14-E14 -> 0.0005 | H14: =+E14/D14-1 -> -0.0095419847
C16: Monto en Dolares
C18: CORTE DE 15 A 15 DE CADA MES

Sheet 2021
B2: REPORTE DE COPIAS - REPRODATA 2021-2022
D5: 44409 | H5: 44440 | L5: 44470 | P5: 44501 | T5: 44531
B6: SERIE DE EQUIPO | C6: UBICACION / AREA | D6: Tipo | E6: Cantidad | F6: Precio $ | G6: Total | H6: Tipo | I6: Cantidad | J6: Precio $ | K6: Total | L6: Tipo | M6: Cantidad | N6: Precio $ | O6: Total | P6: Tipo | Q6: Cantidad | R6: Precio $ | S6: Total | T6: Tipo | U6: Cantidad | V6: Precio $ | W6: Total
B7: IR-1730IQFX06246 | C7: Contabilidad | D7: B/N | E7: 2042 | F7: 0.0146 | G7: =+E7*F7 -> 29.8132 | H7: B/N | I7: 1618 | J7: 0.0146 | K7: =+I7*J7 -> 23.6228 | L7: B/N | M7: 2414 | N7: 0.0146 | O7: =+M7*N7 -> 35.2444 | P7: B/N | Q7: 1743 | R7: 0.0111 | S7: =+Q7*R7 -> 19.3473 | T7: B/N | U7: 1642 | V7: 0.0111 | W7: =+U7*V7 -> 18.2262
B8: IR-1730IQFX06246 | C8: Contabilidad | D8: Colores | F8: 0.0545 | G8: =+E8*F8 -> 0 | H8: Colores | J8: 0.0545 | K8: =+I8*J8 -> 0 | L8: Colores | N8: 0.0545 | O8: =+M8*N8 -> 0 | P8: Colores | R8: 0.0501 | S8: =+Q8*R8 -> 0 | T8: Colores | V8: 0.0501 | W8: =+U8*V8 -> 0
B9: X3B7003581 | C9: C&M Oficina | D9: B/N | E9: 279 | F9: 0.0198 | G9: =+E9*F9 -> 5.5242 | H9: B/N | I9: 483 | J9: 0.0198 | K9: =+I9*J9 -> 9.5634 | L9: B/N | M9: 440 | N9: 0.0198 | O9: =+M9*N9 -> 8.712 | P9: B/N | Q9: 306 | R9: 0.0198 | S9: =+Q9*R9 -> 6.0588 | T9: B/N | U9: 579 | V9: 0.0198 | W9: =+U9*V9 -> 11.4642
B10: X3B7003581 | C10: C&M Oficina | D10: Colores | F10: 0.0545 | G10: =+E10*F10 -> 0 | H10: Colores | J10: 0.0545 | K10: =+I10*J10 -> 0 | L10: Colores | M10: 2 | N10: 0.0545 | O10: =+M10*N10 -> 0.109 | P10: Colores | R10: 0.0501 | S10: =+Q10*R10 -> 0 | T10: Colores | V10: 0.0501 | W10: =+U10*V10 -> 0
B11: X3B7003609 | C11: Talento y Cultura | D11: B/N | E11: 965 | F11: 0.0198 | G11: =+E11*F11 -> 19.107 | H11: B/N | I11: 1196 | J11: 0.0198 | K11: =+I11*J11 -> 23.6808 | L11: B/N | M11: 1184 | N11: 0.0198 | O11: =+M11*N11 -> 23.4432 | P11: B/N | Q11: 1186 | R11: 0.0198 | S11: =+Q11*R11 -> 23.4828 | T11: B/N | U11: 3508 | V11: 0.0198 | W11: =+U11*V11 -> 69.4584
B12: X3B7003609 | C12: Talento y Cultura | D12: Colores | E12: 13 | F12: 0.0545 | G12: =+E12*F12 -> 0.7085 | H12: Colores | I12: 437 | J12: 0.0545 | K12: =+I12*J12 -> 23.8165 | L12: Colores | M12: 1556 | N12: 0.0545 | O12: =+M12*N12 -> 84.802 | P12: Colores | Q12: 71 | R12: 0.0501 | S12: =+Q12*R12 -> 3.5571 | T12: Colores | U12: 62 | V12: 0.0501 | W12: =+U12*V12 -> 3.1062
A13: No se usa | B13: X3B7003615 | C13: Disponible | D13: B/N | F13: 0.0198 | G13: =+E13*F13 -> 0 | H13: B/N | I13: 1 | J13: 0.0198 | K13: =+I13*J13 -> 0.0198 | L13: B/N | N13: 0.0198 | O13: =+M13*N13 -> 0 | P13: B/N | R13: 0.0198 | S13: =+Q13*R13 -> 0 | T13: B/N | V13: 0.0198 | W13: =+U13*V13 -> 0
A14: No se usa | B14: X3B7003615 | C14: Disponible | D14: Colores | F14: 0.0545 | G14: =+E14*F14 -> 0 | H14: Colores | I14: 5 | J14: 0.0545 | K14: =+I14*J14 -> 0.2725 | L14: Colores | N14: 0.0545 | O14: =+M14*N14 -> 0 | P14: Colores | R14: 0.0501 | S14: =+Q14*R14 -> 0 | T14: Colores | V14: 0.0501 | W14: =+U14*V14 -> 0
B15: X3B7003656 | C15: Concierge | D15: B/N | E15: 41 | F15: 0.0198 | G15: =+E15*F15 -> 0.8118 | H15: B/N | I15: 44 | J15: 0.0198 | K15: =+I15*J15 -> 0.8712 | L15: B/N | M15: 5 | N15: 0.0198 | O15: =+M15*N15 -> 0.099 | P15: B/N | Q15: 1 | R15: 0.0198 | S15: =+Q15*R15 -> 0.0198 | T15: B/N | V15: 0.0198 | W15: =+U15*V15 -> 0
B16: X3B7003656 | C16: Concierge | D16: Colores | F16: 0.0545 | G16: =+E16*F16 -> 0 | H16: Colores | J16: 0.0545 | K16: =+I16*J16 -> 0 | L16: Colores | M16: 2 | N16: 0.0545 | O16: =+M16*N16 -> 0.109 | P16: Colores | R16: 0.0501 | S16: =+Q16*R16 -> 0 | T16: Colores | V16: 0.0501 | W16: =+U16*V16 -> 0
B17: X3B7003659 | C17: Asistente Gerencia General | D17: B/N | E17: 301 | F17: 0.0198 | G17: =+E17*F17 -> 5.9598 | H17: B/N | I17: 93 | J17: 0.0198 | K17: =+I17*J17 -> 1.8414 | L17: B/N | M17: 134 | N17: 0.0198 | O17: =+M17*N17 -> 2.6532 | P17: B/N | Q17: 101 | R17: 0.0198 | S17: =+Q17*R17 -> 1.9998 | T17: B/N | V17: 0.0198 | W17: =+U17*V17 -> 0
B18: X3B7003659 | C18: Asistente Gerencia General | D18: Colores | E18: 162 | F18: 0.0545 | G18: =+E18*F18 -> 8.829 | H18: Colores | I18: 352 | J18: 0.0545 | K18: =+I18*J18 -> 19.184 | L18: Colores | M18: 245 | N18: 0.0545 | O18: =+M18*N18 -> 13.3525 | P18: Colores | Q18: 141 | R18: 0.0501 | S18: =+Q18*R18 -> 7.0641 | T18: Colores | V18: 0.0501 | W18: =+U18*V18 -> 0
B19: X3B7003660 | C19: Room Service | D19: B/N | E19: 1534 | F19: 0.0198 | G19: =+E19*F19 -> 30.3732 | H19: B/N | I19: 1949 | J19: 0.0198 | K19: =+I19*J19 -> 38.5902 | L19: B/N | M19: 1951 | N19: 0.0198 | O19: =+M19*N19 -> 38.6298 | P19: B/N | Q19: 1831 | R19: 0.0198 | S19: =+Q19*R19 -> 36.2538 | T19: B/N | U19: 1425 | V19: 0.0198 | W19: =+U19*V19 -> 28.215
B20: X3B7003660 | C20: Room Service | D20: Colores | F20: 0.0545 | G20: =+E20*F20 -> 0 | H20: Colores | I20: 1 | J20: 0.0545 | K20: =+I20*J20 -> 0.0545 | L20: Colores | N20: 0.0545 | O20: =+M20*N20 -> 0 | P20: Colores | R20: 0.0501 | S20: =+Q20*R20 -> 0 | T20: Colores | U20: 1 | V20: 0.0501 | W20: =+U20*V20 -> 0.0501
A21: No se usa | B21: X3B7003661 | C21: Disponible | D21: B/N | F21: 0.0198 | G21: =+E21*F21 -> 0 | H21: B/N | I21: 7 | J21: 0.0198 | K21: =+I21*J21 -> 0.1386 | L21: B/N | M21: 2 | N21: 0.0198 | O21: =+M21*N21 -> 0.0396 | P21: B/N | R21: 0.0198 | S21: =+Q21*R21 -> 0 | T21: B/N | V21: 0.0198 | W21: =+U21*V21 -> 0
A22: No se usa | B22: X3B7003661 | C22: Disponible | D22: Colores | E22: 2 | F22: 0.0545 | G22: =+E22*F22 -> 0.109 | H22: Colores | I22: 3 | J22: 0.0545 | K22: =+I22*J22 -> 0.1635 | L22: Colores | N22: 0.0545 | O22: =+M22*N22 -> 0 | P22: Colores | R22: 0.0501 | S22: =+Q22*R22 -> 0 | T22: Colores | V22: 0.0501 | W22: =+U22*V22 -> 0
B23: X3B7003671 | C23: Compras | D23: B/N | E23: 9 | F23: 0.0198 | G23: =+E23*F23 -> 0.1782 | H23: B/N | I23: 20 | J23: 0.0198 | K23: =+I23*J23 -> 0.396 | L23: B/N | M23: 24 | N23: 0.0198 | O23: =+M23*N23 -> 0.4752 | P23: B/N | Q23: 20 | R23: 0.0198 | S23: =+Q23*R23 -> 0.396 | T23: B/N | U23: 15 | V23: 0.0198 | W23: =+U23*V23 -> 0.297
B24: X3B7003671 | C24: Compras | D24: Colores | E24: 25 | F24: 0.0545 | G24: =+E24*F24 -> 1.3625 | H24: Colores | I24: 13 | J24: 0.0545 | K24: =+I24*J24 -> 0.7085 | L24: Colores | M24: 27 | N24: 0.0545 | O24: =+M24*N24 -> 1.4715 | P24: Colores | Q24: 18 | R24: 0.0501 | S24: =+Q24*R24 -> 0.9018 | T24: Colores | U24: 17 | V24: 0.0501 | W24: =+U24*V24 -> 0.8517
B25: X3B7003690 | C25: Cuadres | D25: B/N | F25: 0.0198 | G25: =+E25*F25 -> 0 | H25: B/N | J25: 0.0198 | K25: =+I25*J25 -> 0 | L25: B/N | N25: 0.0198 | O25: =+M25*N25 -> 0 | P25: B/N | R25: 0.0198 | S25: =+Q25*R25 -> 0 | T25: B/N | V25: 0.0198 | W25: =+U25*V25 -> 0
B26: X3B7003690 | C26: Cuadres | D26: Colores | F26: 0.0545 | G26: =+E26*F26 -> 0 | H26: Colores | J26: 0.0545 | K26: =+I26*J26 -> 0 | L26: Colores | N26: 0.0545 | O26: =+M26*N26 -> 0 | P26: Colores | R26: 0.0501 | S26: =+Q26*R26 -> 0 | T26: Colores | V26: 0.0501 | W26: =+U26*V26 -> 0
B27: X3B7003703 | C27: GYM | D27: B/N | E27: 853 | F27: 0.0198 | G27: =+E27*F27 -> 16.8894 | H27: B/N | I27: 921 | J27: 0.0198 | K27: =+I27*J27 -> 18.2358 | L27: B/N | N27: 0.0198 | O27: =+M27*N27 -> 0 | P27: B/N | R27: 0.0198 | S27: =+Q27*R27 -> 0 | T27: B/N | V27: 0.0198 | W27: =+U27*V27 -> 0
B28: X3B7003703 | C28: GYM | D28: Colores | F28: 0.0545 | G28: =+E28*F28 -> 0 | H28: Colores | J28: 0.0545 | K28: =+I28*J28 -> 0 | L28: Colores | M28: 1227 | N28: 0.0545 | O28: =+M28*N28 -> 66.8715 | P28: Colores | Q28: 540 | R28: 0.0501 | S28: =+Q28*R28 -> 27.054 | T28: Colores | V28: 0.0501 | W28: =+U28*V28 -> 0
B29: X3B7003711 | C29: Oficina de Recepción | D29: B/N | E29: 481 | F29: 0.0198 | G29: =+E29*F29 -> 9.5238 | H29: B/N | I29: 529 | J29: 0.0198 | K29: =+I29*J29 -> 10.4742 | L29: B/N | M29: 510 | N29: 0.0198 | O29: =+M29*N29 -> 10.098 | P29: B/N | Q29: 453 | R29: 0.0198 | S29: =+Q29*R29 -> 8.9694 | T29: B/N | U29: 868 | V29: 0.0198 | W29: =+U29*V29 -> 17.1864
B30: X3B7003711 | C30: Oficina de Recepción | D30: Colores | E30: 65 | F30: 0.0545 | G30: =+E30*F30 -> 3.5425 | H30: Colores | I30: 173 | J30: 0.0545 | K30: =+I30*J30 -> 9.4285 | L30: Colores | M30: 28 | N30: 0.0545 | O30: =+M30*N30 -> 1.526 | P30: Colores | Q30: 75 | R30: 0.0501 | S30: =+Q30*R30 -> 3.7575 | T30: Colores | U30: 115 | V30: 0.0501 | W30: =+U30*V30 -> 5.7615
B31: X3B7003712 | C31: Bodegas | D31: B/N | E31: 66 | F31: 0.0198 | G31: =+E31*F31 -> 1.3068 | H31: B/N | I31: 53 | J31: 0.0198 | K31: =+I31*J31 -> 1.0494 | L31: B/N | M31: 80 | N31: 0.0198 | O31: =+M31*N31 -> 1.584 | P31: B/N | Q31: 49 | R31: 0.0198 | S31: =+Q31*R31 -> 0.9702 | T31: B/N | U31: 49 | V31: 0.0198 | W31: =+U31*V31 -> 0.9702
B32: X3B7003712 | C32: Bodegas | D32: Colores | F32: 0.0545 | G32: =+E32*F32 -> 0 | H32: Colores | I32: 2 | J32: 0.0545 | K32: =+I32*J32 -> 0.109 | L32: Colores | N32: 0.0545 | O32: =+M32*N32 -> 0 | P32: Colores | R32: 0.0501 | S32: =+Q32*R32 -> 0 | T32: Colores | V32: 0.0501 | W32: =+U32*V32 -> 0
B33: X3B7003716 | C33: Limpieza | D33: B/N | E33: 22 | F33: 0.0198 | G33: =+E33*F33 -> 0.4356 | H33: B/N | I33: 74 | J33: 0.0198 | K33: =+I33*J33 -> 1.4652 | L33: B/N | M33: 86 | N33: 0.0198 | O33: =+M33*N33 -> 1.7028 | P33: B/N | Q33: 84 | R33: 0.0198 | S33: =+Q33*R33 -> 1.6632 | T33: B/N | U33: 84 | V33: 0.0198 | W33: =+U33*V33 -> 1.6632
B34: X3B7003716 | C34: Limpieza | D34: Colores | F34: 0.0545 | G34: =+E34*F34 -> 0 | H34: Colores | I34: 2 | J34: 0.0545 | K34: =+I34*J34 -> 0.109 | L34: Colores | M34: 540 | N34: 0.0545 | O34: =+M34*N34 -> 29.43 | P34: Colores | R34: 0.0501 | S34: =+Q34*R34 -> 0 | T34: Colores | V34: 0.0501 | W34: =+U34*V34 -> 0
B35: X3B7003751 | C35: Housekeeping | D35: B/N | F35: 0.0198 | G35: =+E35*F35 -> 0 | H35: B/N | I35: 4652 | J35: 0.0198 | K35: =+I35*J35 -> 92.1096 | L35: B/N | M35: 2420 | N35: 0.0198 | O35: =+M35*N35 -> 47.916 | P35: B/N | Q35: 2051 | R35: 0.0198 | S35: =+Q35*R35 -> 40.6098 | T35: B/N | U35: 1788 | V35: 0.0198 | W35: =+U35*V35 -> 35.4024
B36: X3B7003751 | C36: Housekeeping | D36: Colores | F36: 0.0545 | G36: =+E36*F36 -> 0 | H36: Colores | J36: 0.0545 | K36: =+I36*J36 -> 0 | L36: Colores | N36: 0.0545 | O36: =+M36*N36 -> 0 | P36: Colores | R36: 0.0501 | S36: =+Q36*R36 -> 0 | T36: Colores | V36: 0.0501 | W36: =+U36*V36 -> 0
A37: No se usa | B37: X3B7003828 | C37: Disponible | D37: B/N | F37: 0.0198 | G37: =+E37*F37 -> 0 | H37: B/N | J37: 0.0198 | K37: =+I37*J37 -> 0 | L37: B/N | N37: 0.0198 | O37: =+M37*N37 -> 0 | P37: B/N | R37: 0.0198 | S37: =+Q37*R37 -> 0 | T37: B/N | V37: 0.0198 | W37: =+U37*V37 -> 0
A38: No se usa | B38: X3B7003828 | C38: Disponible | D38: Colores | F38: 0.0545 | G38: =+E38*F38 -> 0 | H38: Colores | J38: 0.0545 | K38: =+I38*J38 -> 0 | L38: Colores | N38: 0.0545 | O38: =+M38*N38 -> 0 | P38: Colores | R38: 0.0501 | S38: =+Q38*R38 -> 0 | T38: Colores | V38: 0.0501 | W38: =+U38*V38 -> 0
B39: X3B7003944 | C39: Reservas | D39: B/N | E39: 17 | F39: 0.0198 | G39: =+E39*F39 -> 0.3366 | H39: B/N | J39: 0.0198 | K39: =+I39*J39 -> 0 | L39: B/N | M39: 29 | N39: 0.0198 | O39: =+M39*N39 -> 0.5742 | P39: B/N | Q39: 16 | R39: 0.0198 | S39: =+Q39*R39 -> 0.3168 | T39: B/N | U39: 29 | V39: 0.0198 | W39: =+U39*V39 -> 0.5742
B40: X3B7003944 | C40: Reservas | D40: Colores | F40: 0.0545 | G40: =+E40*F40 -> 0 | H40: Colores | J40: 0.0545 | K40: =+I40*J40 -> 0 | L40: Colores | M40: 5 | N40: 0.0545 | O40: =+M40*N40 -> 0.2725 | P40: Colores | Q40: 5 | R40: 0.0501 | S40: =+Q40*R40 -> 0.2505 | T40: Colores | U40: 1 | V40: 0.0501 | W40: =+U40*V40 -> 0.0501
B41: X3B7003739 | C41: Banquetes | D41: B/N | F41: 0.0198 | G41: =+E41*F41 -> 0 | H41: B/N | J41: 0.0198 | K41: =+I41*J41 -> 0 | L41: B/N | N41: 0.0198 | O41: =+M41*N41 -> 0 | P41: B/N | R41: 0.0198 | S41: =+Q41*R41 -> 0 | T41: B/N | U41: 109 | V41: 0.0198 | W41: =+U41*V41 -> 2.1582
B42: X3B7003739 | C42: Banquetes | D42: Colores | F42: 0.0545 | G42: =+E42*F42 -> 0 | H42: Colores | J42: 0.0545 | K42: =+I42*J42 -> 0 | L42: Colores | N42: 0.0545 | O42: =+M42*N42 -> 0 | P42: Colores | R42: 0.0501 | S42: =+Q42*R42 -> 0 | T42: Colores | U42: 33 | V42: 0.0501 | W42: =+U42*V42 -> 1.6533
B43: MXC300 45000119 | C43: AyB | D43: B/N | E43: 163 | F43: 0.0135 | G43: =+E43*F43 -> 2.2005 | H43: B/N | J43: 0.0135 | K43: =+I43*J43 -> 0 | L43: B/N | N43: 0.0135 | O43: =+M43*N43 -> 0 | P43: B/N | Q43: 153 | R43: 0.0136 | S43: =+Q43*R43 -> 2.0808 | T43: B/N | U43: 395 | V43: 0.0136 | W43: =+U43*V43 -> 5.372
B44: MXC300 45000119 | C44: AyB | D44: Colores | E44: 860 | F44: 0.0599 | G44: =+E44*F44 -> 51.514 | H44: Colores | I44: 880 | J44: 0.0599 | K44: =+I44*J44 -> 52.712 | L44: Colores | M44: 735 | N44: 0.0599 | O44: =+M44*N44 -> 44.0265 | P44: Colores | Q44: 707 | R44: 0.0601 | S44: =+Q44*R44 -> 42.4907 | T44: Colores | U44: 767 | V44: 0.0601 | W44: =+U44*V44 -> 46.0967
B45: X3B2001312 | C45: Ventas - B&N | D45: B/N | E45: 779 | F45: 0.0207 | G45: =+E45*F45 -> 16.1253 | H45: B/N | I45: 274 | J45: 0.0207 | K45: =+I45*J45 -> 5.6718 | L45: B/N | M45: 605 | N45: 0.0207 | O45: =+M45*N45 -> 12.5235 | P45: B/N | Q45: 1115 | R45: 0.0202 | S45: =+Q45*R45 -> 22.523 | T45: B/N | U45: 598 | V45: 0.0202 | W45: =+U45*V45 -> 12.0796
B46: X3B2001312 | C46: Ventas - B&N | D46: Colores | E46: 44 | F46: 0.0554 | G46: =+E46*F46 -> 2.4376 | H46: Colores | I46: 54 | J46: 0.0554 | K46: =+I46*J46 -> 2.9916 | L46: Colores | M46: 276 | N46: 0.0554 | O46: =+M46*N46 -> 15.2904 | P46: Colores | Q46: 561 | R46: 0.0519 | S46: =+Q46*R46 -> 29.1159 | T46: Colores | U46: 806 | V46: 0.0519 | W46: =+U46*V46 -> 41.8314
B47: MF426QFX06116 | C47: Auditor nocturno | D47: B/N | E47: 17558 | F47: 0.0146 | G47: =+E47*F47 -> 256.3468 | H47: B/N | I47: 16511 | J47: 0.0146 | K47: =+I47*J47 -> 241.0606 | L47: B/N | M47: 17680 | N47: 0.0146 | O47: =+M47*N47 -> 258.128 | P47: B/N | Q47: 16309 | R47: 0.0111 | S47: =+Q47*R47 -> 181.0299 | T47: B/N | U47: 13318 | V47: 0.0111 | W47: =+U47*V47 -> 147.8298
B48: MF426QFX06116 | C48: Auditor nocturno | D48: Colores | F48: 0.0545 | G48: =+E48*F48 -> 0 | H48: Colores | J48: 0.0545 | K48: =+I48*J48 -> 0 | L48: Colores | N48: 0.0545 | O48: =+M48*N48 -> 0 | P48: Colores | R48: 0.0545 | S48: =+Q48*R48 -> 0 | T48: Colores | V48: 0.0545 | W48: =+U48*V48 -> 0
B49: MF426QFX06245 | C49: FD 3,4 | D49: B/N | E49: 7780 | F49: 0.0146 | G49: =+E49*F49 -> 113.588 | H49: B/N | I49: 7036 | J49: 0.0146 | K49: =+I49*J49 -> 102.7256 | L49: B/N | M49: 6130 | N49: 0.0146 | O49: =+M49*N49 -> 89.498 | P49: B/N | Q49: 6734 | R49: 0.0111 | S49: =+Q49*R49 -> 74.7474 | T49: B/N | U49: 6228 | V49: 0.0111 | W49: =+U49*V49 -> 69.1308
B50: MF426QFX06245 | C50: FD 3,4 | D50: Colores | F50: 0.0545 | G50: =+E50*F50 -> 0 | H50: Colores | J50: 0.0545 | K50: =+I50*J50 -> 0 | L50: Colores | N50: 0.0545 | O50: =+M50*N50 -> 0 | P50: Colores | R50: 0.0501 | S50: =+Q50*R50 -> 0 | T50: Colores | V50: 0.0501 | W50: =+U50*V50 -> 0
B51: MF426QFX06113 | C51: FD 1,2 | D51: B/N | F51: 0.0198 | G51: =+E51*F51 -> 0 | H51: B/N | J51: 0.0198 | K51: =+I51*J51 -> 0 | L51: B/N | N51: 0.0198 | O51: =+M51*N51 -> 0 | P51: B/N | R51: 0.0198 | S51: =+Q51*R51 -> 0 | T51: B/N | V51: 0.0198 | W51: =+U51*V51 -> 0
B52: MF426QFX06113 | C52: FD 1,2 | D52: Colores | F52: 0.0545 | G52: =+E52*F52 -> 0 | H52: Colores | J52: 0.0545 | K52: =+I52*J52 -> 0 | L52: Colores | N52: 0.0545 | O52: =+M52*N52 -> 0 | P52: Colores | R52: 0.0501 | S52: =+Q52*R52 -> 0 | T52: Colores | V52: 0.0501 | W52: =+U52*V52 -> 0
E53: =SUM(E7:E52) -> 34061 | I53: =SUM(I7:I52) -> 37383 | M53: =SUM(M7:M52) -> 38337 | Q53: =SUM(Q7:Q52) -> 34270 | U53: =SUM(U7:U52) -> 32437 | Y53: =(E53+I53+M53+Q53+U53)/5 -> 35297.6
D54: TOTAL COPIAS | G54: =SUM(G7:G52) -> 577.0233 | H54: TOTAL COPIAS | K54: =SUM(K7:K52) -> 681.066 | L54: TOTAL COPIAS | O54: =SUM(O7:O52) -> 788.5818 | P54: TOTAL COPIAS | S54: =SUM(S7:S52) -> 534.6604 | T54: TOTAL COPIAS | W54: =SUM(W7:W52) -> 519.4286 | Y54: Promedio
D55: TOTAL RENTA | G55: 574.76 | H55: TOTAL RENTA | K55: 574.76 | L55: TOTAL RENTA | O55: 574.76 | P55: TOTAL RENTA | S55: 390.6 | T55: TOTAL RENTA | W55: 390.6
D57: FACTURACION | G57: =+G54+G55 -> 1151.7833 | H57: FACTURACION | K57: =+K54+K55 -> 1255.826 | L57: FACTURACION | O57: =+O54+O55 -> 1363.3418 | P57: FACTURACION | S57: =+S54+S55 -> 925.2604 | T57: FACTURACION | W57: =+W54+W55 -> 910.0286
D59: B/N | E59: 0.0198 | H59: B/N | I59: 0.0198 | L59: B/N | M59: 0.0198 | P59: B/N | Q59: 0.0198 | T59: B/N | U59: 0.0198
D60: Color | E60: 0.0545 | H60: Color | I60: 0.0545 | L60: Color | M60: 0.0545 | P60: Color | Q60: 0.0545 | T60: Color | U60: 0.0545
B62: CAMBIO DE CONTRATO
B63: RENTA OCT 21 | C63: 574.76 | S63: =+S57/O57-1 -> -0.3213291 | W63: =+W57/S57-1 -> -0.016462176
B64: RENTA NOV 21 | C64: 390.6
C65: =+C63-C64 -> 184.16

Sheet 01
A1: Column1 | B1: Column2 | C1: Column3 | D1: Column4 | E1: Column5 | F1: Column6 | G1: Column7 | H1: Column8 | I1: Column9 | J1: Column10 | K1: Column11 | L1: Column12 | M1: Column13
C2: TOTALES | D2: 3111 | E2: 4213 | M2: =IF(AND(A2<>"",LEFT(A2,3)<>"AV."),A2,M1) -> Column13
A3: XBJZ021745 - WF-C5890 - Bolsa 3 | C3: A4BN | D3: 4141 | E3: 4785 | G3: 644 | H3: 0 | J3: 0 | K3: 0.0168 | L3: 0.00 | M3: =IF(AND(A3<>"",LEFT(A3,3)<>"AV."),A3,M2) -> XBJZ021745 - WF-C5890 - Bolsa 3
A4: AV. VIA CENTRAL 190 CENTRO EMPRESARIAL | C4: A3BN | D4: 0 | E4: 0 | G4: 0 | H4: 0 | J4: 0 | K4: 0.0301 | L4: 0.00 | M4: =IF(AND(A4<>"",LEFT(A4,3)<>"AV."),A4,M3) -> XBJZ021745 - WF-C5890 - Bolsa 3
C5: A4CL | D5: 23586 | E5: 27528 | G5: 3942 | H5: 0 | J5: 0 | K5: 0.0472 | L5: 0.00 | M5: =IF(AND(A5<>"",LEFT(A5,3)<>"AV."),A5,M4) -> XBJZ021745 - WF-C5890 - Bolsa 3
C6: A3CL | D6: 0 | E6: 0 | G6: 0 | H6: 0 | J6: 0 | K6: 0.0906 | L6: 0.00 | M6: =IF(AND(A6<>"",LEFT(A6,3)<>"AV."),A6,M5) -> XBJZ021745 - WF-C5890 - Bolsa 3
C7: TOTALES | D7: 27727 | E7: 32313 | M7: =IF(AND(A7<>"",LEFT(A7,3)<>"AV."),A7,M6) -> XBJZ021745 - WF-C5890 - Bolsa 3
A8: XBJZ027512 - WF-C5890 - Bolsa 3 | C8: A4BN | D8: 3883 | E8: 5188 | G8: 1305 | H8: 0 | J8: 0 | K8: 0.0168 | L8: 0.00 | M8: =IF(AND(A8<>"",LEFT(A8,3)<>"AV."),A8,M7) -> XBJZ027512 - WF-C5890 - Bolsa 3
A9: AV. VIA CENTRAL 190 CENTRO EMPRESARIAL | C9: A3BN | D9: 0 | E9: 0 | G9: 0 | H9: 0 | J9: 0 | K9: 0.0301 | L9: 0.00 | M9: =IF(AND(A9<>"",LEFT(A9,3)<>"AV."),A9,M8) -> XBJZ027512 - WF-C5890 - Bolsa 3
C10: A4CL | D10: 11370 | E10: 15352 | G10: 3982 | H10: 0 | J10: 0 | K10: 0.0472 | L10: 0.00 | M10: =IF(AND(A10<>"",LEFT(A10,3)<>"AV."),A10,M9) -> XBJZ027512 - WF-C5890 - Bolsa 3
C11: A3CL | D11: 0 | E11: 0 | G11: 0 | H11: 0 | J11: 0 | K11: 0.0906 | L11: 0.00 | M11: =IF(AND(A11<>"",LEFT(A11,3)<>"AV."),A11,M10) -> XBJZ027512 - WF-C5890 - Bolsa 3
C12: TOTALES | D12: 15253 | E12: 20540 | M12: =IF(AND(A12<>"",LEFT(A12,3)<>"AV."),A12,M11) -> XBJZ027512 - WF-C5890 - Bolsa 3
A13: 35009304 - MX-3070 - Bolsa 4 | C13: A4BN | D13: 5 | E13: 3848 | G13: 3843 | H13: 0 | J13: 0 | K13: 0.0168 | L13: 0.00 | M13: =IF(AND(A13<>"",LEFT(A13,3)<>"AV."),A13,M12) -> 35009304 - MX-3070 - Bolsa 4
C14: A3BN | D14: 0 | E14: 0 | G14: 0 | H14: 0 | J14: 0 | K14: 0.0301 | L14: 0.00 | M14: =IF(AND(A14<>"",LEFT(A14,3)<>"AV."),A14,M13) -> 35009304 - MX-3070 - Bolsa 4
C15: A4CL | D15: 31 | E15: 340 | G15: 309 | H15: 0 | J15: 0 | K15: 0.0472 | L15: 0.00 | M15: =IF(AND(A15<>"",LEFT(A15,3)<>"AV."),A15,M14) -> 35009304 - MX-3070 - Bolsa 4
C16: A3CL | D16: 0 | E16: 0 | G16: 0 | H16: 0 | J16: 0 | K16: 0.0906 | L16: 0.00 | M16: =IF(AND(A16<>"",LEFT(A16,3)<>"AV."),A16,M15) -> 35009304 - MX-3070 - Bolsa 4
C17: TOTALES | D17: 36 | E17: 4188 | M17: =IF(AND(A17<>"",LEFT(A17,3)<>"AV."),A17,M16) -> 35009304 - MX-3070 - Bolsa 4
A18: 35E33608 - IR-1643 - Bolsa 1 | C18: A4BN | D18: 36 | E18: 23904 | G18: 23868 | H18: 0 | J18: 0 | K18: 0.0168 | L18: 0.00 | M18: =IF(AND(A18<>"",LEFT(A18,3)<>"AV."),A18,M17) -> 35E33608 - IR-1643 - Bolsa 1
A19: AV. SANTO TORIBIO NRO 173 URB ROSARIO (V | C19: A3BN | D19: 0 | E19: 0 | G19: 0 | H19: 0 | J19: 0 | K19: 0.0301 | L19: 0.00 | M19: =IF(AND(A19<>"",LEFT(A19,3)<>"AV."),A19,M18) -> 35E33608 - IR-1643 - Bolsa 1
C20: A4CL | D20: 0 | E20: 0 | G20: 0 | H20: 0 | J20: 0 | K20: 0.0472 | L20: 0.00 | M20: =IF(AND(A20<>"",LEFT(A20,3)<>"AV."),A20,M19) -> 35E33608 - IR-1643 - Bolsa 1
C21: A3CL | D21: 0 | E21: 0 | G21: 0 | H21: 0 | J21: 0 | K21: 0.0906 | L21: 0.00 | M21: =IF(AND(A21<>"",LEFT(A21,3)<>"AV."),A21,M20) -> 35E33608 - IR-1643 - Bolsa 1
C22: TOTALES | D22: 36 | E22: 23904 | M22: =IF(AND(A22<>"",LEFT(A22,3)<>"AV."),A22,M21) -> 35E33608 - IR-1643 - Bolsa 1
A23: 35E33607 - IR-1643 - Bolsa 1 | C23: A4BN | D23: 6528 | E23: 14888 | G23: 8360 | H23: 0 | J23: 0 | K23: 0.0168 | L23: 0.00 | M23: =IF(AND(A23<>"",LEFT(A23,3)<>"AV."),A23,M22) -> 35E33607 - IR-1643 - Bolsa 1
A24: AV. SANTO TORIBIO NRO 173 URB ROSARIO (VIA CENTRO | C24: A3BN | D24: 0 | E24: 0 | G24: 0 | H24: 0 | J24: 0 | K24: 0.0301 | L24: 0.00 | M24: =IF(AND(A24<>"",LEFT(A24,3)<>"AV."),A24,M23) -> 35E33607 - IR-1643 - Bolsa 1
C25: A4CL | D25: 0 | E25: 0 | G25: 0 | H25: 0 | J25: 0 | K25: 0.0472 | L25: 0.00 | M25: =IF(AND(A25<>"",LEFT(A25,3)<>"AV."),A25,M24) -> 35E33607 - IR-1643 - Bolsa 1
C26: A3CL | D26: 0 | E26: 0 | G26: 0 | H26: 0 | J26: 0 | K26: 0.0906 | L26: 0.00 | M26: =IF(AND(A26<>"",LEFT(A26,3)<>"AV."),A26,M25) -> 35E33607 - IR-1643 - Bolsa 1
C27: TOTALES | D27: 6528 | E27: 14888 | M27: =IF(AND(A27<>"",LEFT(A27,3)<>"AV."),A27,M26) -> 35E33607 - IR-1643 - Bolsa 1
A28: RJQ00596 - IR-C3330 - Bolsa 5 | C28: A4BN | D28: 130708 | E28: 131063 | G28: 355 | H28: 0 | J28: 0 | K28: 0.0168 | L28: 0.00 | M28: =IF(AND(A28<>"",LEFT(A28,3)<>"AV."),A28,M27) -> RJQ00596 - IR-C3330 - Bolsa 5
A29: AV. VIA CENTRAL 190 CENTRO EMPRESARIAL | C29: A3BN | D29: 6966 | E29: 6966 | G29: 0 | H29: 0 | J29: 0 | K29: 0.0301 | L29: 0.00 | M29: =IF(AND(A29<>"",LEFT(A29,3)<>"AV."),A29,M28) -> RJQ00596 - IR-C3330 - Bolsa 5
C30: A4CL | D30: 187880 | E30: 188332 | G30: 452 | H30: 0 | J30: 0 | K30: 0.0472 | L30: 0.00 | M30: =IF(AND(A30<>"",LEFT(A30,3)<>"AV."),A30,M29) -> RJQ00596 - IR-C3330 - Bolsa 5
C31: A3CL | D31: 6966 | E31: 6970 | G31: 4 | H31: 0 | J31: 0 | K31: 0.0906 | L31: 0.00 | M31: =IF(AND(A31<>"",LEFT(A31,3)<>"AV."),A31,M30) -> RJQ00596 - IR-C3330 - Bolsa 5
C32: TOTALES | D32: 332520 | E32: 333331 | M32: =IF(AND(A32<>"",LEFT(A32,3)<>"AV."),A32,M31) -> RJQ00596 - IR-C3330 - Bolsa 5
A33: BOLSA N° #1 | C33: FORMATOS | F33: VOLUMEN MAXIMO ESTABLECIDO | I33: VOLUMEN EXCEDENTE A LO ESTABLECIDO | K33: VALOR UNIDAD EXCEDENTE | L33: MONTO TOTAL EXCEDENTE | M33: =IF(AND(A33<>"",LEFT(A33,3)<>"AV."),A33,M32) -> BOLSA N° #1
C34: A4BN | D34: 43216 | F34: 13000 | I34: 30216 | K34: 0.0168 | L34: 507.63 | M34: =IF(AND(A34<>"",LEFT(A34,3)<>"AV."),A34,M33) -> BOLSA N° #1
C35: A3BN | D35: 0 | F35: 0 | I35: 0 | K35: 0.0301 | L35: 0.00 | M35: =IF(AND(A35<>"",LEFT(A35,3)<>"AV."),A35,M34) -> BOLSA N° #1
C36: A4CL | D36: 0 | F36: 0 | I36: 0 | K36: 0.0472 | L36: 0.00 | M36: =IF(AND(A36<>"",LEFT(A36,3)<>"AV."),A36,M35) -> BOLSA N° #1
C37: A3CL | D37: 0 | F37: 0 | I37: 0 | K37: 0.0906 | L37: 0.00 | M37: =IF(AND(A37<>"",LEFT(A37,3)<>"AV."),A37,M36) -> BOLSA N° #1
A38: BOLSA N° #2 | C38: FORMATOS | F38: VOLUMEN MAXIMO ESTABLECIDO | I38: VOLUMEN EXCEDENTE A LO ESTABLECIDO | K38: VALOR UNIDAD EXCEDENTE | L38: MONTO TOTAL EXCEDENTE | M38: =IF(AND(A38<>"",LEFT(A38,3)<>"AV."),A38,M37) -> BOLSA N° #2
C39: A4BN | D39: 9567 | F39: 1504 | I39: 8063 | K39: 0.0168 | L39: 135.46 | M39: =IF(AND(A39<>"",LEFT(A39,3)<>"AV."),A39,M38) -> BOLSA N° #2
C40: A3BN | D40: 0 | F40: 0 | I40: 0 | K40: 0.0301 | L40: 0.00 | M40: =IF(AND(A40<>"",LEFT(A40,3)<>"AV."),A40,M39) -> BOLSA N° #2
C41: A4CL | D41: 9450 | F41: 4504 | I41: 4946 | K41: 0.0472 | L41: 233.45 | M41: =IF(AND(A41<>"",LEFT(A41,3)<>"AV."),A41,M40) -> BOLSA N° #2
C42: A3CL | D42: 0 | F42: 0 | I42: 0 | K42: 0.0906 | L42: 0.00 | M42: =IF(AND(A42<>"",LEFT(A42,3)<>"AV."),A42,M41) -> BOLSA N° #2
A43: BOLSA N° #3 | C43: FORMATOS | F43: VOLUMEN MAXIMO ESTABLECIDO | I43: VOLUMEN EXCEDENTE A LO ESTABLECIDO | K43: VALOR UNIDAD EXCEDENTE | L43: MONTO TOTAL EXCEDENTE | M43: =IF(AND(A43<>"",LEFT(A43,3)<>"AV."),A43,M42) -> BOLSA N° #3
C44: A4BN | D44: 4130 | F44: 1128 | I44: 3002 | K44: 0.0168 | L44: 50.43 | M44: =IF(AND(A44<>"",LEFT(A44,3)<>"AV."),A44,M43) -> BOLSA N° #3
C45: A3BN | D45: 0 | F45: 0 | I45: 0 | K45: 0.0301 | L45: 0.00 | M45: =IF(AND(A45<>"",LEFT(A45,3)<>"AV."),A45,M44) -> BOLSA N° #3
C46: A4CL | D46: 14794 | F46: 3378 | I46: 11416 | K46: 0.0472 | L46: 538.84 | M46: =IF(AND(A46<>"",LEFT(A46,3)<>"AV."),A46,M45) -> BOLSA N° #3
C47: A3CL | D47: 0 | F47: 0 | I47: 0 | K47: 0.0906 | L47: 0.00 | M47: =IF(AND(A47<>"",LEFT(A47,3)<>"AV."),A47,M46) -> BOLSA N° #3
A48: BOLSA N° #4 | C48: FORMATOS | F48: VOLUMEN MAXIMO ESTABLECIDO | I48: VOLUMEN EXCEDENTE A LO ESTABLECIDO | K48: VALOR UNIDAD EXCEDENTE | L48: MONTO TOTAL EXCEDENTE | M48: =IF(AND(A48<>"",LEFT(A48,3)<>"AV."),A48,M47) -> BOLSA N° #4
C49: A4BN | D49: 3843 | F49: 188 | I49: 3655 | K49: 0.0168 | L49: 61.40 | M49: =IF(AND(A49<>"",LEFT(A49,3)<>"AV."),A49,M48) -> BOLSA N° #4
C50: A3BN | D50: 0 | F50: 0 | I50: 0 | K50: 0.0301 | L50: 0.00 | M50: =IF(AND(A50<>"",LEFT(A50,3)<>"AV."),A50,M49) -> BOLSA N° #4
C51: A4CL | D51: 309 | F51: 563 | I51: 0 | K51: 0.0472 | L51: 0.00 | M51: =IF(AND(A51<>"",LEFT(A51,3)<>"AV."),A51,M50) -> BOLSA N° #4
C52: A3CL | D52: 0 | F52: 0 | I52: 0 | K52: 0.0906 | L52: 0.00 | M52: =IF(AND(A52<>"",LEFT(A52,3)<>"AV."),A52,M51) -> BOLSA N° #4
A53: BOLSA N° #5 | C53: FORMATOS | F53: VOLUMEN MAXIMO ESTABLECIDO | I53: VOLUMEN EXCEDENTE A LO ESTABLECIDO | K53: VALOR UNIDAD EXCEDENTE | L53: MONTO TOTAL EXCEDENTE | M53: =IF(AND(A53<>"",LEFT(A53,3)<>"AV."),A53,M52) -> BOLSA N° #5
C54: A4BN | D54: 355 | F54: 188 | I54: 167 | K54: 0.0168 | L54: 2.81 | M54: =IF(AND(A54<>"",LEFT(A54,3)<>"AV."),A54,M53) -> BOLSA N° #5
C55: A3BN | D55: 0 | F55: 0 | I55: 0 | K55: 0.0301 | L55: 0.00 | M55: =IF(AND(A55<>"",LEFT(A55,3)<>"AV."),A55,M54) -> BOLSA N° #5
C56: A4CL | D56: 452 | F56: 563 | I56: 0 | K56: 0.0472 | L56: 0.00 | M56: =IF(AND(A56<>"",LEFT(A56,3)<>"AV."),A56,M55) -> BOLSA N° #5
C57: A3CL | D57: 4 | F57: 0 | I57: 4 | K57: 0.0906 | L57: 0.36 | M57: =IF(AND(A57<>"",LEFT(A57,3)<>"AV."),A57,M56) -> BOLSA N° #5
A58: TOTAL EXCEDENTES | B58: $ 1967.74 | M58: =IF(AND(A58<>"",LEFT(A58,3)<>"AV."),A58,M57) -> TOTAL EXCEDENTES
A59: TOTAL RENTA MENSUAL | B59: $ 1085.32 | M59: =IF(AND(A59<>"",LEFT(A59,3)<>"AV."),A59,M58) -> TOTAL RENTA MENSUAL
A60: TOTAL FACTURACIÓN | B60: $ 3053.06 | M60: =IF(AND(A60<>"",LEFT(A60,3)<>"AV."),A60,M59) -> TOTAL FACTURACIÓN

Sheet 02
A1: Column1 | B1: Column2 | C1: Column3 | D1: Column4 | E1: Column5 | F1: Column6 | G1: Column7 | H1: Column8 | I1: Column9 | J1: Column10
A2: [image] | B2: CUADRO DE CONSUMO DEL CONTRATO 276580 PERIODO 2026 MES DE MARZO | J2: =IF(AND(A2<>"",LEFT(A2,3)<>"AV."),A2,J1) -> [image]
A3: HOTELERA COSTA DEL PACIFICO S.A. - | B3: (C20297885538) | J3: =IF(AND(A3<>"",LEFT(A3,3)<>"AV."),A3,J2) -> HOTELERA COSTA DEL PACIFICO S.A. -
A4: EQUIPO | B4: FORMATOS | J4: =IF(AND(A4<>"",LEFT(A4,3)<>"AV."),A4,J3) -> EQUIPO
A5: GRUPO: SIN BOLSA SEGUN CONTRATO VIGENTE | J5: =IF(AND(A5<>"",LEFT(A5,3)<>"AV."),A5,J4) -> GRUPO: SIN BOLSA SEGUN CONTRATO VIGENTE
A6: X3B7003661 - WF-C5790 | B6: A4BN | C6: 13075 | D6: 20147 | E6: 7072 | F6: 0 | G6: 7072 | H6: 0.0168 | I6: 118.81 | J6: =IF(AND(A6<>"",LEFT(A6,3)<>"AV."),A6,J5) -> X3B7003661 - WF-C5790
A7: AV. VIA CENTRAL 190 CENTRO EMPRESARIAL | B7: A3BN | C7: 0 | D7: 0 | E7: 0 | F7: 0 | G7: 0 | H7: 0.0301 | I7: 0 | J7: =IF(AND(A7<>"",LEFT(A7,3)<>"AV."),A7,J6) -> X3B7003661 - WF-C5790
B8: A4CL | C8: 6457 | D8: 13206 | E8: 6749 | F8: 0 | G8: 6749 | H8: 0.0472 | I8: 318.55 | J8: =IF(AND(A8<>"",LEFT(A8,3)<>"AV."),A8,J7) -> X3B7003661 - WF-C5790
B9: A3CL | C9: 0 | D9: 0 | E9: 0 | F9: 0 | G9: 0 | H9: 0.0906 | I9: 0 | J9: =IF(AND(A9<>"",LEFT(A9,3)<>"AV."),A9,J8) -> X3B7003661 - WF-C5790
B10: TOTALES | C10: 19532 | D10: 33353 | J10: =IF(AND(A10<>"",LEFT(A10,3)<>"AV."),A10,J9) -> X3B7003661 - WF-C5790
A11: 9502370Y - MX-M3070 - Bolsa 1 | B11: A4BN | C11: 57 | D11: 8633 | E11: 8576 | F11: 0 | G11: 0 | H11: 0.0168 | I11: 0 | J11: =IF(AND(A11<>"",LEFT(A11,3)<>"AV."),A11,J10) -> 9502370Y - MX-M3070 - Bolsa 1
A12: AV. SANTO TORIBIO NRO 173 URB ROSARIO (VIA CENTRO | B12: A3BN | C12: 0 | D12: 0 | E12: 0 | F12: 0 | G12: 0 | H12: 0.0301 | I12: 0 | J12: =IF(AND(A12<>"",LEFT(A12,3)<>"AV."),A12,J11) -> 9502370Y - MX-M3070 - Bolsa 1
B13: A4CL | C13: 0 | D13: 0 | E13: 0 | F13: 0 | G13: 0 | H13: 0.0472 | I13: 0 | J13: =IF(AND(A13<>"",LEFT(A13,3)<>"AV."),A13,J12) -> 9502370Y - MX-M3070 - Bolsa 1
B14: A3CL | C14: 0 | D14: 0 | E14: 0 | F14: 0 | G14: 0 | H14: 0.0906 | I14: 0 | J14: =IF(AND(A14<>"",LEFT(A14,3)<>"AV."),A14,J13) -> 9502370Y - MX-M3070 - Bolsa 1
B15: TOTALES | C15: 57 | D15: 8633 | J15: =IF(AND(A15<>"",LEFT(A15,3)<>"AV."),A15,J14) -> 9502370Y - MX-M3070 - Bolsa 1
A16: QFX06245 - IR-1730 - Bolsa 1 | B16: A4BN | C16: 156715 | D16: 159127 | E16: 2412 | F16: 0 | G16: 0 | H16: 0.0168 | I16: 0 | J16: =IF(AND(A16<>"",LEFT(A16,3)<>"AV."),A16,J15) -> QFX06245 - IR-1730 - Bolsa 1
A17: AV. SANTO TORIBIO NRO 173 URB ROSARIO (VIA CENTRO | B17: A3BN | C17: 0 | D17: 0 | E17: 0 | F17: 0 | G17: 0 | H17: 0.0301 | I17: 0 | J17: =IF(AND(A17<>"",LEFT(A17,3)<>"AV."),A17,J16) -> QFX06245 - IR-1730 - Bolsa 1
B18: A4CL | C18: 0 | D18: 0 | E18: 0 | F18: 0 | G18: 0 | H18: 0.0472 | I18: 0 | J18: =IF(AND(A18<>"",LEFT(A18,3)<>"AV."),A18,J17) -> QFX06245 - IR-1730 - Bolsa 1
B19: A3CL | C19: 0 | D19: 0 | E19: 0 | F19: 0 | G19: 0 | H19: 0.0906 | I19: 0 | J19: =IF(AND(A19<>"",LEFT(A19,3)<>"AV."),A19,J18) -> QFX06245 - IR-1730 - Bolsa 1
B20: TOTALES | C20: 156715 | D20: 159127 | J20: =IF(AND(A20<>"",LEFT(A20,3)<>"AV."),A20,J19) -> QFX06245 - IR-1730 - Bolsa 1
A21: X3B7002433 - WF-C5790 - Bolsa 2 | B21: A4BN | C21: 83734 | D21: 84608 | E21: 874 | F21: 0 | G21: 0 | H21: 0.0168 | I21: 0 | J21: =IF(AND(A21<>"",LEFT(A21,3)<>"AV."),A21,J20) -> X3B7002433 - WF-C5790 - Bolsa 2
A22: AV. VIA CENTRAL 190 CENTRO EMPRESARIAL | B22: A3BN | C22: 0 | D22: 0 | E22: 0 | F22: 0 | G22: 0 | H22: 0.0301 | I22: 0 | J22: =IF(AND(A22<>"",LEFT(A22,3)<>"AV."),A22,J21) -> X3B7002433 - WF-C5790 - Bolsa 2
B23: A4CL | C23: 21349 | D23: 25358 | E23: 4009 | F23: 0 | G23: 0 | H23: 0.0472 | I23: 0 | J23: =IF(AND(A23<>"",LEFT(A23,3)<>"AV."),A23,J22) -> X3B7002433 - WF-C5790 - Bolsa 2
B24: A3CL | C24: 0 | D24: 0 | E24: 0 | F24: 0 | G24: 0 | H24: 0.0906 | I24: 0 | J24: =IF(AND(A24<>"",LEFT(A24,3)<>"AV."),A24,J23) -> X3B7002433 - WF-C5790 - Bolsa 2
B25: TOTALES | C25: 105083 | D25: 109966 | J25: =IF(AND(A25<>"",LEFT(A25,3)<>"AV."),A25,J24) -> X3B7002433 - WF-C5790 - Bolsa 2
A26: X3B7003876 - WF-C5790 - Bolsa 2 | B26: A4BN | C26: 58830 | D26: 59665 | E26: 835 | F26: 0 | G26: 0 | H26: 0.0168 | I26: 0 | J26: =IF(AND(A26<>"",LEFT(A26,3)<>"AV."),A26,J25) -> X3B7003876 - WF-C5790 - Bolsa 2
A27: AV. VIA CENTRAL 190 CENTRO EMPRESARIAL | B27: A3BN | C27: 0 | D27: 0 | E27: 0 | F27: 0 | G27: 0 | H27: 0.0301 | I27: 0 | J27: =IF(AND(A27<>"",LEFT(A27,3)<>"AV."),A27,J26) -> X3B7003876 - WF-C5790 - Bolsa 2
B28: A4CL | C28: 35550 | D28: 36043 | E28: 493 | F28: 0 | G28: 0 | H28: 0.0472 | I28: 0 | J28: =IF(AND(A28<>"",LEFT(A28,3)<>"AV."),A28,J27) -> X3B7003876 - WF-C5790 - Bolsa 2
B29: A3CL | C29: 0 | D29: 0 | E29: 0 | F29: 0 | G29: 0 | H29: 0.0906 | I29: 0 | J29: =IF(AND(A29<>"",LEFT(A29,3)<>"AV."),A29,J28) -> X3B7003876 - WF-C5790 - Bolsa 2
B30: TOTALES | C30: 94380 | D30: 95708 | J30: =IF(AND(A30<>"",LEFT(A30,3)<>"AV."),A30,J29) -> X3B7003876 - WF-C5790 - Bolsa 2
A31: X3B7003659 - WF-C5790 - Bolsa 2 | B31: A4BN | C31: 15527 | D31: 15992 | E31: 465 | F31: 0 | G31: 0 | H31: 0.0168 | I31: 0 | J31: =IF(AND(A31<>"",LEFT(A31,3)<>"AV."),A31,J30) -> X3B7003659 - WF-C5790 - Bolsa 2
A32: AV. SANTO TORIBIO NRO 173 URB ROSARIO (VIA CENTRO | B32: A3BN | C32: 0 | D32: 0 | E32: 0 | F32: 0 | G32: 0 | H32: 0.0301 | I32: 0 | J32: =IF(AND(A32<>"",LEFT(A32,3)<>"AV."),A32,J31) -> X3B7003659 - WF-C5790 - Bolsa 2
B33: A4CL | C33: 14379 | D33: 15205 | E33: 826 | F33: 0 | G33: 0 | H33: 0.0472 | I33: 0 | J33: =IF(AND(A33<>"",LEFT(A33,3)<>"AV."),A33,J32) -> X3B7003659 - WF-C5790 - Bolsa 2
B34: A3CL | C34: 0 | D34: 0 | E34: 0 | F34: 0 | G34: 0 | H34: 0.0906 | I34: 0 | J34: =IF(AND(A34<>"",LEFT(A34,3)<>"AV."),A34,J33) -> X3B7003659 - WF-C5790 - Bolsa 2
B35: TOTALES | C35: 29906 | D35: 31197 | J35: =IF(AND(A35<>"",LEFT(A35,3)<>"AV."),A35,J34) -> X3B7003659 - WF-C5790 - Bolsa 2
A36: X3B7003660 - WF-C5790 - Bolsa 2 | B36: A4BN | C36: 83188 | D36: 83943 | E36: 755 | F36: 0 | G36: 0 | H36: 0.0168 | I36: 0 | J36: =IF(AND(A36<>"",LEFT(A36,3)<>"AV."),A36,J35) -> X3B7003660 - WF-C5790 - Bolsa 2
A37: AV. SANTO TORIBIO NRO 173 URB ROSARIO (VIA CENTRO | B37: A3BN | C37: 0 | D37: 0 | E37: 0 | F37: 0 | G37: 0 | H37: 0.0301 | I37: 0 | J37: =IF(AND(A37<>"",LEFT(A37,3)<>"AV."),A37,J36) -> X3B7003660 - WF-C5790 - Bolsa 2
B38: A4CL | C38: 18110 | D38: 20208 | E38: 2098 | F38: 0 | G38: 0 | H38: 0.0472 | I38: 0 | J38: =IF(AND(A38<>"",LEFT(A38,3)<>"AV."),A38,J37) -> X3B7003660 - WF-C5790 - Bolsa 2
B39: A3CL | C39: 0 | D39: 0 | E39: 0 | F39: 0 | G39: 0 | H39: 0.0906 | I39: 0 | J39: =IF(AND(A39<>"",LEFT(A39,3)<>"AV."),A39,J38) -> X3B7003660 - WF-C5790 - Bolsa 2
B40: TOTALES | C40: 101298 | D40: 104151 | J40: =IF(AND(A40<>"",LEFT(A40,3)<>"AV."),A40,J39) -> X3B7003660 - WF-C5790 - Bolsa 2
A41: X3B7003671 - WF-C5790 - Bolsa 2 | B41: A4BN | C41: 9497 | D41: 9830 | E41: 333 | F41: 0 | G41: 0 | H41: 0.0168 | I41: 0 | J41: =IF(AND(A41<>"",LEFT(A41,3)<>"AV."),A41,J40) -> X3B7003671 - WF-C5790 - Bolsa 2
A42: AV. SANTO TORIBIO NRO 173 URB ROSARIO (VIA CENTRO | B42: A3BN | C42: 0 | D42: 0 | E42: 0 | F42: 0 | G42: 0 | H42: 0.0301 | I42: 0 | J42: =IF(AND(A42<>"",LEFT(A42,3)<>"AV."),A42,J41) -> X3B7003671 - WF-C5790 - Bolsa 2
B43: A4CL | C43: 4511 | D43: 5062 | E43: 551 | F43: 0 | G43: 0 | H43: 0.0472 | I43: 0 | J43: =IF(AND(A43<>"",LEFT(A43,3)<>"AV."),A43,J42) -> X3B7003671 - WF-C5790 - Bolsa 2
B44: A3CL | C44: 0 | D44: 0 | E44: 0 | F44: 0 | G44: 0 | H44: 0.0906 | I44: 0 | J44: =IF(AND(A44<>"",LEFT(A44,3)<>"AV."),A44,J43) -> X3B7003671 - WF-C5790 - Bolsa 2
B45: TOTALES | C45: 14008 | D45: 14892 | J45: =IF(AND(A45<>"",LEFT(A45,3)<>"AV."),A45,J44) -> X3B7003671 - WF-C5790 - Bolsa 2
A46: X3B7003703 - WF-C5790 - Bolsa 2 | B46: A4BN | C46: 85135 | D46: 88863 | E46: 3728 | F46: 0 | G46: 0 | H46: 0.0168 | I46: 0 | J46: =IF(AND(A46<>"",LEFT(A46,3)<>"AV."),A46,J45) -> X3B7003703 - WF-C5790 - Bolsa 2
A47: AV. SANTO TORIBIO NRO 173 URB ROSARIO (VIA CENTRO | B47: A3BN | C47: 0 | D47: 0 | E47: 0 | F47: 0 | G47: 0 | H47: 0.0301 | I47: 0 | J47: =IF(AND(A47<>"",LEFT(A47,3)<>"AV."),A47,J46) -> X3B7003703 - WF-C5790 - Bolsa 2
B48: A4CL | C48: 9094 | D48: 9572 | E48: 478 | F48: 0 | G48: 0 | H48: 0.0472 | I48: 0 | J48: =IF(AND(A48<>"",LEFT(A48,3)<>"AV."),A48,J47) -> X3B7003703 - WF-C5790 - Bolsa 2
B49: A3CL | C49: 0 | D49: 0 | E49: 0 | F49: 0 | G49: 0 | H49: 0.0906 | I49: 0 | J49: =IF(AND(A49<>"",LEFT(A49,3)<>"AV."),A49,J48) -> X3B7003703 - WF-C5790 - Bolsa 2
B50: TOTALES | C50: 94229 | D50: 98435 | J50: =IF(AND(A50<>"",LEFT(A50,3)<>"AV."),A50,J49) -> X3B7003703 - WF-C5790 - Bolsa 2
A51: X3B7003711 - WF-C5790 - Bolsa 2 | B51: A4BN | C51: 129700 | D51: 131931 | E51: 2231 | F51: 0 | G51: 0 | H51: 0.0168 | I51: 0 | J51: =IF(AND(A51<>"",LEFT(A51,3)<>"AV."),A51,J50) -> X3B7003711 - WF-C5790 - Bolsa 2
A52: AV. SANTO TORIBIO NRO 173 URB ROSARIO (VIA CENTRO | B52: A3BN | C52: 0 | D52: 0 | E52: 0 | F52: 0 | G52: 0 | H52: 0.0301 | I52: 0 | J52: =IF(AND(A52<>"",LEFT(A52,3)<>"AV."),A52,J51) -> X3B7003711 - WF-C5790 - Bolsa 2
B53: A4CL | C53: 23452 | D53: 24235 | E53: 783 | F53: 0 | G53: 0 | H53: 0.0472 | I53: 0 | J53: =IF(AND(A53<>"",LEFT(A53,3)<>"AV."),A53,J52) -> X3B7003711 - WF-C5790 - Bolsa 2
B54: A3CL | C54: 0 | D54: 0 | E54: 0 | F54: 0 | G54: 0 | H54: 0.0906 | I54: 0 | J54: =IF(AND(A54<>"",LEFT(A54,3)<>"AV."),A54,J53) -> X3B7003711 - WF-C5790 - Bolsa 2
B55: TOTALES | C55: 153152 | D55: 156166 | J55: =IF(AND(A55<>"",LEFT(A55,3)<>"AV."),A55,J54) -> X3B7003711 - WF-C5790 - Bolsa 2
A56: X3B7003739 - WF-C5790 - Bolsa 2 | B56: A4BN | C56: 30199 | D56: 30545 | E56: 346 | F56: 0 | G56: 0 | H56: 0.0168 | I56: 0 | J56: =IF(AND(A56<>"",LEFT(A56,3)<>"AV."),A56,J55) -> X3B7003739 - WF-C5790 - Bolsa 2
A57: AV. SANTO TORIBIO NRO 173 URB ROSARIO (VIA CENTRO | B57: A3BN | C57: 0 | D57: 0 | E57: 0 | F57: 0 | G57: 0 | H57: 0.0301 | I57: 0 | J57: =IF(AND(A57<>"",LEFT(A57,3)<>"AV."),A57,J56) -> X3B7003739 - WF-C5790 - Bolsa 2
B58: A4CL | C58: 34833 | D58: 35045 | E58: 212 | F58: 0 | G58: 0 | H58: 0.0472 | I58: 0 | J58: =IF(AND(A58<>"",LEFT(A58,3)<>"AV."),A58,J57) -> X3B7003739 - WF-C5790 - Bolsa 2
B59: A3CL | C59: 0 | D59: 0 | E59: 0 | F59: 0 | G59: 0 | H59: 0.0906 | I59: 0 | J59: =IF(AND(A59<>"",LEFT(A59,3)<>"AV."),A59,J58) -> X3B7003739 - WF-C5790 - Bolsa 2
B60: TOTALES | C60: 65032 | D60: 65590 | J60: =IF(AND(A60<>"",LEFT(A60,3)<>"AV."),A60,J59) -> X3B7003739 - WF-C5790 - Bolsa 2
A61: XBJZ017602 - WF-C5890 - Bolsa 3 | B61: A4BN | C61: 28313 | D61: 28834 | E61: 521 | F61: 0 | G61: 0 | H61: 0.0168 | I61: 0 | J61: =IF(AND(A61<>"",LEFT(A61,3)<>"AV."),A61,J60) -> XBJZ017602 - WF-C5890 - Bolsa 3
A62: AV. SANTO TORIBIO NRO 173 URB ROSARIO (VIA CENTRO | B62: A3BN | C62: 0 | D62: 0 | E62: 0 | F62: 0 | G62: 0 | H62: 0.0301 | I62: 0 | J62: =IF(AND(A62<>"",LEFT(A62,3)<>"AV."),A62,J61) -> XBJZ017602 - WF-C5890 - Bolsa 3
B63: A4CL | C63: 34374 | D63: 35704 | E63: 1330 | F63: 0 | G63: 0 | H63: 0.0472 | I63: 0 | J63: =IF(AND(A63<>"",LEFT(A63,3)<>"AV."),A63,J62) -> XBJZ017602 - WF-C5890 - Bolsa 3
B64: A3CL | C64: 0 | D64: 0 | E64: 0 | F64: 0 | G64: 0 | H64: 0.0906 | I64: 0 | J64: =IF(AND(A64<>"",LEFT(A64,3)<>"AV."),A64,J63) -> XBJZ017602 - WF-C5890 - Bolsa 3
B65: TOTALES | C65: 62687 | D65: 64538 | J65: =IF(AND(A65<>"",LEFT(A65,3)<>"AV."),A65,J64) -> XBJZ017602 - WF-C5890 - Bolsa 3
A66: XBJZ017603 - WF-C5890 - Bolsa 3 | B66: A4BN | C66: 3603 | D66: 4044 | E66: 441 | F66: 0 | G66: 0 | H66: 0.0168 | I66: 0 | J66: =IF(AND(A66<>"",LEFT(A66,3)<>"AV."),A66,J65) -> XBJZ017603 - WF-C5890 - Bolsa 3
A67: AV. SANTO TORIBIO NRO 173 URB ROSARIO (VIA CENTRO | B67: A3BN | C67: 0 | D67: 0 | E67: 0 | F67: 0 | G67: 0 | H67: 0.0301 | I67: 0 | J67: =IF(AND(A67<>"",LEFT(A67,3)<>"AV."),A67,J66) -> XBJZ017603 - WF-C5890 - Bolsa 3
B68: A4CL | C68: 3848 | D68: 4293 | E68: 445 | F68: 0 | G68: 0 | H68: 0.0472 | I68: 0 | J68: =IF(AND(A68<>"",LEFT(A68,3)<>"AV."),A68,J67) -> XBJZ017603 - WF-C5890 - Bolsa 3
B69: A3CL | C69: 0 | D69: 0 | E69: 0 | F69: 0 | G69: 0 | H69: 0.0906 | I69: 0 | J69: =IF(AND(A69<>"",LEFT(A69,3)<>"AV."),A69,J68) -> XBJZ017603 - WF-C5890 - Bolsa 3
B70: TOTALES | C70: 7451 | D70: 8337 | J70: =IF(AND(A70<>"",LEFT(A70,3)<>"AV."),A70,J69) -> XBJZ017603 - WF-C5890 - Bolsa 3
A71: XBJZ017266 - WF-C5890 - Bolsa 3 | B71: A4BN | C71: 6445 | D71: 7222 | E71: 777 | F71: 0 | G71: 0 | H71: 0.0168 | I71: 0 | J71: =IF(AND(A71<>"",LEFT(A71,3)<>"AV."),A71,J70) -> XBJZ017266 - WF-C5890 - Bolsa 3
A72: AV. SANTO TORIBIO NRO 173 URB ROSARIO (VIA CENTRO | B72: A3BN | C72: 0 | D72: 0 | E72: 0 | F72: 0 | G72: 0 | H72: 0.0301 | I72: 0 | J72: =IF(AND(A72<>"",LEFT(A72,3)<>"AV."),A72,J71) -> XBJZ017266 - WF-C5890 - Bolsa 3
B73: A4CL | C73: 24340 | D73: 28775 | E73: 4435 | F73: 0 | G73: 0 | H73: 0.0472 | I73: 0 | J73: =IF(AND(A73<>"",LEFT(A73,3)<>"AV."),A73,J72) -> XBJZ017266 - WF-C5890 - Bolsa 3
B74: A3CL | C74: 0 | D74: 0 | E74: 0 | F74: 0 | G74: 0 | H74: 0.0906 | I74: 0 | J74: =IF(AND(A74<>"",LEFT(A74,3)<>"AV."),A74,J73) -> XBJZ017266 - WF-C5890 - Bolsa 3
B75: TOTALES | C75: 30785 | D75: 35997 | J75: =IF(AND(A75<>"",LEFT(A75,3)<>"AV."),A75,J74) -> XBJZ017266 - WF-C5890 - Bolsa 3
A76: XBJZ021772 - WF-C5890 - Bolsa 3 | B76: A4BN | C76: 1638 | D76: 2080 | E76: 442 | F76: 0 | G76: 0 | H76: 0.0168 | I76: 0 | J76: =IF(AND(A76<>"",LEFT(A76,3)<>"AV."),A76,J75) -> XBJZ021772 - WF-C5890 - Bolsa 3
A77: AV. VIA CENTRAL 190 CENTRO EMPRESARIAL | B77: A3BN | C77: 0 | D77: 0 | E77: 0 | F77: 0 | G77: 0 | H77: 0.0301 | I77: 0 | J77: =IF(AND(A77<>"",LEFT(A77,3)<>"AV."),A77,J76) -> XBJZ021772 - WF-C5890 - Bolsa 3
B78: A4CL | C78: 1473 | D78: 2133 | E78: 660 | F78: 0 | G78: 0 | H78: 0.0472 | I78: 0 | J78: =IF(AND(A78<>"",LEFT(A78,3)<>"AV."),A78,J77) -> XBJZ021772 - WF-C5890 - Bolsa 3
B79: A3CL | C79: 0 | D79: 0 | E79: 0 | F79: 0 | G79: 0 | H79: 0.0906 | I79: 0 | J79: =IF(AND(A79<>"",LEFT(A79,3)<>"AV."),A79,J78) -> XBJZ021772 - WF-C5890 - Bolsa 3

Sheet 2026-3
A1: 46112 | B1: Marca | C1: Modelo | D1: S/N | E1: IP | F1: Observación | G1: Cantidad Impresoras | H1: Bolsa | I1: Formatos | J1: Contador Inicial | K1: Contador Final | L1: Consumo del Mes | M1: Volumen Maximo Establecido | N1: Volumen Excedente | O1: Precio | P1: Total | Q1: alquiler fijo | T1: centro costo | V1: Bolsa | W1: Formatos | X1: Volumen Maximo
B2: Canon | C2: IR-C3330 | D2: RJQ00596 | E2: 10.72.8.203 | F2: 2do Piso - Seguridad | G2: 1 | H2: Bolsa 5 | I2: A4BN | J2: =+SUMIFS('01'!$D:$D,'01'!$M:$M,$D$2&" - "&$C$2&" - "&$H$2,'01'!$C:$C,'2026-3'!$I2) -> 130708 | K2: =+SUMIFS('01'!$E:$E,'01'!$M:$M,$D$2&" - "&$C$2&" - "&$H$2,'01'!$C:$C,'2026-3'!$I2) -> 131063 | L2: =IF(K2-J2<=0,"0",K2-J2) -> 355 | M2: =SUMIFS(X:X,V:V,H$18,W:W,I2)/COUNTIF(H:H,H$18) -> 188 | N2: =IFERROR(+L2-M2,"") -> 167 | O2: =VALUE(+VLOOKUP(I2,'01'!C:K,9,FALSE)) -> 0.0168 | P2: =IFERROR(+N2*O2,"") -> 2.8056 | Q2: {=_xlfn._xlws.FILTER(SAP!$B$2,1)/COUNTA($G$2:$G$85)} -> 51.681905 | R2: =+SUM(P2:P5) -> -2.0712 | S2: 941231308 | T2: 408 | U2: 1 | V2: Bolsa 1 | W2: A4BN | X2: 13000
I3: A3BN | J3: =+SUMIFS('01'!$D:$D,'01'!$M:$M,$D$2&" - "&$C$2&" - "&$H$2,'01'!$C:$C,'2026-3'!$I3) -> 6966 | K3: =+SUMIFS('01'!$E:$E,'01'!$M:$M,$D$2&" - "&$C$2&" - "&$H$2,'01'!$C:$C,'2026-3'!$I3) -> 6966 | L3: =IF(K3-J3<=0,"0",K3-J3) -> 0 | M3: =SUMIFS(X:X,V:V,H$18,W:W,I3)/COUNTIF(H:H,H$18) -> 0 | N3: =IFERROR(+L3-M3,"") -> 0 | O3: =VALUE(+VLOOKUP(I3,'01'!C:K,9,FALSE)) -> 0.0301 | P3: =IFERROR(+N3*O3,"") -> 0 | V3: Bolsa 1 | W3: A3BN
I4: A4CL | J4: =+SUMIFS('01'!$D:$D,'01'!$M:$M,$D$2&" - "&$C$2&" - "&$H$2,'01'!$C:$C,'2026-3'!$I4) -> 187880 | K4: =+SUMIFS('01'!$E:$E,'01'!$M:$M,$D$2&" - "&$C$2&" - "&$H$2,'01'!$C:$C,'2026-3'!$I4) -> 188332 | L4: =IF(K4-J4<=0,"0",K4-J4) -> 452 | M4: =SUMIFS(X:X,V:V,H$18,W:W,I4)/COUNTIF(H:H,H$18) -> 563 | N4: =IFERROR(+L4-M4,"") -> -111 | O4: =VALUE(+VLOOKUP(I4,'01'!C:K,9,FALSE)) -> 0.0472 | P4: =IFERROR(+N4*O4,"") -> -5.2392 | V4: Bolsa 1 | W4: A4CL
I5: A3CL | J5: =+SUMIFS('01'!$D:$D,'01'!$M:$M,$D$2&" - "&$C$2&" - "&$H$2,'01'!$C:$C,'2026-3'!$I5) -> 6966 | K5: =+SUMIFS('01'!$E:$E,'01'!$M:$M,$D$2&" - "&$C$2&" - "&$H$2,'01'!$C:$C,'2026-3'!$I5) -> 6970 | L5: =IF(K5-J5<=0,"0",K5-J5) -> 4 | M5: =SUMIFS(X:X,V:V,H$18,W:W,I5)/COUNTIF(H:H,H$18) -> 0 | N5: =IFERROR(+L5-M5,"") -> 4 | O5: =VALUE(+VLOOKUP(I5,'01'!C:K,9,FALSE)) -> 0.0906 | P5: =IFERROR(+N5*O5,"") -> 0.3624 | V5: Bolsa 1 | W5: A3CL
C6: IR-1730 | D6: QFX06245 | E6: 10.72.8.215 | F6: 2do Piso - Oficina Auditor de Ingresos | G6: 1 | H6: Bolsa 1 | I6: A4BN | J6: =+SUMIFS('02'!C:C,'02'!J:J,D6&" - "&C6&" - "&H6,'02'!B:B,'2026-3'!$I6) -> 156715 | K6: =+SUMIFS('02'!D:D,'02'!J:J,D6&" - "&C6&" - "&H6,'02'!B:B,'2026-3'!$I6) -> 159127 | L6: =IF(K6-J6<=0,"0",K6-J6) -> 2412 | M6: =SUMIFS(X:X,V:V,H6,W:W,I6)/COUNTIF(H:H,H6) -> 3250 | N6: =IFERROR(+L6-M6,"") -> -838 | O6: =VALUE(+VLOOKUP(I6,'01'!C:K,9,FALSE)) -> 0.0168 | P6: =+N6*O6 -> -14.0784 | Q6: {=_xlfn._xlws.FILTER(SAP!$B$2,1)/COUNTA($G$2:$G$85)} -> 51.681905 | R6: =+SUM(P6:P9) -> -14.0784 | S6: 941231308 | T6: 403 | U6: 2 | V6: Bolsa 2 | W6: A4BN | X6: 1504 | Y6: =+COUNTIF(H:H,V6) -> 8
I7: A3BN | J7: =+SUMIFS('02'!C:C,'02'!J:J,D6&" - "&C6&" - "&H6,'02'!B:B,'2026-3'!$I7) -> 0 | K7: =+SUMIFS('02'!D:D,'02'!J:J,D6&" - "&C6&" - "&H6,'02'!B:B,'2026-3'!$I7) -> 0 | L7: =IF(K7-J7<=0,"0",K7-J7) -> 0 | N7: =IFERROR(+L7-M7,"") -> 0 | O7: =VALUE(+VLOOKUP(I7,'01'!C:K,9,FALSE)) -> 0.0301 | P7: =+N7*O7 -> 0 | V7: Bolsa 2 | W7: A3BN
I8: A4CL | J8: =+SUMIFS('02'!C:C,'02'!J:J,D6&" - "&C6&" - "&H6,'02'!B:B,'2026-3'!$I8) -> 0 | K8: =+SUMIFS('02'!D:D,'02'!J:J,D6&" - "&C6&" - "&H6,'02'!B:B,'2026-3'!$I8) -> 0 | L8: =IF(K8-J8<=0,"0",K8-J8) -> 0 | N8: =IFERROR(+L8-M8,"") -> 0 | O8: =VALUE(+VLOOKUP(I8,'01'!C:K,9,FALSE)) -> 0.0472 | P8: =+N8*O8 -> 0 | V8: Bolsa 2 | W8: A4CL | X8: 4504 | Y8: =+X6/Y6 -> 188
I9: A3CL | J9: =+SUMIFS('02'!C:C,'02'!J:J,D6&" - "&C6&" - "&H6,'02'!B:B,'2026-3'!$I9) -> 0 | K9: =+SUMIFS('02'!D:D,'02'!J:J,D6&" - "&C6&" - "&H6,'02'!B:B,'2026-3'!$I9) -> 0 | L9: =IF(K9-J9<=0,"0",K9-J9) -> 0 | N9: =IFERROR(+L9-M9,"") -> 0 | O9: =VALUE(+VLOOKUP(I9,'01'!C:K,9,FALSE)) -> 0.0906 | P9: =+N9*O9 -> 0 | V9: Bolsa 2 | W9: A3CL
C10: IR-1643 | D10: 35E33608 | E10: 10.72.8.211 | F10: 1er Piso - Front Desk - Recepción | G10: 1 | H10: Bolsa 1 | I10: A4BN | J10: =+SUMIFS('01'!$D:$D,'01'!$M:$M,$D$10&" - "&$C$10&" - "&$H$10,'01'!$C:$C,'2026-3'!$I10) -> 36 | K10: =+SUMIFS('01'!$E:$E,'01'!$M:$M,$D$10&" - "&$C$10&" - "&$H$10,'01'!$C:$C,'2026-3'!$I10) -> 23904 | L10: =IF(K10-J10<=0,"0",K10-J10) -> 23868 | M10: =SUMIFS(X:X,V:V,H10,W:W,I10)/COUNTIF(H:H,H10) -> 3250 | N10: =IFERROR(+L10-M10,"") -> 20618 | O10: =VALUE(+VLOOKUP(I10,'01'!C:K,9,FALSE)) -> 0.0168 | P10: =+N10*O10 -> 346.3824 | Q10: {=_xlfn._xlws.FILTER(SAP!$B$2,1)/COUNTA($G$2:$G$85)} -> 51.681905 | R10: =+SUM(P10:P13) -> 346.3824 | S10: 931221108 | T10: 101 | U10: 1 | V10: Bolsa 3 | W10: A4BN | X10: 1128
I11: A3BN | J11: =+SUMIFS('01'!$D:$D,'01'!$M:$M,$D$10&" - "&$C$10&" - "&$H$10,'01'!$C:$C,'2026-3'!$I11) -> 0 | K11: =+SUMIFS('01'!$E:$E,'01'!$M:$M,$D$10&" - "&$C$10&" - "&$H$10,'01'!$C:$C,'2026-3'!$I11) -> 0 | L11: =IF(K11-J11<=0,"0",K11-J11) -> 0 | N11: =IFERROR(+L11-M11,"") -> 0 | O11: =VALUE(+VLOOKUP(I11,'01'!C:K,9,FALSE)) -> 0.0301 | P11: =+N11*O11 -> 0 | V11: Bolsa 3 | W11: A3BN
I12: A4CL | J12: =+SUMIFS('01'!$D:$D,'01'!$M:$M,$D$10&" - "&$C$10&" - "&$H$10,'01'!$C:$C,'2026-3'!$I12) -> 0 | K12: =+SUMIFS('01'!$E:$E,'01'!$M:$M,$D$10&" - "&$C$10&" - "&$H$10,'01'!$C:$C,'2026-3'!$I12) -> 0 | L12: =IF(K12-J12<=0,"0",K12-J12) -> 0 | N12: =IFERROR(+L12-M12,"") -> 0 | O12: =VALUE(+VLOOKUP(I12,'01'!C:K,9,FALSE)) -> 0.0472 | P12: =+N12*O12 -> 0 | V12: Bolsa 3 | W12: A4CL | X12: 3378
I13: A3CL | J13: =+SUMIFS('01'!$D:$D,'01'!$M:$M,$D$10&" - "&$C$10&" - "&$H$10,'01'!$C:$C,'2026-3'!$I13) -> 0 | K13: =+SUMIFS('01'!$E:$E,'01'!$M:$M,$D$10&" - "&$C$10&" - "&$H$10,'01'!$C:$C,'2026-3'!$I13) -> 0 | L13: =IF(K13-J13<=0,"0",K13-J13) -> 0 | N13: =IFERROR(+L13-M13,"") -> 0 | O13: =VALUE(+VLOOKUP(I13,'01'!C:K,9,FALSE)) -> 0.0906 | P13: =+N13*O13 -> 0 | V13: Bolsa 3 | W13: A3CL
C14: IR-1643 | D14: 35E33607 | E14: 10.72.8.153 | F14: 1er Piso - Front Desk - Recepción | G14: 1 | H14: Bolsa 1 | I14: A4BN | J14: =+SUMIFS('01'!$D:$D,'01'!$M:$M,$D$14&" - "&$C$14&" - "&$H$14,'01'!$C:$C,'2026-3'!$I14) -> 6528 | K14: =+SUMIFS('01'!$E:$E,'01'!$M:$M,$D$14&" - "&$C$14&" - "&$H$14,'01'!$C:$C,'2026-3'!$I14) -> 14888 | L14: =IF(K14-J14<=0,"0",K14-J14) -> 8360 | M14: =SUMIFS(X:X,V:V,H14,W:W,I14)/COUNTIF(H:H,H14) -> 3250 | N14: =IFERROR(+L14-M14,"") -> 5110 | O14: =VALUE(+VLOOKUP(I14,'01'!C:K,9,FALSE)) -> 0.0168 | P14: =+N14*O14 -> 85.848 | Q14: {=_xlfn._xlws.FILTER(SAP!$B$2,1)/COUNTA($G$2:$G$85)} -> 51.681905 | R14: =+SUM(P14:P17) -> 85.848 | S14: 931221108 | T14: 101 | U14: 1 | V14: Bolsa 4 | W14: A4BN | X14: 188
I15: A3BN | J15: =+SUMIFS('01'!$D:$D,'01'!$M:$M,$D$14&" - "&$C$14&" - "&$H$14,'01'!$C:$C,'2026-3'!$I15) -> 0 | K15: =+SUMIFS('01'!$E:$E,'01'!$M:$M,$D$14&" - "&$C$14&" - "&$H$14,'01'!$C:$C,'2026-3'!$I15) -> 0 | L15: =IF(K15-J15<=0,"0",K15-J15) -> 0 | N15: =IFERROR(+L15-M15,"") -> 0 | O15: =VALUE(+VLOOKUP(I15,'01'!C:K,9,FALSE)) -> 0.0301 | P15: =+N15*O15 -> 0 | V15: Bolsa 4 | W15: A3BN
I16: A4CL | J16: =+SUMIFS('01'!$D:$D,'01'!$M:$M,$D$14&" - "&$C$14&" - "&$H$14,'01'!$C:$C,'2026-3'!$I16) -> 0 | K16: =+SUMIFS('01'!$E:$E,'01'!$M:$M,$D$14&" - "&$C$14&" - "&$H$14,'01'!$C:$C,'2026-3'!$I16) -> 0 | L16: =IF(K16-J16<=0,"0",K16-J16) -> 0 | N16: =IFERROR(+L16-M16,"") -> 0 | O16: =VALUE(+VLOOKUP(I16,'01'!C:K,9,FALSE)) -> 0.0472 | P16: =+N16*O16 -> 0 | V16: Bolsa 4 | W16: A4CL | X16: 563
I17: A3CL | J17: =+SUMIFS('01'!$D:$D,'01'!$M:$M,$D$14&" - "&$C$14&" - "&$H$14,'01'!$C:$C,'2026-3'!$I17) -> 0 | K17: =+SUMIFS('01'!$E:$E,'01'!$M:$M,$D$14&" - "&$C$14&" - "&$H$14,'01'!$C:$C,'2026-3'!$I17) -> 0 | L17: =IF(K17-J17<=0,"0",K17-J17) -> 0 | N17: =IFERROR(+L17-M17,"") -> 0 | O17: =VALUE(+VLOOKUP(I17,'01'!C:K,9,FALSE)) -> 0.0906 | P17: =+N17*O17 -> 0 | V17: Bolsa 4 | W17: A3CL
B18: Epson | C18: WF-C5790 | D18: X3B7002433 | E18: 10.72.8.191 | F18: 2do Piso - Oficina Banquetes | G18: 1 | H18: Bolsa 2 | I18: A4BN | J18: =+SUMIFS('02'!C:C,'02'!J:J,D18&" - "&C18&" - "&H18,'02'!B:B,'2026-3'!$I18) -> 83734 | K18: =+SUMIFS('02'!D:D,'02'!J:J,D18&" - "&C18&" - "&H18,'02'!B:B,'2026-3'!$I18) -> 84608 | L18: =IF(K18-J18<=0,"0",K18-J18) -> 874 | M18: =SUMIFS(X:X,V:V,H$18,W:W,I18)/COUNTIF(H:H,H$18) -> 188 | N18: =IFERROR(+L18-M18,"") -> 686 | O18: =VALUE(+VLOOKUP(I18,'01'!C:K,9,FALSE)) -> 0.0168 | P18: =+N18*O18 -> 11.5248 | Q18: {=_xlfn._xlws.FILTER(SAP!$B$2,1)/COUNTA($G$2:$G$85)} -> 51.681905 | R18: =+SUM(P18:P21) -> 174.176 | S18: 932341308 | T18: 207 | U18: 2 | V18: Bolsa 5 | W18: A4BN | X18: 188
I19: A3BN | J19: =+SUMIFS('02'!C:C,'02'!J:J,D18&" - "&C18&" - "&H18,'02'!B:B,'2026-3'!$I19) -> 0 | K19: =+SUMIFS('02'!D:D,'02'!J:J,D18&" - "&C18&" - "&H18,'02'!B:B,'2026-3'!$I19) -> 0 | L19: =IF(K19-J19<=0,"0",K19-J19) -> 0 | N19: =IFERROR(+L19-M19,"") -> 0 | O19: =VALUE(+VLOOKUP(I19,'01'!C:K,9,FALSE)) -> 0.0301 | P19: =+N19*O19 -> 0 | V19: Bolsa 5 | W19: A3BN
I20: A4CL | J20: =+SUMIFS('02'!C:C,'02'!J:J,D18&" - "&C18&" - "&H18,'02'!B:B,'2026-3'!$I20) -> 21349 | K20: =+SUMIFS('02'!D:D,'02'!J:J,D18&" - "&C18&" - "&H18,'02'!B:B,'2026-3'!$I20) -> 25358 | L20: =IF(K20-J20<=0,"0",K20-J20) -> 4009 | M20: =SUMIFS(X:X,V:V,$H18,W:W,I20)/COUNTIF(H:H,$H18) -> 563 | N20: =IFERROR(+L20-M20,"") -> 3446 | O20: =VALUE(+VLOOKUP(I20,'01'!C:K,9,FALSE)) -> 0.0472 | P20: =+N20*O20 -> 162.6512 | V20: Bolsa 5 | W20: A4CL | X20: 563
I21: A3CL | J21: =+SUMIFS('02'!C:C,'02'!J:J,D18&" - "&C18&" - "&H18,'02'!B:B,'2026-3'!$I21) -> 0 | K21: =+SUMIFS('02'!D:D,'02'!J:J,D18&" - "&C18&" - "&H18,'02'!B:B,'2026-3'!$I21) -> 0 | L21: =IF(K21-J21<=0,"0",K21-J21) -> 0 | N21: =IFERROR(+L21-M21,"") -> 0 | O21: =VALUE(+VLOOKUP(I21,'01'!C:K,9,FALSE)) -> 0.0906 | P21: =+N21*O21 -> 0 | V21: Bolsa 5 | W21: A3CL
C22: WF-C5790 | D22: X3B7003659 | E22: 10.72.8.197 | F22: 3er Piso - Reservas | G22: 1 | H22: Bolsa 2 | I22: A4BN | J22: =+SUMIFS('02'!C:C,'02'!J:J,D22&" - "&C22&" - "&H22,'02'!B:B,'2026-3'!$I22) -> 15527 | K22: =+SUMIFS('02'!D:D,'02'!J:J,D22&" - "&C22&" - "&H22,'02'!B:B,'2026-3'!$I22) -> 15992 | L22: =IF(K22-J22<=0,"0",K22-J22) -> 465 | M22: =SUMIFS(X:X,V:V,H22,W:W,I22)/COUNTIF(H:H,H22) -> 188 | N22: =IFERROR(+L22-M22,"") -> 277 | O22: =VALUE(+VLOOKUP(I22,'01'!C:K,9,FALSE)) -> 0.0168 | P22: =+N22*O22 -> 4.6536 | Q22: {=_xlfn._xlws.FILTER(SAP!$B$2,1)/COUNTA($G$2:$G$85)} -> 51.681905 | R22: =+SUM(P22:P25) -> 17.0672 | S22: 943331308 | T22: 406 | U22: 2
I23: A3BN | J23: =+SUMIFS('02'!C:C,'02'!J:J,D22&" - "&C22&" - "&H22,'02'!B:B,'2026-3'!$I23) -> 0 | K23: =+SUMIFS('02'!D:D,'02'!J:J,D22&" - "&C22&" - "&H22,'02'!B:B,'2026-3'!$I23) -> 0 | L23: =IF(K23-J23<=0,"0",K23-J23) -> 0 | N23: =IFERROR(+L23-M23,"") -> 0 | O23: =VALUE(+VLOOKUP(I23,'01'!C:K,9,FALSE)) -> 0.0301 | P23: =+N23*O23 -> 0
I24: A4CL | J24: =+SUMIFS('02'!C:C,'02'!J:J,D22&" - "&C22&" - "&H22,'02'!B:B,'2026-3'!$I24) -> 14379 | K24: =+SUMIFS('02'!D:D,'02'!J:J,D22&" - "&C22&" - "&H22,'02'!B:B,'2026-3'!$I24) -> 15205 | L24: =IF(K24-J24<=0,"0",K24-J24) -> 826 | M24: =SUMIFS(X:X,V:V,$H22,W:W,I24)/COUNTIF(H:H,$H22) -> 563 | N24: =IFERROR(+L24-M24,"") -> 263 | O24: =VALUE(+VLOOKUP(I24,'01'!C:K,9,FALSE)) -> 0.0472 | P24: =+N24*O24 -> 12.4136
I25: A3CL | J25: =+SUMIFS('02'!C:C,'02'!J:J,D22&" - "&C22&" - "&H22,'02'!B:B,'2026-3'!$I25) -> 0 | K25: =+SUMIFS('02'!D:D,'02'!J:J,D22&" - "&C22&" - "&H22,'02'!B:B,'2026-3'!$I25) -> 0 | L25: =IF(K25-J25<=0,"0",K25-J25) -> 0 | N25: =IFERROR(+L25-M25,"") -> 0 | O25: =VALUE(+VLOOKUP(I25,'01'!C:K,9,FALSE)) -> 0.0906 | P25: =+N25*O25 -> 0
C26: WF-C5790 | D26: X3B7003660 | E26: 10.72.8.204 | F26: 1er Piso - Room Service | G26: 1 | H26: Bolsa 2 | I26: A4BN | J26: =+SUMIFS('02'!C:C,'02'!J:J,D26&" - "&C26&" - "&H26,'02'!B:B,'2026-3'!$I26) -> 83188 | K26: =+SUMIFS('02'!D:D,'02'!J:J,D26&" - "&C26&" - "&H26,'02'!B:B,'2026-3'!$I26) -> 83943 | L26: =IF(K26-J26<=0,"0",K26-J26) -> 755 | M26: =SUMIFS(X:X,V:V,H26,W:W,I26)/COUNTIF(H:H,H26) -> 188 | N26: =IFERROR(+L26-M26,"") -> 567 | O26: =VALUE(+VLOOKUP(I26,'01'!C:K,9,FALSE)) -> 0.0168 | P26: =+N26*O26 -> 9.5256 | Q26: {=_xlfn._xlws.FILTER(SAP!$B$2,1)/COUNTA($G$2:$G$85)} -> 51.681905 | R26: =+SUM(P26:P29) -> 81.9776 | S26: 932341308 | T26: 206 | U26: 2
I27: A3BN | J27: =+SUMIFS('02'!C:C,'02'!J:J,D26&" - "&C26&" - "&H26,'02'!B:B,'2026-3'!$I27) -> 0 | K27: =+SUMIFS('02'!D:D,'02'!J:J,D26&" - "&C26&" - "&H26,'02'!B:B,'2026-3'!$I27) -> 0 | L27: =IF(K27-J27<=0,"0",K27-J27) -> 0 | N27: =IFERROR(+L27-M27,"") -> 0 | O27: =VALUE(+VLOOKUP(I27,'01'!C:K,9,FALSE)) -> 0.0301 | P27: =+N27*O27 -> 0 | W27: X3B7003661 - WF-C5790
I28: A4CL | J28: =+SUMIFS('02'!C:C,'02'!J:J,D26&" - "&C26&" - "&H26,'02'!B:B,'2026-3'!$I28) -> 18110 | K28: =+SUMIFS('02'!D:D,'02'!J:J,D26&" - "&C26&" - "&H26,'02'!B:B,'2026-3'!$I28) -> 20208 | L28: =IF(K28-J28<=0,"0",K28-J28) -> 2098 | M28: =SUMIFS(X:X,V:V,$H26,W:W,I28)/COUNTIF(H:H,$H26) -> 563 | N28: =IFERROR(+L28-M28,"") -> 1535 | O28: =VALUE(+VLOOKUP(I28,'01'!C:K,9,FALSE)) -> 0.0472 | P28: =+N28*O28 -> 72.452 | W28: =D30&" - "&C30&" - "&H30 -> X3B7003661 - WF-C5790 -
I29: A3CL | J29: =+SUMIFS('02'!C:C,'02'!J:J,D26&" - "&C26&" - "&H26,'02'!B:B,'2026-3'!$I29) -> 0 | K29: =+SUMIFS('02'!D:D,'02'!J:J,D26&" - "&C26&" - "&H26,'02'!B:B,'2026-3'!$I29) -> 0 | L29: =IF(K29-J29<=0,"0",K29-J29) -> 0 | N29: =IFERROR(+L29-M29,"") -> 0 | O29: =VALUE(+VLOOKUP(I29,'01'!C:K,9,FALSE)) -> 0.0906 | P29: =+N29*O29 -> 0
C30: WF-C5790 | D30: X3B7003661 | E30: 10.72.8.132 | F30: 1er Sotano - Steward - Limpieza | G30: 1 | I30: A4BN | J30: =+SUMIFS('02'!C:C,'02'!J:J,D30&" - "&C30,'02'!B:B,'2026-3'!$I30) -> 13075 | K30: =+SUMIFS('02'!D:D,'02'!J:J,D30&" - "&C30,'02'!B:B,'2026-3'!$I30) -> 20147 | L30: =IF(K30-J30<=0,"0",K30-J30) -> 7072 | M30: =IFERROR(+SUMIFS(X:X,V:V,H30,W:W,I30)/COUNTIF(H:H,H30),"") | N30: =IFERROR(+L30-M30,"") | O30: =VALUE(+VLOOKUP(I30,'01'!C:K,9,FALSE)) -> 0.0168 | P30: =+O30*L30 -> 118.8096 | Q30: {=_xlfn._xlws.FILTER(SAP!$B$2,1)/COUNTA($G$2:$G$85)} -> 51.681905 | R30: =SUM(P30:P33) -> 437.3624 | S30: 932341308 | T30: 200 | W30: =+EXACT(W28,W27) -> FALSE
I31: A3BN | J31: =+SUMIFS('02'!C:C,'02'!J:J,D30&" - "&C30,'02'!B:B,'2026-3'!$I31) -> 0 | K31: =+SUMIFS('02'!D:D,'02'!J:J,D30&" - "&C30,'02'!B:B,'2026-3'!$I31) -> 0 | L31: =IF(K31-J31<=0,"0",K31-J31) -> 0 | N31: =IFERROR(+L31-M31,"") -> 0 | O31: =VALUE(+VLOOKUP(I31,'01'!C:K,9,FALSE)) -> 0.0301 | P31: =+O31*L31 -> 0
I32: A4CL | J32: =+SUMIFS('02'!C:C,'02'!J:J,D30&" - "&C30,'02'!B:B,'2026-3'!$I32) -> 6457 | K32: =+SUMIFS('02'!D:D,'02'!J:J,D30&" - "&C30,'02'!B:B,'2026-3'!$I32) -> 13206 | L32: =IF(K32-J32<=0,"0",K32-J32) -> 6749 | M32: =IFERROR(+SUMIFS(X:X,V:V,$H30,W:W,I32)/COUNTIF(H:H,$H30),"") | N32: =IFERROR(+L32-M32,"") | O32: =VALUE(+VLOOKUP(I32,'01'!C:K,9,FALSE)) -> 0.0472 | P32: =+O32*L32 -> 318.5528
I33: A3CL | J33: =+SUMIFS('02'!C:C,'02'!J:J,D30&" - "&C30,'02'!B:B,'2026-3'!$I33) -> 0 | K33: =+SUMIFS('02'!D:D,'02'!J:J,D30&" - "&C30,'02'!B:B,'2026-3'!$I33) -> 0 | L33: =IF(K33-J33<=0,"0",K33-J33) -> 0 | N33: =IFERROR(+L33-M33,"") -> 0 | O33: =VALUE(+VLOOKUP(I33,'01'!C:K,9,FALSE)) -> 0.0906 | P33: =+O33*L33 -> 0
C34: WF-C5790 | D34: X3B7003671 | E34: 10.72.8.208 | F34: 1er Piso - Caja Lobby Bar | G34: 1 | H34: Bolsa 2 | I34: A4BN | J34: =+SUMIFS('02'!C:C,'02'!J:J,D34&" - "&C34&" - "&H34,'02'!B:B,'2026-3'!$I34) -> 9497 | K34: =+SUMIFS('02'!D:D,'02'!J:J,D34&" - "&C34&" - "&H34,'02'!B:B,'2026-3'!$I34) -> 9830 | L34: =IF(K34-J34<=0,"0",K34-J34) -> 333 | M34: =SUMIFS(X:X,V:V,H34,W:W,I34)/COUNTIF(H:H,H34) -> 188 | N34: =IFERROR(+L34-M34,"") -> 145 | O34: =VALUE(+VLOOKUP(I34,'01'!C:K,9,FALSE)) -> 0.0168 | P34: =+N34*O34 -> 2.436 | Q34: {=_xlfn._xlws.FILTER(SAP!$B$2,1)/COUNTA($G$2:$G$85)} -> 51.681905 | R34: =+SUM(P34:P37) -> 1.8696 | S34: 932341308 | T34: 204
I35: A3BN | J35: =+SUMIFS('02'!C:C,'02'!J:J,D34&" - "&C34&" - "&H34,'02'!B:B,'2026-3'!$I35) -> 0 | K35: =+SUMIFS('02'!D:D,'02'!J:J,D34&" - "&C34&" - "&H34,'02'!B:B,'2026-3'!$I35) -> 0 | L35: =IF(K35-J35<=0,"0",K35-J35) -> 0 | N35: =IFERROR(+L35-M35,"") -> 0 | O35: =VALUE(+VLOOKUP(I35,'01'!C:K,9,FALSE)) -> 0.0301 | P35: =+N35*O35 -> 0
I36: A4CL | J36: =+SUMIFS('02'!C:C,'02'!J:J,D34&" - "&C34&" - "&H34,'02'!B:B,'2026-3'!$I36) -> 4511 | K36: =+SUMIFS('02'!D:D,'02'!J:J,D34&" - "&C34&" - "&H34,'02'!B:B,'2026-3'!$I36) -> 5062 | L36: =IF(K36-J36<=0,"0",K36-J36) -> 551 | M36: =SUMIFS(X:X,V:V,$H34,W:W,I36)/COUNTIF(H:H,$H34) -> 563 | N36: =IFERROR(+L36-M36,"") -> -12 | O36: =VALUE(+VLOOKUP(I36,'01'!C:K,9,FALSE)) -> 0.0472 | P36: =+N36*O36 -> -0.5664
I37: A3CL | J37: =+SUMIFS('02'!C:C,'02'!J:J,D34&" - "&C34&" - "&H34,'02'!B:B,'2026-3'!$I37) -> 0 | K37: =+SUMIFS('02'!D:D,'02'!J:J,D34&" - "&C34&" - "&H34,'02'!B:B,'2026-3'!$I37) -> 0 | L37: =IF(K37-J37<=0,"0",K37-J37) -> 0 | N37: =IFERROR(+L37-M37,"") -> 0 | O37: =VALUE(+VLOOKUP(I37,'01'!C:K,9,FALSE)) -> 0.0906 | P37: =+N37*O37 -> 0
C38: WF-C5790 | D38: X3B7003703 | E38: 10.9.10.153 | F38: 1er Piso Gym | G38: 1 | H38: Bolsa 2 | I38: A4BN | J38: =+SUMIFS('02'!C:C,'02'!J:J,D38&" - "&C38&" - "&H38,'02'!B:B,'2026-3'!$I38) -> 85135 | K38: =+SUMIFS('02'!D:D,'02'!J:J,D38&" - "&C38&" - "&H38,'02'!B:B,'2026-3'!$I38) -> 88863 | L38: =IF(K38-J38<=0,"0",K38-J38) -> 3728 | M38: =1504/COUNTIF(H:H,"Bolsa 2") -> 188 | N38: =IFERROR(+L38-M38,"") -> 3540 | O38: =VALUE(+VLOOKUP(I38,'01'!C:K,9,FALSE)) -> 0.0168 | P38: =+N38*O38 -> 59.472 | Q38: {=_xlfn._xlws.FILTER(SAP!$B$2,1)/COUNTA($G$2:$G$85)} -> 51.681905 | R38: =+SUM(P38:P41) -> 55.46 | S38: 933441108 | T38: 304
I39: A3BN | J39: =+SUMIFS('02'!C:C,'02'!J:J,D38&" - "&C38&" - "&H38,'02'!B:B,'2026-3'!$I39) -> 0 | K39: =+SUMIFS('02'!D:D,'02'!J:J,D38&" - "&C38&" - "&H38,'02'!B:B,'2026-3'!$I39) -> 0 | L39: =IF(K39-J39<=0,"0",K39-J39) -> 0 | N39: =IFERROR(+L39-M39,"") -> 0 | O39: =VALUE(+VLOOKUP(I39,'01'!C:K,9,FALSE)) -> 0.0301 | P39: =+N39*O39 -> 0
I40: A4CL | J40: =+SUMIFS('02'!C:C,'02'!J:J,D38&" - "&C38&" - "&H38,'02'!B:B,'2026-3'!$I40) -> 9094 | K40: =+SUMIFS('02'!D:D,'02'!J:J,D38&" - "&C38&" - "&H38,'02'!B:B,'2026-3'!$I40) -> 9572 | L40: =IF(K40-J40<=0,"0",K40-J40) -> 478 | M40: =SUMIFS(X:X,V:V,$H38,W:W,I40)/COUNTIF(H:H,$H38) -> 563 | N40: =IFERROR(+L40-M40,"") -> -85 | O40: =VALUE(+VLOOKUP(I40,'01'!C:K,9,FALSE)) -> 0.0472 | P40: =+N40*O40 -> -4.012
I41: A3CL | J41: =+SUMIFS('02'!C:C,'02'!J:J,D38&" - "&C38&" - "&H38,'02'!B:B,'2026-3'!$I41) -> 0 | K41: =+SUMIFS('02'!D:D,'02'!J:J,D38&" - "&C38&" - "&H38,'02'!B:B,'2026-3'!$I41) -> 0 | L41: =IF(K41-J41<=0,"0",K41-J41) -> 0 | N41: =IFERROR(+L41-M41,"") -> 0 | O41: =VALUE(+VLOOKUP(I41,'01'!C:K,9,FALSE)) -> 0.0906 | P41: =+N41*O41 -> 0
C42: WF-C5790 | D42: X3B7003711 | E42: 10.72.8.205 | F42: 1er Piso - Recepción - Back Office | G42: 1 | H42: Bolsa 2 | I42: A4BN | J42: =+SUMIFS('02'!C:C,'02'!J:J,D42&" - "&C42&" - "&H42,'02'!B:B,'2026-3'!$I42) -> 129700 | K42: =+SUMIFS('02'!D:D,'02'!J:J,D42&" - "&C42&" - "&H42,'02'!B:B,'2026-3'!$I42) -> 131931 | L42: =IF(K42-J42<=0,"0",K42-J42) -> 2231 | M42: =SUMIFS(X:X,V:V,H42,W:W,I42)/COUNTIF(H:H,H42) -> 188 | N42: =IFERROR(+L42-M42,"") -> 2043 | O42: =VALUE(+VLOOKUP(I42,'01'!C:K,9,FALSE)) -> 0.0168 | P42: =+N42*O42 -> 34.3224 | Q42: {=_xlfn._xlws.FILTER(SAP!$B$2,1)/COUNTA($G$2:$G$85)} -> 51.681905 | R42: =+SUM(P42:P45) -> 44.7064 | S42: 931221108 | T42: 101 | U42: =13075-20147 -> -7072
I43: A3BN | J43: =+SUMIFS('02'!C:C,'02'!J:J,D42&" - "&C42&" - "&H42,'02'!B:B,'2026-3'!$I43) -> 0 | K43: =+SUMIFS('02'!D:D,'02'!J:J,D42&" - "&C42&" - "&H42,'02'!B:B,'2026-3'!$I43) -> 0 | L43: =IF(K43-J43<=0,"0",K43-J43) -> 0 | N43: =IFERROR(+L43-M43,"") -> 0 | O43: =VALUE(+VLOOKUP(I43,'01'!C:K,9,FALSE)) -> 0.0301 | P43: =+N43*O43 -> 0
I44: A4CL | J44: =+SUMIFS('02'!C:C,'02'!J:J,D42&" - "&C42&" - "&H42,'02'!B:B,'2026-3'!$I44) -> 23452 | K44: =+SUMIFS('02'!D:D,'02'!J:J,D42&" - "&C42&" - "&H42,'02'!B:B,'2026-3'!$I44) -> 24235 | L44: =IF(K44-J44<=0,"0",K44-J44) -> 783 | M44: =SUMIFS(X:X,V:V,$H42,W:W,I44)/COUNTIF(H:H,$H42) -> 563 | N44: =IFERROR(+L44-M44,"") -> 220 | O44: =VALUE(+VLOOKUP(I44,'01'!C:K,9,FALSE)) -> 0.0472 | P44: =+N44*O44 -> 10.384
I45: A3CL | J45: =+SUMIFS('02'!C:C,'02'!J:J,D42&" - "&C42&" - "&H42,'02'!B:B,'2026-3'!$I45) -> 0 | K45: =+SUMIFS('02'!D:D,'02'!J:J,D42&" - "&C42&" - "&H42,'02'!B:B,'2026-3'!$I45) -> 0 | L45: =IF(K45-J45<=0,"0",K45-J45) -> 0 | N45: =IFERROR(+L45-M45,"") -> 0 | O45: =VALUE(+VLOOKUP(I45,'01'!C:K,9,FALSE)) -> 0.0906 | P45: =+N45*O45 -> 0
C46: WF-C5790 | D46: X3B7003739 | E46: 10.72.10.43 | F46: 1er Piso Compras | G46: 1 | H46: Bolsa 2 | I46: A4BN | J46: =+SUMIFS('02'!C:C,'02'!J:J,D46&" - "&C46&" - "&H46,'02'!B:B,'2026-3'!$I46) -> 30199 | K46: =+SUMIFS('02'!D:D,'02'!J:J,D46&" - "&C46&" - "&H46,'02'!B:B,'2026-3'!$I46) -> 30545 | L46: =IF(K46-J46<=0,"0",K46-J46) -> 346 | M46: =SUMIFS(X:X,V:V,H46,W:W,I46)/COUNTIF(H:H,H46) -> 188 | N46: =IFERROR(+L46-M46,"") -> 158 | O46: =VALUE(+VLOOKUP(I46,'01'!C:K,9,FALSE)) -> 0.0168 | P46: =+N46*O46 -> 2.6544 | Q46: {=_xlfn._xlws.FILTER(SAP!$B$2,1)/COUNTA($G$2:$G$85)} -> 51.681905 | R46: =+SUM(P46:P49) -> -13.9128 | S46: 941231308 | T46: 402
I47: A3BN | J47: =+SUMIFS('02'!C:C,'02'!J:J,D46&" - "&C46&" - "&H46,'02'!B:B,'2026-3'!$I47) -> 0 | K47: =+SUMIFS('02'!D:D,'02'!J:J,D46&" - "&C46&" - "&H46,'02'!B:B,'2026-3'!$I47) -> 0 | L47: =IF(K47-J47<=0,"0",K47-J47) -> 0 | N47: =IFERROR(+L47-M47,"") -> 0 | O47: =VALUE(+VLOOKUP(I47,'01'!C:K,9,FALSE)) -> 0.0301 | P47: =+N47*O47 -> 0
I48: A4CL | J48: =+SUMIFS('02'!C:C,'02'!J:J,D46&" - "&C46&" - "&H46,'02'!B:B,'2026-3'!$I48) -> 34833 | K48: =+SUMIFS('02'!D:D,'02'!J:J,D46&" - "&C46&" - "&H46,'02'!B:B,'2026-3'!$I48) -> 35045 | L48: =IF(K48-J48<=0,"0",K48-J48) -> 212 | M48: =SUMIFS(X:X,V:V,$H46,W:W,I48)/COUNTIF(H:H,$H46) -> 563 | N48: =IFERROR(+L48-M48,"") -> -351 | O48: =VALUE(+VLOOKUP(I48,'01'!C:K,9,FALSE)) -> 0.0472 | P48: =+N48*O48 -> -16.5672
I49: A3CL | J49: =+SUMIFS('02'!C:C,'02'!J:J,D46&" - "&C46&" - "&H46,'02'!B:B,'2026-3'!$I49) -> 0 | K49: =+SUMIFS('02'!D:D,'02'!J:J,D46&" - "&C46&" - "&H46,'02'!B:B,'2026-3'!$I49) -> 0 | L49: =IF(K49-J49<=0,"0",K49-J49) -> 0 | N49: =IFERROR(+L49-M49,"") -> 0 | O49: =VALUE(+VLOOKUP(I49,'01'!C:K,9,FALSE)) -> 0.0906 | P49: =+N49*O49 -> 0
C50: WF-C5790 | D50: X3B7003876 | E50: 10.72.8.220 | F50: 1er Piso - Oficina AyB | G50: 1 | H50: Bolsa 2 | I50: A4BN | J50: =+SUMIFS('02'!C:C,'02'!J:J,D50&" - "&C50&" - "&H50,'02'!B:B,'2026-3'!$I50) -> 58830 | K50: =+SUMIFS('02'!D:D,'02'!J:J,D50&" - "&C50&" - "&H50,'02'!B:B,'2026-3'!$I50) -> 59665 | L50: =IF(K50-J50<=0,"0",K50-J50) -> 835 | M50: =SUMIFS(X:X,V:V,H50,W:W,I50)/COUNTIF(H:H,H50) -> 188 | N50: =IFERROR(+L50-M50,"") -> 647 | O50: =VALUE(+VLOOKUP(I50,'01'!C:K,9,FALSE)) -> 0.0168 | P50: =+N50*O50 -> 10.8696 | Q50: {=_xlfn._xlws.FILTER(SAP!$B$2,1)/COUNTA($G$2:$G$85)} -> 51.681905 | R50: =+SUM(P50:P53) -> 7.5656 | S50: 932341308 | T50: 200
I51: A3BN | J51: =+SUMIFS('02'!C:C,'02'!J:J,D50&" - "&C50&" - "&H50,'02'!B:B,'2026-3'!$I51) -> 0 | K51: =+SUMIFS('02'!D:D,'02'!J:J,D50&" - "&C50&" - "&H50,'02'!B:B,'2026-3'!$I51) -> 0 | L51: =IF(K51-J51<=0,"0",K51-J51) -> 0 | N51: =IFERROR(+L51-M51,"") -> 0 | O51: =VALUE(+VLOOKUP(I51,'01'!C:K,9,FALSE)) -> 0.0301 | P51: =+N51*O51 -> 0
I52: A4CL | J52: =+SUMIFS('02'!C:C,'02'!J:J,D50&" - "&C50&" - "&H50,'02'!B:B,'2026-3'!$I52) -> 35550 | K52: =+SUMIFS('02'!D:D,'02'!J:J,D50&" - "&C50&" - "&H50,'02'!B:B,'2026-3'!$I52) -> 36043 | L52: =IF(K52-J52<=0,"0",K52-J52) -> 493 | M52: =SUMIFS(X:X,V:V,$H50,W:W,I52)/COUNTIF(H:H,$H50) -> 563 | N52: =IFERROR(+L52-M52,"") -> -70 | O52: =VALUE(+VLOOKUP(I52,'01'!C:K,9,FALSE)) -> 0.0472 | P52: =+N52*O52 -> -3.304
I53: A3CL | J53: =+SUMIFS('02'!C:C,'02'!J:J,D50&" - "&C50&" - "&H50,'02'!B:B,'2026-3'!$I53) -> 0 | K53: =+SUMIFS('02'!D:D,'02'!J:J,D50&" - "&C50&" - "&H50,'02'!B:B,'2026-3'!$I53) -> 0 | L53: =IF(K53-J53<=0,"0",K53-J53) -> 0 | N53: =IFERROR(+L53-M53,"") -> 0 | O53: =VALUE(+VLOOKUP(I53,'01'!C:K,9,FALSE)) -> 0.0906 | P53: =+N53*O53 -> 0
C54: WF-C5890 | D54: XBJZ017266 | E54: 10.72.8.229 | F54: 1er Sotano - Housekeeping | G54: 1 | H54: Bolsa 3 | I54: A4BN | J54: =+SUMIFS('02'!C:C,'02'!J:J,D54&" - "&C54&" - "&H54,'02'!B:B,'2026-3'!$I54) -> 6445 | K54: =+SUMIFS('02'!D:D,'02'!J:J,D54&" - "&C54&" - "&H54,'02'!B:B,'2026-3'!$I54) -> 7222 | L54: =IF(K54-J54<=0,"0",K54-J54) -> 777 | M54: =SUMIFS(X:X,V:V,H54,W:W,I54)/COUNTIF(H:H,H54) -> 188 | N54: =IFERROR(+L54-M54,"") -> 589 | O54: =VALUE(+VLOOKUP(I54,'01'!C:K,9,FALSE)) -> 0.0168 | P54: =+N54*O54 -> 9.8952 | Q54: {=_xlfn._xlws.FILTER(SAP!$B$2,1)/COUNTA($G$2:$G$85)} -> 51.681905 | R54: =+SUM(P54:P57) -> 192.6536 | S54: 931221108 | T54: 102
I55: A3BN | J55: =+SUMIFS('02'!C:C,'02'!J:J,D54&" - "&C54&" - "&H54,'02'!B:B,'2026-3'!$I55) -> 0 | K55: =+SUMIFS('02'!D:D,'02'!J:J,D54&" - "&C54&" - "&H54,'02'!B:B,'2026-3'!$I55) -> 0 | L55: =IF(K55-J55<=0,"0",K55-J55) -> 0 | N55: =IFERROR(+L55-M55,"") -> 0 | O55: =VALUE(+VLOOKUP(I55,'01'!C:K,9,FALSE)) -> 0.0301 | P55: =+N55*O55 -> 0
I56: A4CL | J56: =+SUMIFS('02'!C:C,'02'!J:J,D54&" - "&C54&" - "&H54,'02'!B:B,'2026-3'!$I56) -> 24340 | K56: =+SUMIFS('02'!D:D,'02'!J:J,D54&" - "&C54&" - "&H54,'02'!B:B,'2026-3'!$I56) -> 28775 | L56: =IF(K56-J56<=0,"0",K56-J56) -> 4435 | M56: =SUMIFS(X:X,V:V,$H54,W:W,I56)/COUNTIF(H:H,$H54) -> 563 | N56: =IFERROR(+L56-M56,"") -> 3872 | O56: =VALUE(+VLOOKUP(I56,'01'!C:K,9,FALSE)) -> 0.0472 | P56: =+N56*O56 -> 182.7584
I57: A3CL | J57: =+SUMIFS('02'!C:C,'02'!J:J,D54&" - "&C54&" - "&H54,'02'!B:B,'2026-3'!$I57) -> 0 | K57: =+SUMIFS('02'!D:D,'02'!J:J,D54&" - "&C54&" - "&H54,'02'!B:B,'2026-3'!$I57) -> 0 | L57: =IF(K57-J57<=0,"0",K57-J57) -> 0 | N57: =IFERROR(+L57-M57,"") -> 0 | O57: =VALUE(+VLOOKUP(I57,'01'!C:K,9,FALSE)) -> 0.0906 | P57: =+N57*O57 -> 0
C58: WF-C5890 | D58: XBJZ017602 | E58: 10.72.8.206 | F58: 1er Piso - Bodega | G58: 1 | H58: Bolsa 3 | I58: A4BN | J58: =+SUMIFS('02'!C:C,'02'!J:J,D58&" - "&C58&" - "&H58,'02'!B:B,'2026-3'!$I58) -> 28313 | K58: =+SUMIFS('02'!D:D,'02'!J:J,D58&" - "&C58&" - "&H58,'02'!B:B,'2026-3'!$I58) -> 28834 | L58: =IF(K58-J58<=0,"0",K58-J58) -> 521 | M58: =SUMIFS(X:X,V:V,H58,W:W,I58)/COUNTIF(H:H,H58) -> 188 | N58: =IFERROR(+L58-M58,"") -> 333 | O58: =VALUE(+VLOOKUP(I58,'01'!C:K,9,FALSE)) -> 0.0168 | P58: =+N58*O58 -> 5.5944 | Q58: {=_xlfn._xlws.FILTER(SAP!$B$2,1)/COUNTA($G$2:$G$85)} -> 51.681905 | R58: =+SUM(P58:P61) -> 41.7968 | S58: 941231308 | T58: 403
I59: A3BN | J59: =+SUMIFS('02'!C:C,'02'!J:J,D58&" - "&C58&" - "&H58,'02'!B:B,'2026-3'!$I59) -> 0 | K59: =+SUMIFS('02'!D:D,'02'!J:J,D58&" - "&C58&" - "&H58,'02'!B:B,'2026-3'!$I59) -> 0 | L59: =IF(K59-J59<=0,"0",K59-J59) -> 0 | N59: =IFERROR(+L59-M59,"") -> 0 | O59: =VALUE(+VLOOKUP(I59,'01'!C:K,9,FALSE)) -> 0.0301 | P59: =+N59*O59 -> 0
I60: A4CL | J60: =+SUMIFS('02'!C:C,'02'!J:J,D58&" - "&C58&" - "&H58,'02'!B:B,'2026-3'!$I60) -> 34374 | K60: =+SUMIFS('02'!D:D,'02'!J:J,D58&" - "&C58&" - "&H58,'02'!B:B,'2026-3'!$I60) -> 35704 | L60: =IF(K60-J60<=0,"0",K60-J60) -> 1330 | M60: =SUMIFS(X:X,V:V,$H58,W:W,I60)/COUNTIF(H:H,$H58) -> 563 | N60: =IFERROR(+L60-M60,"") -> 767 | O60: =VALUE(+VLOOKUP(I60,'01'!C:K,9,FALSE)) -> 0.0472 | P60: =+N60*O60 -> 36.2024
I61: A3CL | J61: =+SUMIFS('02'!C:C,'02'!J:J,D58&" - "&C58&" - "&H58,'02'!B:B,'2026-3'!$I61) -> 0 | K61: =+SUMIFS('02'!D:D,'02'!J:J,D58&" - "&C58&" - "&H58,'02'!B:B,'2026-3'!$I61) -> 0 | L61: =IF(K61-J61<=0,"0",K61-J61) -> 0 | N61: =IFERROR(+L61-M61,"") -> 0 | O61: =VALUE(+VLOOKUP(I61,'01'!C:K,9,FALSE)) -> 0.0906 | P61: =+N61*O61 -> 0
C62: WF-C5890 | D62: XBJZ017603 | E62: 10.72.8.196 | F62: 1er Piso - Conserge | G62: 1 | H62: Bolsa 3 | I62: A4BN | J62: =+SUMIFS('02'!C:C,'02'!J:J,D62&" - "&C62&" - "&H62,'02'!B:B,'2026-3'!$I62) -> 3603 | K62: =+SUMIFS('02'!D:D,'02'!J:J,D62&" - "&C62&" - "&H62,'02'!B:B,'2026-3'!$I62) -> 4044 | L62: =IF(K62-J62<=0,"0",K62-J62) -> 441 | M62: =SUMIFS(X:X,V:V,H62,W:W,I62)/COUNTIF(H:H,H62) -> 188 | N62: =IFERROR(+L62-M62,"") -> 253 | O62: =VALUE(+VLOOKUP(I62,'01'!C:K,9,FALSE)) -> 0.0168 | P62: =+N62*O62 -> 4.2504 | Q62: {=_xlfn._xlws.FILTER(SAP!$B$2,1)/COUNTA($G$2:$G$85)} -> 51.681905 | R62: =+SUM(P62:P65) -> -1.3192 | S62: 931221108 | T62: 103
I63: A3BN | J63: =+SUMIFS('02'!C:C,'02'!J:J,D62&" - "&C62&" - "&H62,'02'!B:B,'2026-3'!$I63) -> 0 | K63: =+SUMIFS('02'!D:D,'02'!J:J,D62&" - "&C62&" - "&H62,'02'!B:B,'2026-3'!$I63) -> 0 | L63: =IF(K63-J63<=0,"0",K63-J63) -> 0 | N63: =IFERROR(+L63-M63,"") -> 0 | O63: =VALUE(+VLOOKUP(I63,'01'!C:K,9,FALSE)) -> 0.0301 | P63: =+N63*O63 -> 0
I64: A4CL | J64: =+SUMIFS('02'!C:C,'02'!J:J,D62&" - "&C62&" - "&H62,'02'!B:B,'2026-3'!$I64) -> 3848 | K64: =+SUMIFS('02'!D:D,'02'!J:J,D62&" - "&C62&" - "&H62,'02'!B:B,'2026-3'!$I64) -> 4293 | L64: =IF(K64-J64<=0,"0",K64-J64) -> 445 | M64: =SUMIFS(X:X,V:V,$H62,W:W,I64)/COUNTIF(H:H,$H62) -> 563 | N64: =IFERROR(+L64-M64,"") -> -118 | O64: =VALUE(+VLOOKUP(I64,'01'!C:K,9,FALSE)) -> 0.0472 | P64: =+N64*O64 -> -5.5696
I65: A3CL | J65: =+SUMIFS('02'!C:C,'02'!J:J,D62&" - "&C62&" - "&H62,'02'!B:B,'2026-3'!$I65) -> 0 | K65: =+SUMIFS('02'!D:D,'02'!J:J,D62&" - "&C62&" - "&H62,'02'!B:B,'2026-3'!$I65) -> 0 | L65: =IF(K65-J65<=0,"0",K65-J65) -> 0 | N65: =IFERROR(+L65-M65,"") -> 0 | O65: =VALUE(+VLOOKUP(I65,'01'!C:K,9,FALSE)) -> 0.0906 | P65: =+N65*O65 -> 0
C66: WF-C5890 | D66: XBJZ021745 | E66: 10.72.8.219 | F66: 1er Piso - Oficina Chef | G66: 1 | H66: Bolsa 3 | I66: A4BN | J66: =+SUMIFS('01'!$D:$D,'01'!$M:$M,$D$66&" - "&$C$66&" - "&$H$66,'01'!$C:$C,'2026-3'!$I66) -> 4141 | K66: =+SUMIFS('01'!$E:$E,'01'!$M:$M,$D$66&" - "&$C$66&" - "&$H$66,'01'!$C:$C,'2026-3'!$I66) -> 4785 | L66: =IF(K66-J66<=0,"0",K66-J66) -> 644 | M66: =SUMIFS(X:X,V:V,H66,W:W,I66)/COUNTIF(H:H,H66) -> 188 | N66: =IFERROR(+L66-M66,"") -> 456 | O66: =VALUE(+VLOOKUP(I66,'01'!C:K,9,FALSE)) -> 0.0168 | P66: =+N66*O66 -> 7.6608 | Q66: {=_xlfn._xlws.FILTER(SAP!$B$2,1)/COUNTA($G$2:$G$85)} -> 51.681905 | R66: =+SUM(P66:P69) -> 167.1496 | S66: 932341308 | T66: 200 | U66: 1
I67: A3BN | J67: =+SUMIFS('01'!$D:$D,'01'!$M:$M,$D$66&" - "&$C$66&" - "&$H$66,'01'!$C:$C,'2026-3'!$I67) -> 0 | K67: =+SUMIFS('01'!$E:$E,'01'!$M:$M,$D$66&" - "&$C$66&" - "&$H$66,'01'!$C:$C,'2026-3'!$I67) -> 0 | L67: =IF(K67-J67<=0,"0",K67-J67) -> 0 | N67: =IFERROR(+L67-M67,"") -> 0 | O67: =VALUE(+VLOOKUP(I67,'01'!C:K,9,FALSE)) -> 0.0301 | P67: =+N67*O67 -> 0
I68: A4CL | J68: =+SUMIFS('01'!$D:$D,'01'!$M:$M,$D$66&" - "&$C$66&" - "&$H$66,'01'!$C:$C,'2026-3'!$I68) -> 23586 | K68: =+SUMIFS('01'!$E:$E,'01'!$M:$M,$D$66&" - "&$C$66&" - "&$H$66,'01'!$C:$C,'2026-3'!$I68) -> 27528 | L68: =IF(K68-J68<=0,"0",K68-J68) -> 3942 | M68: =SUMIFS(X:X,V:V,$H66,W:W,I68)/COUNTIF(H:H,$H66) -> 563 | N68: =IFERROR(+L68-M68,"") -> 3379 | O68: =VALUE(+VLOOKUP(I68,'01'!C:K,9,FALSE)) -> 0.0472 | P68: =+N68*O68 -> 159.4888
I69: A3CL | J69: =+SUMIFS('01'!$D:$D,'01'!$M:$M,$D$66&" - "&$C$66&" - "&$H$66,'01'!$C:$C,'2026-3'!$I69) -> 0 | K69: =+SUMIFS('01'!$E:$E,'01'!$M:$M,$D$66&" - "&$C$66&" - "&$H$66,'01'!$C:$C,'2026-3'!$I69) -> 0 | L69: =IF(K69-J69<=0,"0",K69-J69) -> 0 | N69: =IFERROR(+L69-M69,"") -> 0 | O69: =VALUE(+VLOOKUP(I69,'01'!C:K,9,FALSE)) -> 0.0906 | P69: =+N69*O69 -> 0
C70: WF-C5890 | D70: XBJZ021772 | E70: 10.72.8.151 | F70: 3er Piso - Gerencia General | G70: 1 | H70: Bolsa 3 | I70: A4BN | J70: =+SUMIFS('02'!C:C,'02'!J:J,D70&" - "&C70&" - "&H70,'02'!B:B,'2026-3'!$I70) -> 1638 | K70: =+SUMIFS('02'!D:D,'02'!J:J,D70&" - "&C70&" - "&H70,'02'!B:B,'2026-3'!$I70) -> 2080 | L70: =IF(K70-J70<=0,"0",K70-J70) -> 442 | M70: =SUMIFS(X:X,V:V,H70,W:W,I70)/COUNTIF(H:H,H70) -> 188 | N70: =IFERROR(+L70-M70,"") -> 254 | O70: =VALUE(+VLOOKUP(I70,'01'!C:K,9,FALSE)) -> 0.0168 | P70: =+N70*O70 -> 4.2672 | Q70: {=_xlfn._xlws.FILTER(SAP!$B$2,1)/COUNTA($G$2:$G$85)} -> 51.681905 | R70: =+SUM(P70:P73) -> 8.8456 | S70: 941231308 | T70: 401
I71: A3BN | J71: =+SUMIFS('02'!C:C,'02'!J:J,D70&" - "&C70&" - "&H70,'02'!B:B,'2026-3'!$I71) -> 0 | K71: =+SUMIFS('02'!D:D,'02'!J:J,D70&" - "&C70&" - "&H70,'02'!B:B,'2026-3'!$I71) -> 0 | L71: =IF(K71-J71<=0,"0",K71-J71) -> 0 | N71: =IFERROR(+L71-M71,"") -> 0 | O71: =VALUE(+VLOOKUP(I71,'01'!C:K,9,FALSE)) -> 0.0301 | P71: =+N71*O71 -> 0
I72: A4CL | J72: =+SUMIFS('02'!C:C,'02'!J:J,D70&" - "&C70&" - "&H70,'02'!B:B,'2026-3'!$I72) -> 1473 | K72: =+SUMIFS('02'!D:D,'02'!J:J,D70&" - "&C70&" - "&H70,'02'!B:B,'2026-3'!$I72) -> 2133 | L72: =IF(K72-J72<=0,"0",K72-J72) -> 660 | M72: =SUMIFS(X:X,V:V,$H70,W:W,I72)/COUNTIF(H:H,$H70) -> 563 | N72: =IFERROR(+L72-M72,"") -> 97 | O72: =VALUE(+VLOOKUP(I72,'01'!C:K,9,FALSE)) -> 0.0472 | P72: =+N72*O72 -> 4.5784
I73: A3CL | J73: =+SUMIFS('02'!C:C,'02'!J:J,D70&" - "&C70&" - "&H70,'02'!B:B,'2026-3'!$I73) -> 0 | K73: =+SUMIFS('02'!D:D,'02'!J:J,D70&" - "&C70&" - "&H70,'02'!B:B,'2026-3'!$I73) -> 0 | L73: =IF(K73-J73<=0,"0",K73-J73) -> 0 | N73: =IFERROR(+L73-M73,"") -> 0 | O73: =VALUE(+VLOOKUP(I73,'01'!C:K,9,FALSE)) -> 0.0906 | P73: =+N73*O73 -> 0
C74: WF-C5890 | D74: XBJZ027512 | E74: 10.72.8.210 | F74: 3er Piso - Ventas | G74: 1 | H74: Bolsa 3 | I74: A4BN | J74: =+SUMIFS('01'!$D:$D,'01'!$M:$M,$D$74&" - "&$C$74&" - "&$H$74,'01'!$C:$C,'2026-3'!$I74) -> 3883 | K74: =+SUMIFS('01'!$E:$E,'01'!$M:$M,$D$74&" - "&$C$74&" - "&$H$74,'01'!$C:$C,'2026-3'!$I74) -> 5188 | L74: =IF(K74-J74<=0,"0",K74-J74) -> 1305 | M74: =SUMIFS(X:X,V:V,H74,W:W,I74)/COUNTIF(H:H,H74) -> 188 | N74: =IFERROR(+L74-M74,"") -> 1117 | O74: =VALUE(+VLOOKUP(I74,'01'!C:K,9,FALSE)) -> 0.0168 | P74: =+N74*O74 -> 18.7656 | Q74: {=_xlfn._xlws.FILTER(SAP!$B$2,1)/COUNTA($G$2:$G$85)} -> 51.681905 | R74: =+SUM(P74:P77) -> 180.1424 | S74: 943331308 | T74: 406
I75: A3BN | J75: =+SUMIFS('01'!$D:$D,'01'!$M:$M,$D$74&" - "&$C$74&" - "&$H$74,'01'!$C:$C,'2026-3'!$I75) -> 0 | K75: =+SUMIFS('01'!$E:$E,'01'!$M:$M,$D$74&" - "&$C$74&" - "&$H$74,'01'!$C:$C,'2026-3'!$I75) -> 0 | L75: =IF(K75-J75<=0,"0",K75-J75) -> 0 | N75: =IFERROR(+L75-M75,"") -> 0 | O75: =VALUE(+VLOOKUP(I75,'01'!C:K,9,FALSE)) -> 0.0301 | P75: =+N75*O75 -> 0
I76: A4CL | J76: =+SUMIFS('01'!$D:$D,'01'!$M:$M,$D$74&" - "&$C$74&" - "&$H$74,'01'!$C:$C,'2026-3'!$I76) -> 11370 | K76: =+SUMIFS('01'!$E:$E,'01'!$M:$M,$D$74&" - "&$C$74&" - "&$H$74,'01'!$C:$C,'2026-3'!$I76) -> 15352 | L76: =IF(K76-J76<=0,"0",K76-J76) -> 3982 | M76: =SUMIFS(X:X,V:V,$H74,W:W,I76)/COUNTIF(H:H,$H74) -> 563 | N76: =IFERROR(+L76-M76,"") -> 3419 | O76: =VALUE(+VLOOKUP(I76,'01'!C:K,9,FALSE)) -> 0.0472 | P76: =+N76*O76 -> 161.3768
I77: A3CL | J77: =+SUMIFS('01'!$D:$D,'01'!$M:$M,$D$74&" - "&$C$74&" - "&$H$74,'01'!$C:$C,'2026-3'!$I77) -> 0 | K77: =+SUMIFS('01'!$E:$E,'01'!$M:$M,$D$74&" - "&$C$74&" - "&$H$74,'01'!$C:$C,'2026-3'!$I77) -> 0 | L77: =IF(K77-J77<=0,"0",K77-J77) -> 0 | N77: =IFERROR(+L77-M77,"") -> 0 | O77: =VALUE(+VLOOKUP(I77,'01'!C:K,9,FALSE)) -> 0.0906 | P77: =+N77*O77 -> 0
B78: Sharp | C78: MX-3070 | D78: 35009304 | E78: 10.72.8.200 | F78: 1er Sotano - RRHH - Sistemas | G78: 1 | H78: Bolsa 4 | I78: A4BN | J78: =+SUMIFS('01'!$D:$D,'01'!$M:$M,$D$78&" - "&$C$78&" - "&$H$78,'01'!$C:$C,'2026-3'!$I78) -> 5 | K78: =+SUMIFS('01'!$E:$E,'01'!$M:$M,$D$78&" - "&$C$78&" - "&$H$78,'01'!$C:$C,'2026-3'!$I78) -> 3848 | L78: =IF(K78-J78<=0,"0",K78-J78) -> 3843 | M78: =SUMIFS(X:X,V:V,H78,W:W,I78)/COUNTIF(H:H,H78) -> 188 | N78: =IFERROR(+L78-M78,"") -> 3655 | O78: =VALUE(+VLOOKUP(I78,'01'!C:K,9,FALSE)) -> 0.0168 | P78: =+N78*O78 -> 61.404 | Q78: {=_xlfn._xlws.FILTER(SAP!$B$2,1)/COUNTA($G$2:$G$85)} -> 51.681905 | R78: =+SUM(P78:P81) -> 61.404 | S78: 942331307 | T78: 404
I79: A3BN | J79: =+SUMIFS('01'!$D:$D,'01'!$M:$M,$D$78&" - "&$C$78&" - "&$H$78,'01'!$C:$C,'2026-3'!$I79) -> 0 | K79: =+SUMIFS('01'!$E:$E,'01'!$M:$M,$D$78&" - "&$C$78&" - "&$H$78,'01'!$C:$C,'2026-3'!$I79) -> 0 | L79: =IF(K79-J79<=0,"0",K79-J79) -> 0 | N79: =IFERROR(+L79-M79,"") -> 0 | O79: =VALUE(+VLOOKUP(I79,'01'!C:K,9,FALSE)) -> 0.0301 | P79: =+N79*O79 -> 0
I80: A4CL | J80: =+SUMIFS('01'!$D:$D,'01'!$M:$M,$D$78&" - "&$C$78&" - "&$H$78,'01'!$C:$C,'2026-3'!$I80) -> 31 | K80: =+SUMIFS('01'!$E:$E,'01'!$M:$M,$D$78&" - "&$C$78&" - "&$H$78,'01'!$C:$C,'2026-3'!$I80) -> 340 | L80: =IF(K80-J80<=0,"0",K80-J80) -> 309 | M80: =SUMIFS(X:X,V:V,$H78,W:W,I80)/COUNTIF(H:H,$H78) -> 563 | N80: =IFERROR(IF(L80-M80<0,0,L80-M80),"") -> 0 | O80: =VALUE(+VLOOKUP(I80,'01'!C:K,9,FALSE)) -> 0.0472 | P80: =+N80*O80 -> 0
I81: A3CL | J81: =+SUMIFS('01'!$D:$D,'01'!$M:$M,$D$78&" - "&$C$78&" - "&$H$78,'01'!$C:$C,'2026-3'!$I81) -> 0 | K81: =+SUMIFS('01'!$E:$E,'01'!$M:$M,$D$78&" - "&$C$78&" - "&$H$78,'01'!$C:$C,'2026-3'!$I81) -> 0 | L81: =IF(K81-J81<=0,"0",K81-J81) -> 0 | N81: =IFERROR(IF(L81-M81<0,0,L81-M81),"") -> 0 | O81: =VALUE(+VLOOKUP(I81,'01'!C:K,9,FALSE)) -> 0.0906 | P81: =+N81*O81 -> 0
C82: MX-M3070 | D82: 9502370Y | E82: 10.72.8.207 | F82: 3er Piso - Contabilidad | G82: 1 | H82: Bolsa 1 | I82: A4BN | J82: =+SUMIFS('02'!C:C,'02'!J:J,D82&" - "&C82&" - "&H82,'02'!B:B,'2026-3'!$I82) -> 57 | K82: =+SUMIFS('02'!D:D,'02'!J:J,D82&" - "&C82&" - "&H82,'02'!B:B,'2026-3'!$I82) -> 8633 | L82: =IF(K82-J82<=0,"0",K82-J82) -> 8576 | M82: =SUMIFS(X:X,V:V,H82,W:W,I82)/COUNTIF(H:H,H82) -> 3250 | N82: =IFERROR(+L82-M82,"") -> 5326 | O82: =VALUE(+VLOOKUP(I82,'01'!C:K,9,FALSE)) -> 0.0168 | P82: =+N82*O82 -> 89.4768 | Q82: {=_xlfn._xlws.FILTER(SAP!$B$2,1)/COUNTA($G$2:$G$85)} -> 51.681905 | R82: =+SUM(P82:P85) -> 89.4768 | S82: 941231308 | T82: 403
I83: A3BN | J83: =+SUMIFS('02'!C:C,'02'!J:J,D82&" - "&C82&" - "&H82,'02'!B:B,'2026-3'!$I83) -> 0 | K83: =+SUMIFS('02'!D:D,'02'!J:J,D82&" - "&C82&" - "&H82,'02'!B:B,'2026-3'!$I83) -> 0 | L83: =IF(K83-J83<=0,"0",K83-J83) -> 0 | N83: =IFERROR(+L83-M83,"") -> 0 | O83: =VALUE(+VLOOKUP(I83,'01'!C:K,9,FALSE)) -> 0.0301 | P83: =+N83*O83 -> 0
I84: A4CL | J84: =+SUMIFS('02'!C:C,'02'!J:J,D82&" - "&C82&" - "&H82,'02'!B:B,'2026-3'!$I84) -> 0 | K84: =+SUMIFS('02'!D:D,'02'!J:J,D82&" - "&C82&" - "&H82,'02'!B:B,'2026-3'!$I84) -> 0 | L84: =IF(K84-J84<=0,"0",K84-J84) -> 0 | M84: =SUMIFS(X:X,V:V,$H82,W:W,I84)/COUNTIF(H:H,$H82) -> 0 | N84: =IFERROR(+L84-M84,"") -> 0 | O84: =VALUE(+VLOOKUP(I84,'01'!C:K,9,FALSE)) -> 0.0472 | P84: =+N84*O84 -> 0
I85: A3CL | J85: =+SUMIFS('02'!C:C,'02'!J:J,D82&" - "&C82&" - "&H82,'02'!B:B,'2026-3'!$I85) -> 0 | K85: =+SUMIFS('02'!D:D,'02'!J:J,D82&" - "&C82&" - "&H82,'02'!B:B,'2026-3'!$I85) -> 0 | L85: =IF(K85-J85<=0,"0",K85-J85) -> 0 | N85: =IFERROR(+L85-M85,"") -> 0 | O85: =VALUE(+VLOOKUP(I85,'01'!C:K,9,FALSE)) -> 0.0906 | P85: =+N85*O85 -> 0
B86: Total | G86: =SUM(G2:G85) -> 21 | O86: A4BN | P86: =P82+P6+P10+P14 -> 507.6288 | U86: Bolsa 1 | V86: ok
O87: A4BN | P87: =+P18+P22+P26+P34+P38+P42+P46+P50 -> 135.4584 | U87: Bolsa2 | V87: ok
O88: A4CL | P88: =+P20+P24+P28+P36+P40+P44+P48+P52 -> 233.4512 | U88: Bolsa2 | V88: ok
O89: A4BN | P89: =+P74+P70+P66+P62+P58+P54 -> 50.4336 | U89: Bolsa3 | V89: ok
O90: A4CL | P90: =+P76+P72+P68+P64+P60+P56 -> 538.8352 | U90: Bolsa3 | V90: ok
O91: A4BN | P91: =+P78 -> 61.404 | U91: Bolsa4 | V91: ok | W91: {=+SUM(P34:P85+SUM(P2:P29))} -> 36679.522
O92: A4BN | P92: =+P2 -> 2.8056 | U92: Bolsa5 | V92: ok
O93: A3CL | P93: =+P5 -> 0.3624 | U93: Bolsa6 | V93: ok
P94: =SUM(P86:P93) -> 1530.3792
P96: =+P94+P30+P32 -> 1967.7416 | R96: =SUM(R2:R84) -> 1962.5024
R97: =+R96-P96 -> -5.2392

Sheet 2026
B2: REPORTE DE COPIAS - REPRODATA 2026-2026
D5: 44562 | I5: 44593 | M5: 44621 | Q5: 44652 | U5: 44682 | Y5: 44713 | AC5: 44743
B6: SERIE DE EQUIPO | C6: UBICACION / AREA | D6: Tipo | E6: Bolsa | F6: Cantidad | G6: Precio $ | H6: Total | I6: Tipo | J6: Cantidad | K6: Precio $ | L6: Total | M6: Tipo | N6: Cantidad | O6: Precio $ | P6: Total | Q6: Tipo | R6: Cantidad | S6: Precio $ | T6: Total | U6: Tipo | V6: Cantidad | W6: Precio $ | X6: Total | Y6: Tipo | Z6: Cantidad | AA6: Precio $ | AB6: Total | AC6: Tipo | AD6: Cantidad | AE6: Precio $ | AF6: Total
B7: X3B7003661 - WF-C5790 | C7: Contabilidad | D7: A4BN | G7: 0.0111 | H7: =+F7*G7 -> 0 | I7: B/N | J7: 1625 | K7: 0.0111 | L7: =+J7*K7 -> 18.0375 | M7: B/N | N7: 2826 | O7: 0.0111 | P7: =+N7*O7 -> 31.3686 | Q7: B/N | R7: 1912 | S7: 0.0111 | T7: =+R7*S7 -> 21.2232 | U7: B/N | V7: 2371 | W7: 0.0111 | X7: =+V7*W7 -> 26.3181 | Y7: B/N | Z7: 1644 | AA7: 0.0111 | AB7: =+Z7*AA7 -> 18.2484 | AC7: B/N | AD7: 23230 | AE7: 0.0111 | AF7: =+AD7*AE7 -> 257.853
D8: A3BN
D9: A4CL
D10: A3CL | G10: 0.0501 | H10: =+F10*G10 -> 0 | I10: Colores | K10: 0.0501 | L10: =+J10*K10 -> 0 | M10: Colores | O10: 0.0501 | P10: =+N10*O10 -> 0 | Q10: Colores | S10: 0.0501 | T10: =+R10*S10 -> 0 | U10: Colores | W10: 0.0501 | X10: =+V10*W10 -> 0 | Y10: Colores | AA10: 0.0501 | AB10: =+Z10*AA10 -> 0 | AC10: Colores | AE10: 0.0501 | AF10: =+AD10*AE10 -> 0
B11: X3B7003581 | C11: C&M Oficina | D11: B/N | F11: 325 | G11: 0.0198 | H11: =+F11*G11 -> 6.435 | I11: B/N | J11: 686 | K11: 0.0198 | L11: =+J11*K11 -> 13.5828 | M11: B/N | N11: 347 | O11: 0.0198 | P11: =+N11*O11 -> 6.8706 | Q11: B/N | R11: 248 | S11: 0.0198 | T11: =+R11*S11 -> 4.9104 | U11: B/N | V11: 600 | W11: 0.0198 | X11: =+V11*W11 -> 11.88 | Y11: B/N | Z11: 1197 | AA11: 0.0198 | AB11: =+Z11*AA11 -> 23.7006 | AC11: B/N | AD11: 753 | AE11: 0.0198 | AF11: =+AD11*AE11 -> 14.9094
B12: X3B7003581 | C12: C&M Oficina | D12: Colores | F12: 2 | G12: 0.0501 | H12: =+F12*G12 -> 0.1002 | I12: Colores | K12: 0.0501 | L12: =+J12*K12 -> 0 | M12: Colores | O12: 0.0501 | P12: =+N12*O12 -> 0 | Q12: Colores | S12: 0.0501 | T12: =+R12*S12 -> 0 | U12: Colores | V12: 1 | W12: 0.0501 | X12: =+V12*W12 -> 0.0501 | Y12: Colores | AA12: 0.0501 | AB12: =+Z12*AA12 -> 0 | AC12: Colores | AE12: 0.0501 | AF12: =+AD12*AE12 -> 0
B13: X3B7003609 | C13: Talento y Cultura | D13: B/N | F13: 2436 | G13: 0.0198 | H13: =+F13*G13 -> 48.2328 | I13: B/N | J13: 1994 | K13: 0.0198 | L13: =+J13*K13 -> 39.4812 | M13: B/N | N13: 2678 | O13: 0.0198 | P13: =+N13*O13 -> 53.0244 | Q13: B/N | R13: 2164 | S13: 0.0198 | T13: =+R13*S13 -> 42.8472 | U13: B/N | V13: 1972 | W13: 0.0198 | X13: =+V13*W13 -> 39.0456 | Y13: B/N | Z13: 904 | AA13: 0.0198 | AB13: =+Z13*AA13 -> 17.8992 | AC13: B/N | AD13: 2482 | AE13: 0.0198 | AF13: =+AD13*AE13 -> 49.1436
B14: X3B7003609 | C14: Talento y Cultura | D14: Colores | F14: 187 | G14: 0.0501 | H14: =+F14*G14 -> 9.3687 | I14: Colores | J14: 82 | K14: 0.0501 | L14: =+J14*K14 -> 4.1082 | M14: Colores | N14: 4215 | O14: 0.0501 | P14: =+N14*O14 -> 211.1715 | Q14: Colores | R14: 141 | S14: 0.0501 | T14: =+R14*S14 -> 7.0641 | U14: Colores | V14: 34 | W14: 0.0501 | X14: =+V14*W14 -> 1.7034 | Y14: Colores | Z14: 266 | AA14: 0.0501 | AB14: =+Z14*AA14 -> 13.3266 | AC14: Colores | AD14: 207 | AE14: 0.0501 | AF14: =+AD14*AE14 -> 10.3707
A15: No se usa | B15: X3B7003615 | C15: Disponible | D15: B/N | G15: 0.0198 | H15: =+F15*G15 -> 0 | I15: B/N | K15: 0.0198 | L15: =+J15*K15 -> 0 | M15: B/N | O15: 0.0198 | P15: =+N15*O15 -> 0 | Q15: B/N | S15: 0.0198 | T15: =+R15*S15 -> 0 | U15: B/N | W15: 0.0198 | X15: =+V15*W15 -> 0 | Y15: B/N | Z15: 12 | AA15: 0.0198 | AB15: =+Z15*AA15 -> 0.2376 | AC15: B/N | AD15: 1819 | AE15: 0.0198 | AF15: =+AD15*AE15 -> 36.0162
A16: No se usa | B16: X3B7003615 | C16: Disponible | D16: Colores | G16: 0.0501 | H16: =+F16*G16 -> 0 | I16: Colores | K16: 0.0501 | L16: =+J16*K16 -> 0 | M16: Colores | O16: 0.0501 | P16: =+N16*O16 -> 0 | Q16: Colores | S16: 0.0501 | T16: =+R16*S16 -> 0 | U16: Colores | W16: 0.0501 | X16: =+V16*W16 -> 0 | Y16: Colores | Z16: 10 | AA16: 0.0501 | AB16: =+Z16*AA16 -> 0.501 | AC16: Colores | AD16: 1208 | AE16: 0.0501 | AF16: =+AD16*AE16 -> 60.5208
B17: X3B7003656 | C17: Concierge | D17: B/N | F17: 127 | G17: 0.0198 | H17: =+F17*G17 -> 2.5146 | I17: B/N | J17: 660 | K17: 0.0198 | L17: =+J17*K17 -> 13.068 | M17: B/N | N17: 533 | O17: 0.0198 | P17: =+N17*O17 -> 10.5534 | Q17: B/N | R17: 541 | S17: 0.0198 | T17: =+R17*S17 -> 10.7118 | U17: B/N | V17: 607 | W17: 0.0198 | X17: =+V17*W17 -> 12.0186 | Y17: B/N | Z17: 586 | AA17: 0.0198 | AB17: =+Z17*AA17 -> 11.6028 | AC17: B/N | AD17: 521 | AE17: 0.0198 | AF17: =+AD17*AE17 -> 10.3158
B18: X3B7003656 | C18: Concierge | D18: Colores | F18: 24 | G18: 0.0501 | H18: =+F18*G18 -> 1.2024 | I18: Colores | J18: 86 | K18: 0.0501 | L18: =+J18*K18 -> 4.3086 | M18: Colores | N18: 23 | O18: 0.0501 | P18: =+N18*O18 -> 1.1523 | Q18: Colores | R18: 63 | S18: 0.0501 | T18: =+R18*S18 -> 3.1563 | U18: Colores | V18: 204 | W18: 0.0501 | X18: =+V18*W18 -> 10.2204 | Y18: Colores | Z18: 132 | AA18: 0.0501 | AB18: =+Z18*AA18 -> 6.6132 | AC18: Colores | AD18: 50 | AE18: 0.0501 | AF18: =+AD18*AE18 -> 2.505
B19: X3B7003659 | C19: Asistente Gerencia General | D19: B/N | G19: 0.0198 | H19: =+F19*G19 -> 0 | I19: B/N | J19: 384 | K19: 0.0198 | L19: =+J19*K19 -> 7.6032 | M19: B/N | N19: 70 | O19: 0.0198 | P19: =+N19*O19 -> 1.386 | Q19: B/N | R19: 142 | S19: 0.0198 | T19: =+R19*S19 -> 2.8116 | U19: B/N | V19: 143 | W19: 0.0198 | X19: =+V19*W19 -> 2.8314 | Y19: B/N | Z19: 101 | AA19: 0.0198 | AB19: =+Z19*AA19 -> 1.9998 | AC19: B/N | AD19: 154 | AE19: 0.0198 | AF19: =+AD19*AE19 -> 3.0492
B20: X3B7003659 | C20: Asistente Gerencia General | D20: Colores | F20: 40 | G20: 0.0501 | H20: =+F20*G20 -> 2.004 | I20: Colores | J20: 394 | K20: 0.0501 | L20: =+J20*K20 -> 19.7394 | M20: Colores | N20: 281 | O20: 0.0501 | P20: =+N20*O20 -> 14.0781 | Q20: Colores | R20: 195 | S20: 0.0501 | T20: =+R20*S20 -> 9.7695 | U20: Colores | V20: 123 | W20: 0.0501 | X20: =+V20*W20 -> 6.1623 | Y20: Colores | Z20: 84 | AA20: 0.0501 | AB20: =+Z20*AA20 -> 4.2084 | AC20: Colores | AD20: 214 | AE20: 0.0501 | AF20: =+AD20*AE20 -> 10.7214
B21: X3B7003660 | C21: Room Service | D21: B/N | F21: 2077 | G21: 0.0198 | H21: =+F21*G21 -> 41.1246 | I21: B/N | J21: 1547 | K21: 0.0198 | L21: =+J21*K21 -> 30.6306 | M21: B/N | N21: 1326 | O21: 0.0198 | P21: =+N21*O21 -> 26.2548 | Q21: B/N | R21: 789 | S21: 0.0198 | T21: =+R21*S21 -> 15.6222 | U21: B/N | V21: 1131 | W21: 0.0198 | X21: =+V21*W21 -> 22.3938 | Y21: B/N | Z21: 800 | AA21: 0.0198 | AB21: =+Z21*AA21 -> 15.84 | AC21: B/N | AD21: 810 | AE21: 0.0198 | AF21: =+AD21*AE21 -> 16.038
B22: X3B7003660 | C22: Room Service | D22: Colores | G22: 0.0501 | H22: =+F22*G22 -> 0 | I22: Colores | K22: 0.0501 | L22: =+J22*K22 -> 0 | M22: Colores | O22: 0.0501 | P22: =+N22*O22 -> 0 | Q22: Colores | S22: 0.0501 | T22: =+R22*S22 -> 0 | U22: Colores | V22: 2 | W22: 0.0501 | X22: =+V22*W22 -> 0.1002 | Y22: Colores | AA22: 0.0501 | AB22: =+Z22*AA22 -> 0 | AC22: Colores | AE22: 0.0501 | AF22: =+AD22*AE22 -> 0
A23: No se usa | B23: X3B7003661 | C23: Disponible | D23: B/N | G23: 0.0198 | H23: =+F23*G23 -> 0 | I23: B/N | K23: 0.0198 | L23: =+J23*K23 -> 0 | M23: B/N | O23: 0.0198 | P23: =+N23*O23 -> 0 | Q23: B/N | S23: 0.0198 | T23: =+R23*S23 -> 0 | U23: B/N | W23: 0.0198 | X23: =+V23*W23 -> 0 | Y23: B/N | AA23: 0.0198 | AB23: =+Z23*AA23 -> 0 | AC23: B/N | AE23: 0.0198 | AF23: =+AD23*AE23 -> 0
A24: No se usa | B24: X3B7003661 | C24: Disponible | D24: Colores | G24: 0.0501 | H24: =+F24*G24 -> 0 | I24: Colores | K24: 0.0501 | L24: =+J24*K24 -> 0 | M24: Colores | O24: 0.0501 | P24: =+N24*O24 -> 0 | Q24: Colores | S24: 0.0501 | T24: =+R24*S24 -> 0 | U24: Colores | W24: 0.0501 | X24: =+V24*W24 -> 0 | Y24: Colores | AA24: 0.0501 | AB24: =+Z24*AA24 -> 0 | AC24: Colores | AE24: 0.0501 | AF24: =+AD24*AE24 -> 0
B25: X3B7003671 | C25: Compras | D25: B/N | F25: 42 | G25: 0.0198 | H25: =+F25*G25 -> 0.8316 | I25: B/N | J25: 80 | K25: 0.0198 | L25: =+J25*K25 -> 1.584 | M25: B/N | N25: 127 | O25: 0.0198 | P25: =+N25*O25 -> 2.5146 | Q25: B/N | R25: 68 | S25: 0.0198 | T25: =+R25*S25 -> 1.3464 | U25: B/N | V25: 105 | W25: 0.0198 | X25: =+V25*W25 -> 2.079 | Y25: B/N | Z25: 91 | AA25: 0.0198 | AB25: =+Z25*AA25 -> 1.8018 | AC25: B/N | AD25: 123 | AE25: 0.0198 | AF25: =+AD25*AE25 -> 2.4354
B26: X3B7003671 | C26: Compras | D26: Colores | F26: 21 | G26: 0.0501 | H26: =+F26*G26 -> 1.0521 | I26: Colores | J26: 38 | K26: 0.0501 | L26: =+J26*K26 -> 1.9038 | M26: Colores | N26: 60 | O26: 0.0501 | P26: =+N26*O26 -> 3.006 | Q26: Colores | R26: 31 | S26: 0.0501 | T26: =+R26*S26 -> 1.5531 | U26: Colores | V26: 34 | W26: 0.0501 | X26: =+V26*W26 -> 1.7034 | Y26: Colores | Z26: 18 | AA26: 0.0501 | AB26: =+Z26*AA26 -> 0.9018 | AC26: Colores | AD26: 35 | AE26: 0.0501 | AF26: =+AD26*AE26 -> 1.7535
B27: X3B7003690 | C27: Cuadres | D27: B/N | G27: 0.0198 | H27: =+F27*G27 -> 0 | I27: B/N | K27: 0.0198 | L27: =+J27*K27 -> 0 | M27: B/N | N27: 13 | O27: 0.0198 | P27: =+N27*O27 -> 0.2574 | Q27: B/N | R27: 372 | S27: 0.0198 | T27: =+R27*S27 -> 7.3656 | U27: B/N | V27: 372 | W27: 0.0198 | X27: =+V27*W27 -> 7.3656 | Y27: B/N | Z27: 225 | AA27: 0.0198 | AB27: =+Z27*AA27 -> 4.455 | AC27: B/N | AD27: 323 | AE27: 0.0198 | AF27: =+AD27*AE27 -> 6.3954
B28: X3B7003690 | C28: Cuadres | D28: Colores | G28: 0.0501 | H28: =+F28*G28 -> 0 | I28: Colores | J28: 165 | K28: 0.0501 | L28: =+J28*K28 -> 8.2665 | M28: Colores | N28: 232 | O28: 0.0501 | P28: =+N28*O28 -> 11.6232 | Q28: Colores | S28: 0.0501 | T28: =+R28*S28 -> 0 | U28: Colores | V28: 37 | W28: 0.0501 | X28: =+V28*W28 -> 1.8537 | Y28: Colores | Z28: 7 | AA28: 0.0501 | AB28: =+Z28*AA28 -> 0.3507 | AC28: Colores | AD28: 25 | AE28: 0.0501 | AF28: =+AD28*AE28 -> 1.2525
B29: X3B7003703 | C29: GYM | D29: B/N | F29: 1944 | G29: 0.0198 | H29: =+F29*G29 -> 38.4912 | I29: B/N | J29: 926 | K29: 0.0198 | L29: =+J29*K29 -> 18.3348 | M29: B/N | N29: 1253 | O29: 0.0198 | P29: =+N29*O29 -> 24.8094 | Q29: B/N | R29: 1527 | S29: 0.0198 | T29: =+R29*S29 -> 30.2346 | U29: B/N | V29: 1166 | W29: 0.0198 | X29: =+V29*W29 -> 23.0868 | Y29: B/N | Z29: 1418 | AA29: 0.0198 | AB29: =+Z29*AA29 -> 28.0764 | AC29: B/N | AD29: 2093 | AE29: 0.0198 | AF29: =+AD29*AE29 -> 41.4414
B30: X3B7003703 | C30: GYM | D30: Colores | F30: 784 | G30: 0.0501 | H30: =+F30*G30 -> 39.2784 | I30: Colores | J30: 27 | K30: 0.0501 | L30: =+J30*K30 -> 1.3527 | M30: Colores | N30: 31 | O30: 0.0501 | P30: =+N30*O30 -> 1.5531 | Q30: Colores | R30: 134 | S30: 0.0501 | T30: =+R30*S30 -> 6.7134 | U30: Colores | V30: 81 | W30: 0.0501 | X30: =+V30*W30 -> 4.0581 | Y30: Colores | Z30: 56 | AA30: 0.0501 | AB30: =+Z30*AA30 -> 2.8056 | AC30: Colores | AD30: 63 | AE30: 0.0501 | AF30: =+AD30*AE30 -> 3.1563
B31: X3B7003711 | C31: Oficina de Recepción | D31: B/N | F31: 1186 | G31: 0.0198 | H31: =+F31*G31 -> 23.4828 | I31: B/N | J31: 1165 | K31: 0.0198 | L31: =+J31*K31 -> 23.067 | M31: B/N | N31: 797 | O31: 0.0198 | P31: =+N31*O31 -> 15.7806 | Q31: B/N | R31: 1074 | S31: 0.0198 | T31: =+R31*S31 -> 21.2652 | U31: B/N | V31: 1074 | W31: 0.0198 | X31: =+V31*W31 -> 21.2652 | Y31: B/N | Z31: 1257 | AA31: 0.0198 | AB31: =+Z31*AA31 -> 24.8886 | AC31: B/N | AD31: 1167 | AE31: 0.0198 | AF31: =+AD31*AE31 -> 23.1066
B32: X3B7003711 | C32: Oficina de Recepción | D32: Colores | F32: 193 | G32: 0.0501 | H32: =+F32*G32 -> 9.6693 | I32: Colores | J32: 335 | K32: 0.0501 | L32: =+J32*K32 -> 16.7835 | M32: Colores | N32: 312 | O32: 0.0501 | P32: =+N32*O32 -> 15.6312 | Q32: Colores | R32: 211 | S32: 0.0501 | T32: =+R32*S32 -> 10.5711 | U32: Colores | V32: 414 | W32: 0.0501 | X32: =+V32*W32 -> 20.7414 | Y32: Colores | Z32: 318 | AA32: 0.0501 | AB32: =+Z32*AA32 -> 15.9318 | AC32: Colores | AD32: 516 | AE32: 0.0501 | AF32: =+AD32*AE32 -> 25.8516
B33: X3B7003712 | C33: Bodegas | D33: B/N | F33: 262 | G33: 0.0198 | H33: =+F33*G33 -> 5.1876 | I33: B/N | J33: 480 | K33: 0.0198 | L33: =+J33*K33 -> 9.504 | M33: B/N | N33: 554 | O33: 0.0198 | P33: =+N33*O33 -> 10.9692 | Q33: B/N | R33: 447 | S33: 0.0198 | T33: =+R33*S33 -> 8.8506 | U33: B/N | V33: 480 | W33: 0.0198 | X33: =+V33*W33 -> 9.504 | Y33: B/N | Z33: 411 | AA33: 0.0198 | AB33: =+Z33*AA33 -> 8.1378 | AC33: B/N | AD33: 490 | AE33: 0.0198 | AF33: =+AD33*AE33 -> 9.702
B34: X3B7003712 | C34: Bodegas | D34: Colores | F34: 19 | G34: 0.0501 | H34: =+F34*G34 -> 0.9519 | I34: Colores | J34: 38 | K34: 0.0501 | L34: =+J34*K34 -> 1.9038 | M34: Colores | O34: 0.0501 | P34: =+N34*O34 -> 0 | Q34: Colores | S34: 0.0501 | T34: =+R34*S34 -> 0 | U34: Colores | V34: 3 | W34: 0.0501 | X34: =+V34*W34 -> 0.1503 | Y34: Colores | AA34: 0.0501 | AB34: =+Z34*AA34 -> 0 | AC34: Colores | AE34: 0.0501 | AF34: =+AD34*AE34 -> 0
B35: X3B7003716 | C35: Limpieza | D35: B/N | F35: 213 | G35: 0.0198 | H35: =+F35*G35 -> 4.2174 | I35: B/N | J35: 419 | K35: 0.0198 | L35: =+J35*K35 -> 8.2962 | M35: B/N | N35: 183 | O35: 0.0198 | P35: =+N35*O35 -> 3.6234 | Q35: B/N | R35: 80 | S35: 0.0198 | T35: =+R35*S35 -> 1.584 | U35: B/N | V35: 100 | W35: 0.0198 | X35: =+V35*W35 -> 1.98 | Y35: B/N | Z35: 157 | AA35: 0.0198 | AB35: =+Z35*AA35 -> 3.1086 | AC35: B/N | AD35: 146 | AE35: 0.0198 | AF35: =+AD35*AE35 -> 2.8908
B36: X3B7003716 | C36: Limpieza | D36: Colores | G36: 0.0501 | H36: =+F36*G36 -> 0 | I36: Colores | K36: 0.0501 | L36: =+J36*K36 -> 0 | M36: Colores | O36: 0.0501 | P36: =+N36*O36 -> 0 | Q36: Colores | S36: 0.0501 | T36: =+R36*S36 -> 0 | U36: Colores | V36: 2 | W36: 0.0501 | X36: =+V36*W36 -> 0.1002 | Y36: Colores | AA36: 0.0501 | AB36: =+Z36*AA36 -> 0 | AC36: Colores | AE36: 0.0501 | AF36: =+AD36*AE36 -> 0
B37: X3B7003751 | C37: Housekeeping | D37: B/N | F37: 2300 | G37: 0.0198 | H37: =+F37*G37 -> 45.54 | I37: B/N | J37: 2149 | K37: 0.0198 | L37: =+J37*K37 -> 42.5502 | M37: B/N | N37: 2167 | O37: 0.0198 | P37: =+N37*O37 -> 42.9066 | Q37: B/N | R37: 2270 | S37: 0.0198 | T37: =+R37*S37 -> 44.946 | U37: B/N | V37: 2070 | W37: 0.0198 | X37: =+V37*W37 -> 40.986 | Y37: B/N | Z37: 1291 | AA37: 0.0198 | AB37: =+Z37*AA37 -> 25.5618 | AC37: B/N | AD37: 3167 | AE37: 0.0198 | AF37: =+AD37*AE37 -> 62.7066
B38: X3B7003751 | C38: Housekeeping | D38: Colores | G38: 0.0501 | H38: =+F38*G38 -> 0 | I38: Colores | K38: 0.0501 | L38: =+J38*K38 -> 0 | M38: Colores | O38: 0.0501 | P38: =+N38*O38 -> 0 | Q38: Colores | S38: 0.0501 | T38: =+R38*S38 -> 0 | U38: Colores | W38: 0.0501 | X38: =+V38*W38 -> 0 | Y38: Colores | AA38: 0.0501 | AB38: =+Z38*AA38 -> 0 | AC38: Colores | AE38: 0.0501 | AF38: =+AD38*AE38 -> 0
B39: X3B7003828 | C39: Reservas | D39: B/N | G39: 0.0198 | H39: =+F39*G39 -> 0 | I39: B/N | K39: 0.0198 | L39: =+J39*K39 -> 0 | M39: B/N | O39: 0.0198 | P39: =+N39*O39 -> 0 | Q39: B/N | R39: 53 | S39: 0.0198 | T39: =+R39*S39 -> 1.0494 | U39: B/N | V39: 241 | W39: 0.0198 | X39: =+V39*W39 -> 4.7718 | Y39: B/N | Z39: 276 | AA39: 0.0198 | AB39: =+Z39*AA39 -> 5.4648 | AC39: B/N | AD39: 0 | AE39: 0.0198 | AF39: =+AD39*AE39 -> 0
B40: X3B7003828 | C40: Reservas | D40: Colores | F40: 38 | G40: 0.0501 | H40: =+F40*G40 -> 1.9038 | I40: Colores | J40: 131 | K40: 0.0501 | L40: =+J40*K40 -> 6.5631 | M40: Colores | N40: 233 | O40: 0.0501 | P40: =+N40*O40 -> 11.6733 | Q40: Colores | R40: 124 | S40: 0.0501 | T40: =+R40*S40 -> 6.2124 | U40: Colores | V40: 2 | W40: 0.0501 | X40: =+V40*W40 -> 0.1002 | Y40: Colores | Z40: 19 | AA40: 0.0501 | AB40: =+Z40*AA40 -> 0.9519 | AC40: Colores | AD40: 0 | AE40: 0.0501 | AF40: =+AD40*AE40 -> 0
B41: X3B7003944 | C41: Reservas | D41: B/N | G41: 0.0198 | H41: =+F41*G41 -> 0 | I41: B/N | K41: 0.0198 | L41: =+J41*K41 -> 0 | M41: B/N | N41: 1162 | O41: 0.0198 | P41: =+N41*O41 -> 23.0076 | Q41: B/N | R41: 372 | S41: 0.0198 | T41: =+R41*S41 -> 7.3656 | U41: B/N | V41: 372 | W41: 0.0198 | X41: =+V41*W41 -> 7.3656 | Y41: B/N | AA41: 0.0198 | AB41: =+Z41*AA41 -> 0 | AC41: B/N | AD41: 0 | AE41: 0.0198 | AF41: =+AD41*AE41 -> 0
B42: X3B7003944 | C42: Reservas | D42: Colores | G42: 0.0501 | H42: =+F42*G42 -> 0 | I42: Colores | K42: 0.0501 | L42: =+J42*K42 -> 0 | M42: Colores | N42: 342 | O42: 0.0501 | P42: =+N42*O42 -> 17.1342 | Q42: Colores | S42: 0.0501 | T42: =+R42*S42 -> 0 | U42: Colores | V42: 37 | W42: 0.0501 | X42: =+V42*W42 -> 1.8537 | Y42: Colores | AA42: 0.0501 | AB42: =+Z42*AA42 -> 0 | AC42: Colores | AD42: 0 | AE42: 0.0501 | AF42: =+AD42*AE42 -> 0
B43: X3B7003739 | C43: Banquetes | D43: B/N | F43: 192 | G43: 0.0198 | H43: =+F43*G43 -> 3.8016 | I43: B/N | J43: 382 | K43: 0.0198 | L43: =+J43*K43 -> 7.5636 | M43: B/N | O43: 0.0198 | P43: =+N43*O43 -> 0 | Q43: B/N | S43: 0.0198 | T43: =+R43*S43 -> 0 | U43: B/N | V43: 814 | W43: 0.0198 | X43: =+V43*W43 -> 16.1172 | Y43: B/N | Z43: 259 | AA43: 0.0198 | AB43: =+Z43*AA43 -> 5.1282 | AC43: B/N | AD43: 0 | AE43: 0.0198 | AF43: =+AD43*AE43 -> 0
B44: X3B7003739 | C44: Banquetes | D44: Colores | G44: 0.0501 | H44: =+F44*G44 -> 0 | I44: Colores | J44: 2 | K44: 0.0501 | L44: =+J44*K44 -> 0.1002 | M44: Colores | O44: 0.0501 | P44: =+N44*O44 -> 0 | Q44: Colores | S44: 0.0501 | T44: =+R44*S44 -> 0 | U44: Colores | V44: 2 | W44: 0.0501 | X44: =+V44*W44 -> 0.1002 | Y44: Colores | AA44: 0.0501 | AB44: =+Z44*AA44 -> 0 | AC44: Colores | AD44: 0 | AE44: 0.0501 | AF44: =+AD44*AE44 -> 0
B45: MXC300 45000119 | C45: AyB | D45: B/N | F45: 861 | G45: 0.0136 | H45: =+F45*G45 -> 11.7096 | I45: B/N | J45: 302 | K45: 0.0136 | L45: =+J45*K45 -> 4.1072 | M45: B/N | N45: 532 | O45: 0.0136 | P45: =+N45*O45 -> 7.2352 | Q45: B/N | R45: 776 | S45: 0.0136 | T45: =+R45*S45 -> 10.5536 | U45: B/N | V45: 654 | W45: 0.0136 | X45: =+V45*W45 -> 8.8944 | Y45: B/N | Z45: 536 | AA45: 0.0136 | AB45: =+Z45*AA45 -> 7.2896 | AC45: B/N | AD45: 1049 | AE45: 0.0136 | AF45: =+AD45*AE45 -> 14.2664
B46: MXC300 45000119 | C46: AyB | D46: Colores | F46: 727 | G46: 0.0601 | H46: =+F46*G46 -> 43.6927 | I46: Colores | J46: 515 | K46: 0.0601 | L46: =+J46*K46 -> 30.9515 | M46: Colores | N46: 718 | O46: 0.0601 | P46: =+N46*O46 -> 43.1518 | Q46: Colores | R46: 893 | S46: 0.0601 | T46: =+R46*S46 -> 53.6693 | U46: Colores | V46: 1216 | W46: 0.0601 | X46: =+V46*W46 -> 73.0816 | Y46: Colores | Z46: 690 | AA46: 0.0601 | AB46: =+Z46*AA46 -> 41.469 | AC46: Colores | AD46: 1039 | AE46: 0.0601 | AF46: =+AD46*AE46 -> 62.4439
B47: X3B2001312 | C47: Ventas - B&N | D47: B/N | F47: 1386 | G47: 0.0202 | H47: =+F47*G47 -> 27.9972 | I47: B/N | J47: 1094 | K47: 0.0202 | L47: =+J47*K47 -> 22.0988 | M47: B/N | N47: 1539 | O47: 0.0202 | P47: =+N47*O47 -> 31.0878 | Q47: B/N | R47: 1401 | S47: 0.0202 | T47: =+R47*S47 -> 28.3002 | U47: B/N | V47: 1418 | W47: 0.0202 | X47: =+V47*W47 -> 28.6436 | Y47: B/N | Z47: 617 | AA47: 0.0202 | AB47: =+Z47*AA47 -> 12.4634 | AC47: B/N | AD47: 0 | AE47: 0.0202 | AF47: =+AD47*AE47 -> 0
B48: X3B2001312 | C48: Ventas - B&N | D48: Colores | F48: 494 | G48: 0.0519 | H48: =+F48*G48 -> 25.6386 | I48: Colores | J48: 211 | K48: 0.0519 | L48: =+J48*K48 -> 10.9509 | M48: Colores | N48: 339 | O48: 0.0519 | P48: =+N48*O48 -> 17.5941 | Q48: Colores | R48: 560 | S48: 0.0519 | T48: =+R48*S48 -> 29.064 | U48: Colores | V48: 594 | W48: 0.0519 | X48: =+V48*W48 -> 30.8286 | Y48: Colores | Z48: 953 | AA48: 0.0519 | AB48: =+Z48*AA48 -> 49.4607 | AC48: Colores | AD48: 0 | AE48: 0.0519 | AF48: =+AD48*AE48 -> 0
B49: MF426QFX06116 | C49: Auditor nocturno | D49: B/N | F49: 12691 | G49: 0.0111 | H49: =+F49*G49 -> 140.8701 | I49: B/N | J49: 7836 | K49: 0.0111 | L49: =+J49*K49 -> 86.9796 | M49: B/N | N49: 9662 | O49: 0.0111 | P49: =+N49*O49 -> 107.2482 | Q49: B/N | R49: 6545 | S49: 0.0111 | T49: =+R49*S49 -> 72.6495 | U49: B/N | W49: 0.0111 | X49: =+V49*W49 -> 0 | Y49: B/N | Z49: 2508 | AA49: 0.0111 | AB49: =+Z49*AA49 -> 27.8388 | AC49: B/N | AD49: 10067 | AE49: 0.0111 | AF49: =+AD49*AE49 -> 111.7437
B50: MF426QFX06116 | C50: Auditor nocturno | D50: Colores | G50: 0.0545 | H50: =+F50*G50 -> 0 | I50: Colores | K50: 0.0545 | L50: =+J50*K50 -> 0 | M50: Colores | O50: 0.0545 | P50: =+N50*O50 -> 0 | Q50: Colores | S50: 0.0545 | T50: =+R50*S50 -> 0 | U50: Colores | W50: 0.0545 | X50: =+V50*W50 -> 0 | Y50: Colores | AA50: 0.0545 | AB50: =+Z50*AA50 -> 0 | AC50: Colores | AE50: 0.0545 | AF50: =+AD50*AE50 -> 0
B51: MF426QFX06245 | C51: FD 3,4 | D51: B/N | F51: 5406 | G51: 0.0111 | H51: =+F51*G51 -> 60.0066 | I51: B/N | J51: 4102 | K51: 0.0111 | L51: =+J51*K51 -> 45.5322 | M51: B/N | N51: 3187 | O51: 0.0111 | P51: =+N51*O51 -> 35.3757 | Q51: B/N | R51: 23928 | S51: 0.0111 | T51: =+R51*S51 -> 265.6008 | U51: B/N | V51: 3507 | W51: 0.0111 | X51: =+V51*W51 -> 38.9277 | Y51: B/N | Z51: 1827 | AA51: 0.0111 | AB51: =+Z51*AA51 -> 20.2797 | AC51: B/N | AD51: 7304 | AE51: 0.0111 | AF51: =+AD51*AE51 -> 81.0744
B52: MF426QFX06245 | C52: FD 3,4 | D52: Colores | G52: 0.0501 | H52: =+F52*G52 -> 0 | I52: Colores | K52: 0.0501 | L52: =+J52*K52 -> 0 | M52: Colores | O52: 0.0501 | P52: =+N52*O52 -> 0 | Q52: Colores | S52: 0.0501 | T52: =+R52*S52 -> 0 | U52: Colores | W52: 0.0501 | X52: =+V52*W52 -> 0 | Y52: Colores | AA52: 0.0501 | AB52: =+Z52*AA52 -> 0 | AC52: Colores | AE52: 0.0501 | AF52: =+AD52*AE52 -> 0
B53: MF426QFX06113 | C53: FD 1,2 | D53: B/N | F53: 977 | G53: 0.0111 | H53: =+F53*G53 -> 10.8447 | I53: B/N | J53: 618 | K53: 0.0111 | L53: =+J53*K53 -> 6.8598 | M53: B/N | N53: 347 | O53: 0.0111 | P53: =+N53*O53 -> 3.8517 | Q53: B/N | R53: 474 | S53: 0.0111 | T53: =+R53*S53 -> 5.2614 | U53: B/N | V53: 465 | W53: 0.0111 | X53: =+V53*W53 -> 5.1615 | Y53: B/N | Z53: 509 | AA53: 0.0111 | AB53: =+Z53*AA53 -> 5.6499 | AC53: B/N | AD53: 641 | AE53: 0.0111 | AF53: =+AD53*AE53 -> 7.1151
B54: MF426QFX06113 | C54: FD 1,2 | D54: Colores | G54: 0.0501 | H54: =+F54*G54 -> 0 | I54: Colores | K54: 0.0501 | L54: =+J54*K54 -> 0 | M54: Colores | O54: 0.0501 | P54: =+N54*O54 -> 0 | Q54: Colores | S54: 0.0501 | T54: =+R54*S54 -> 0 | U54: Colores | W54: 0.0501 | X54: =+V54*W54 -> 0 | Y54: Colores | AA54: 0.0501 | AB54: =+Z54*AA54 -> 0 | AC54: Colores | AE54: 0.0501 | AF54: =+AD54*AE54 -> 0
F55: =SUM(F7:F54) -> 34954 | J55: =SUM(J7:J54) -> 28473 | N55: =SUM(N7:N54) -> 36089 | R55: =SUM(R7:R54) -> 47535 | V55: =SUM(V7:V54) -> 22448 | Z55: =SUM(Z7:Z54) -> 19179 | AD55: =SUM(AD7:AD54) -> 59696
D56: TOTAL COPIAS | H56: =SUM(H7:H54) -> 606.1495 | I56: TOTAL COPIAS | L56: =SUM(L7:L54) -> 505.8129 | M56: TOTAL COPIAS | P56: =SUM(P7:P54) -> 785.894 | Q56: TOTAL COPIAS | T56: =SUM(T7:T54) -> 732.2725 | U56: TOTAL COPIAS | X56: =SUM(X7:X54) -> 483.4437 | Y56: TOTAL COPIAS | AB56: =SUM(AB7:AB54) -> 406.1935 | AC56: TOTAL COPIAS | AF56: =SUM(AF7:AF54) -> 928.7787
D57: TOTAL RENTA | H57: 390.6 | I57: TOTAL RENTA | L57: 390.6 | M57: TOTAL RENTA | P57: 390.6 | Q57: TOTAL RENTA | T57: 390.6 | U57: TOTAL RENTA | X57: 390.6 | Y57: TOTAL RENTA | AB57: 390.6 | AC57: TOTAL RENTA | AF57: 390.6
D59: FACTURACION | H59: =+H56+H57 -> 996.7495 | I59: FACTURACION | L59: =+L56+L57 -> 896.4129 | M59: FACTURACION | P59: =+P56+P57 -> 1176.494 | Q59: FACTURACION | T59: =+T56+T57 -> 1122.8725 | U59: FACTURACION | X59: =+X56+X57 -> 874.0437 | Y59: FACTURACION | AB59: =+AB56+AB57 -> 796.7935 | AC59: FACTURACION | AF59: =+AF56+AF57 -> 1319.3787
D60: FACTURA FISICA | H60: 1027.29 | I60: FACTURA FISICA | L60: 896.49 | M60: FACTURA FISICA | P60: 1176.48 | Q60: FACTURA FISICA | T60: 1122.86 | U60: FACTURA FISICA | X60: 874.04 | Y60: FACTURA FISICA | AB60: 874.04 | AC60: FACTURA FISICA | AF60: 874.04
D61: DIF | H61: =+H60-H59 -> 30.5405 | I61: DIF | L61: =+L60-L59 -> 0.0771 | M61: DIF | P61: =+P60-P59 -> -0.014 | Q61: DIF | T61: =+T60-T59 -> -0.0125 | U61: DIF | X61: =+X60-X59 -> -0.0037 | Y61: DIF | AB61: =+AB60-AB59 -> 77.2465 | AC61: DIF | AF61: =+AF60-AF59 -> -445.3387
L63: =+L59/H59-1 -> -0.10066381 | P63: =+P59/L59-1 -> 0.31244653 | T63: =+T59/P59-1 -> -0.045577368 | X63: =+X59/T59-1 -> -0.22160023 | AB63: =+AB59/X59-1 -> -0.088382537 | AF63: =+AF59/AB59-1 -> 0.65586027

Sheet ff
B2: REPORTE DE COPIAS - REPRODATA 2021-2022
D5: 44562 | H5: 44593 | L5: 44621 | P5: 44652 | T5: 44682 | X5: 44713
B6: SERIE DE EQUIPO | C6: UBICACION / AREA | D6: Tipo | E6: Cantidad | F6: Precio $ | G6: Total | H6: Tipo | I6: Cantidad | J6: Precio $ | K6: Total | L6: Tipo | M6: Cantidad | N6: Precio $ | O6: Total | P6: Tipo | Q6: Cantidad | R6: Precio $ | S6: Total | T6: Tipo | U6: Cantidad | V6: Precio $ | W6: Total | X6: Tipo | Y6: Cantidad | Z6: Precio $ | AA6: Total
B7: X3B7003659 | C7: Asistente Gerencia General | D7: B/N | F7: 0.0198 | G7: =+E7*F7 -> 0 | H7: B/N | J7: 0.0198 | K7: =+I7*J7 -> 0 | L7: B/N | N7: 0.0198 | O7: =+M7*N7 -> 0 | P7: B/N | R7: 0.0198 | S7: =+Q7*R7 -> 0 | T7: B/N | V7: 0.0198 | W7: =+U7*V7 -> 0 | X7: B/N | Z7: 0.0198 | AA7: =+Y7*Z7 -> 0
B8: X3B7003659 | C8: Asistente Gerencia General | D8: Colores | F8: 0.0501 | G8: =+E8*F8 -> 0 | H8: Colores | J8: 0.0501 | K8: =+I8*J8 -> 0 | L8: Colores | N8: 0.0501 | O8: =+M8*N8 -> 0 | P8: Colores | R8: 0.0501 | S8: =+Q8*R8 -> 0 | T8: Colores | V8: 0.0501 | W8: =+U8*V8 -> 0 | X8: Colores | Z8: 0.0501 | AA8: =+Y8*Z8 -> 0
B9: X3B7003739 | C9: Banquetes | D9: B/N | F9: 0.0198 | G9: =+E9*F9 -> 0 | H9: B/N | J9: 0.0198 | K9: =+I9*J9 -> 0 | L9: B/N | N9: 0.0198 | O9: =+M9*N9 -> 0 | P9: B/N | R9: 0.0198 | S9: =+Q9*R9 -> 0 | T9: B/N | V9: 0.0198 | W9: =+U9*V9 -> 0 | X9: B/N | Z9: 0.0198 | AA9: =+Y9*Z9 -> 0
B10: X3B7003739 | C10: Banquetes | D10: Colores | F10: 0.0501 | G10: =+E10*F10 -> 0 | H10: Colores | J10: 0.0501 | K10: =+I10*J10 -> 0 | L10: Colores | N10: 0.0501 | O10: =+M10*N10 -> 0 | P10: Colores | R10: 0.0501 | S10: =+Q10*R10 -> 0 | T10: Colores | V10: 0.0501 | W10: =+U10*V10 -> 0 | X10: Colores | Z10: 0.0501 | AA10: =+Y10*Z10 -> 0
B11: X3B7003712 | C11: Bodegas | D11: B/N | F11: 0.0198 | G11: =+E11*F11 -> 0 | H11: B/N | J11: 0.0198 | K11: =+I11*J11 -> 0 | L11: B/N | N11: 0.0198 | O11: =+M11*N11 -> 0 | P11: B/N | R11: 0.0198 | S11: =+Q11*R11 -> 0 | T11: B/N | V11: 0.0198 | W11: =+U11*V11 -> 0 | X11: B/N | Z11: 0.0198 | AA11: =+Y11*Z11 -> 0
B12: X3B7003712 | C12: Bodegas | D12: Colores | F12: 0.0501 | G12: =+E12*F12 -> 0 | H12: Colores | J12: 0.0501 | K12: =+I12*J12 -> 0 | L12: Colores | N12: 0.0501 | O12: =+M12*N12 -> 0 | P12: Colores | R12: 0.0501 | S12: =+Q12*R12 -> 0 | T12: Colores | V12: 0.0501 | W12: =+U12*V12 -> 0 | X12: Colores | Z12: 0.0501 | AA12: =+Y12*Z12 -> 0
B13: X3B7003581 | C13: C&M Oficina | D13: B/N | F13: 0.0198 | G13: =+E13*F13 -> 0 | H13: B/N | J13: 0.0198 | K13: =+I13*J13 -> 0 | L13: B/N | N13: 0.0198 | O13: =+M13*N13 -> 0 | P13: B/N | R13: 0.0198 | S13: =+Q13*R13 -> 0 | T13: B/N | V13: 0.0198 | W13: =+U13*V13 -> 0 | X13: B/N | Z13: 0.0198 | AA13: =+Y13*Z13 -> 0
B14: X3B7003581 | C14: C&M Oficina | D14: Colores | F14: 0.0501 | G14: =+E14*F14 -> 0 | H14: Colores | J14: 0.0501 | K14: =+I14*J14 -> 0 | L14: Colores | N14: 0.0501 | O14: =+M14*N14 -> 0 | P14: Colores | R14: 0.0501 | S14: =+Q14*R14 -> 0 | T14: Colores | V14: 0.0501 | W14: =+U14*V14 -> 0 | X14: Colores | Z14: 0.0501 | AA14: =+Y14*Z14 -> 0
A15: No se usa | B15: X3B7003661 | C15: Disponible | D15: B/N | F15: 0.0198 | G15: =+E15*F15 -> 0 | H15: B/N | J15: 0.0198 | K15: =+I15*J15 -> 0 | L15: B/N | N15: 0.0198 | O15: =+M15*N15 -> 0 | P15: B/N | R15: 0.0198 | S15: =+Q15*R15 -> 0 | T15: B/N | V15: 0.0198 | W15: =+U15*V15 -> 0 | X15: B/N | Z15: 0.0198 | AA15: =+Y15*Z15 -> 0
A16: No se usa | B16: X3B7003661 | C16: Disponible | D16: Colores | F16: 0.0501 | G16: =+E16*F16 -> 0 | H16: Colores | J16: 0.0501 | K16: =+I16*J16 -> 0 | L16: Colores | N16: 0.0501 | O16: =+M16*N16 -> 0 | P16: Colores | R16: 0.0501 | S16: =+Q16*R16 -> 0 | T16: Colores | V16: 0.0501 | W16: =+U16*V16 -> 0 | X16: Colores | Z16: 0.0501 | AA16: =+Y16*Z16 -> 0
B17: X3B7003671 | C17: Compras | D17: B/N | F17: 0.0198 | G17: =+E17*F17 -> 0 | H17: B/N | J17: 0.0198 | K17: =+I17*J17 -> 0 | L17: B/N | N17: 0.0198 | O17: =+M17*N17 -> 0 | P17: B/N | R17: 0.0198 | S17: =+Q17*R17 -> 0 | T17: B/N | V17: 0.0198 | W17: =+U17*V17 -> 0 | X17: B/N | Z17: 0.0198 | AA17: =+Y17*Z17 -> 0
B18: X3B7003671 | C18: Compras | D18: Colores | F18: 0.0501 | G18: =+E18*F18 -> 0 | H18: Colores | J18: 0.0501 | K18: =+I18*J18 -> 0 | L18: Colores | N18: 0.0501 | O18: =+M18*N18 -> 0 | P18: Colores | R18: 0.0501 | S18: =+Q18*R18 -> 0 | T18: Colores | V18: 0.0501 | W18: =+U18*V18 -> 0 | X18: Colores | Z18: 0.0501 | AA18: =+Y18*Z18 -> 0
B19: X3B7003656 | C19: Concierge | D19: B/N | F19: 0.0198 | G19: =+E19*F19 -> 0 | H19: B/N | J19: 0.0198 | K19: =+I19*J19 -> 0 | L19: B/N | N19: 0.0198 | O19: =+M19*N19 -> 0 | P19: B/N | R19: 0.0198 | S19: =+Q19*R19 -> 0 | T19: B/N | V19: 0.0198 | W19: =+U19*V19 -> 0 | X19: B/N | Z19: 0.0198 | AA19: =+Y19*Z19 -> 0
B20: X3B7003656 | C20: Concierge | D20: Colores | F20: 0.0501 | G20: =+E20*F20 -> 0 | H20: Colores | J20: 0.0501 | K20: =+I20*J20 -> 0 | L20: Colores | N20: 0.0501 | O20: =+M20*N20 -> 0 | P20: Colores | R20: 0.0501 | S20: =+Q20*R20 -> 0 | T20: Colores | V20: 0.0501 | W20: =+U20*V20 -> 0 | X20: Colores | Z20: 0.0501 | AA20: =+Y20*Z20 -> 0
B21: X3B7003690 | C21: Cuadres | D21: B/N | F21: 0.0198 | G21: =+E21*F21 -> 0 | H21: B/N | J21: 0.0198 | K21: =+I21*J21 -> 0 | L21: B/N | N21: 0.0198 | O21: =+M21*N21 -> 0 | P21: B/N | R21: 0.0198 | S21: =+Q21*R21 -> 0 | T21: B/N | V21: 0.0198 | W21: =+U21*V21 -> 0 | X21: B/N | Z21: 0.0198 | AA21: =+Y21*Z21 -> 0
B22: X3B7003690 | C22: Cuadres | D22: Colores | F22: 0.0501 | G22: =+E22*F22 -> 0 | H22: Colores | J22: 0.0501 | K22: =+I22*J22 -> 0 | L22: Colores | N22: 0.0501 | O22: =+M22*N22 -> 0 | P22: Colores | R22: 0.0501 | S22: =+Q22*R22 -> 0 | T22: Colores | V22: 0.0501 | W22: =+U22*V22 -> 0 | X22: Colores | Z22: 0.0501 | AA22: =+Y22*Z22 -> 0
B23: X3B7003703 | C23: GYM | D23: B/N | F23: 0.0198 | G23: =+E23*F23 -> 0 | H23: B/N | J23: 0.0198 | K23: =+I23*J23 -> 0 | L23: B/N | N23: 0.0198 | O23: =+M23*N23 -> 0 | P23: B/N | R23: 0.0198 | S23: =+Q23*R23 -> 0 | T23: B/N | V23: 0.0198 | W23: =+U23*V23 -> 0 | X23: B/N | Z23: 0.0198 | AA23: =+Y23*Z23 -> 0
B24: X3B7003703 | C24: GYM | D24: Colores | F24: 0.0501 | G24: =+E24*F24 -> 0 | H24: Colores | J24: 0.0501 | K24: =+I24*J24 -> 0 | L24: Colores | N24: 0.0501 | O24: =+M24*N24 -> 0 | P24: Colores | R24: 0.0501 | S24: =+Q24*R24 -> 0 | T24: Colores | V24: 0.0501 | W24: =+U24*V24 -> 0 | X24: Colores | Z24: 0.0501 | AA24: =+Y24*Z24 -> 0
B25: X3B7003751 | C25: Housekeeping | D25: B/N | F25: 0.0198 | G25: =+E25*F25 -> 0 | H25: B/N | J25: 0.0198 | K25: =+I25*J25 -> 0 | L25: B/N | N25: 0.0198 | O25: =+M25*N25 -> 0 | P25: B/N | R25: 0.0198 | S25: =+Q25*R25 -> 0 | T25: B/N | V25: 0.0198 | W25: =+U25*V25 -> 0 | X25: B/N | Z25: 0.0198 | AA25: =+Y25*Z25 -> 0
B26: X3B7003751 | C26: Housekeeping | D26: Colores | F26: 0.0501 | G26: =+E26*F26 -> 0 | H26: Colores | J26: 0.0501 | K26: =+I26*J26 -> 0 | L26: Colores | N26: 0.0501 | O26: =+M26*N26 -> 0 | P26: Colores | R26: 0.0501 | S26: =+Q26*R26 -> 0 | T26: Colores | V26: 0.0501 | W26: =+U26*V26 -> 0 | X26: Colores | Z26: 0.0501 | AA26: =+Y26*Z26 -> 0
A27: No se usa | B27: X3B7003615 | C27: Disponible | D27: B/N | F27: 0.0198 | G27: =+E27*F27 -> 0 | H27: B/N | J27: 0.0198 | K27: =+I27*J27 -> 0 | L27: B/N | N27: 0.0198 | O27: =+M27*N27 -> 0 | P27: B/N | R27: 0.0198 | S27: =+Q27*R27 -> 0 | T27: B/N | V27: 0.0198 | W27: =+U27*V27 -> 0 | X27: B/N | Z27: 0.0198 | AA27: =+Y27*Z27 -> 0
A28: No se usa | B28: X3B7003615 | C28: Disponible | D28: Colores | F28: 0.0501 | G28: =+E28*F28 -> 0 | H28: Colores | J28: 0.0501 | K28: =+I28*J28 -> 0 | L28: Colores | N28: 0.0501 | O28: =+M28*N28 -> 0 | P28: Colores | R28: 0.0501 | S28: =+Q28*R28 -> 0 | T28: Colores | V28: 0.0501 | W28: =+U28*V28 -> 0 | X28: Colores | Z28: 0.0501 | AA28: =+Y28*Z28 -> 0
B29: X3B7003716 | C29: Limpieza | D29: B/N | F29: 0.0198 | G29: =+E29*F29 -> 0 | H29: B/N | J29: 0.0198 | K29: =+I29*J29 -> 0 | L29: B/N | N29: 0.0198 | O29: =+M29*N29 -> 0 | P29: B/N | R29: 0.0198 | S29: =+Q29*R29 -> 0 | T29: B/N | V29: 0.0198 | W29: =+U29*V29 -> 0 | X29: B/N | Z29: 0.0198 | AA29: =+Y29*Z29 -> 0
B30: X3B7003716 | C30: Limpieza | D30: Colores | F30: 0.0501 | G30: =+E30*F30 -> 0 | H30: Colores | J30: 0.0501 | K30: =+I30*J30 -> 0 | L30: Colores | N30: 0.0501 | O30: =+M30*N30 -> 0 | P30: Colores | R30: 0.0501 | S30: =+Q30*R30 -> 0 | T30: Colores | V30: 0.0501 | W30: =+U30*V30 -> 0 | X30: Colores | Z30: 0.0501 | AA30: =+Y30*Z30 -> 0
B31: X3B7003711 | C31: Oficina de Recepción | D31: B/N | F31: 0.0198 | G31: =+E31*F31 -> 0 | H31: B/N | J31: 0.0198 | K31: =+I31*J31 -> 0 | L31: B/N | N31: 0.0198 | O31: =+M31*N31 -> 0 | P31: B/N | R31: 0.0198 | S31: =+Q31*R31 -> 0 | T31: B/N | V31: 0.0198 | W31: =+U31*V31 -> 0 | X31: B/N | Z31: 0.0198 | AA31: =+Y31*Z31 -> 0
B32: X3B7003711 | C32: Oficina de Recepción | D32: Colores | F32: 0.0501 | G32: =+E32*F32 -> 0 | H32: Colores | J32: 0.0501 | K32: =+I32*J32 -> 0 | L32: Colores | N32: 0.0501 | O32: =+M32*N32 -> 0 | P32: Colores | R32: 0.0501 | S32: =+Q32*R32 -> 0 | T32: Colores | V32: 0.0501 | W32: =+U32*V32 -> 0 | X32: Colores | Z32: 0.0501 | AA32: =+Y32*Z32 -> 0
A33: No se usa | B33: X3B7003828 | C33: Disponible | D33: B/N | F33: 0.0198 | G33: =+E33*F33 -> 0 | H33: B/N | J33: 0.0198 | K33: =+I33*J33 -> 0 | L33: B/N | N33: 0.0198 | O33: =+M33*N33 -> 0 | P33: B/N | R33: 0.0198 | S33: =+Q33*R33 -> 0 | T33: B/N | V33: 0.0198 | W33: =+U33*V33 -> 0 | X33: B/N | Z33: 0.0198 | AA33: =+Y33*Z33 -> 0
A34: No se usa | B34: X3B7003828 | C34: Disponible | D34: Colores | F34: 0.0501 | G34: =+E34*F34 -> 0 | H34: Colores | J34: 0.0501 | K34: =+I34*J34 -> 0 | L34: Colores | N34: 0.0501 | O34: =+M34*N34 -> 0 | P34: Colores | R34: 0.0501 | S34: =+Q34*R34 -> 0 | T34: Colores | V34: 0.0501 | W34: =+U34*V34 -> 0 | X34: Colores | Z34: 0.0501 | AA34: =+Y34*Z34 -> 0
B35: X3B7003944 | C35: Reservas | D35: B/N | F35: 0.0198 | G35: =+E35*F35 -> 0 | H35: B/N | J35: 0.0198 | K35: =+I35*J35 -> 0 | L35: B/N | N35: 0.0198 | O35: =+M35*N35 -> 0 | P35: B/N | R35: 0.0198 | S35: =+Q35*R35 -> 0 | T35: B/N | V35: 0.0198 | W35: =+U35*V35 -> 0 | X35: B/N | Z35: 0.0198 | AA35: =+Y35*Z35 -> 0
B36: X3B7003944 | C36: Reservas | D36: Colores | F36: 0.0501 | G36: =+E36*F36 -> 0 | H36: Colores | J36: 0.0501 | K36: =+I36*J36 -> 0 | L36: Colores | N36: 0.0501 | O36: =+M36*N36 -> 0 | P36: Colores | R36: 0.0501 | S36: =+Q36*R36 -> 0 | T36: Colores | V36: 0.0501 | W36: =+U36*V36 -> 0 | X36: Colores | Z36: 0.0501 | AA36: =+Y36*Z36 -> 0
B37: X3B7003660 | C37: Room Service | D37: B/N | F37: 0.0198 | G37: =+E37*F37 -> 0 | H37: B/N | J37: 0.0198 | K37: =+I37*J37 -> 0 | L37: B/N | N37: 0.0198 | O37: =+M37*N37 -> 0 | P37: B/N | R37: 0.0198 | S37: =+Q37*R37 -> 0 | T37: B/N | V37: 0.0198 | W37: =+U37*V37 -> 0 | X37: B/N | Z37: 0.0198 | AA37: =+Y37*Z37 -> 0
B38: X3B7003660 | C38: Room Service | D38: Colores | F38: 0.0501 | G38: =+E38*F38 -> 0 | H38: Colores | J38: 0.0501 | K38: =+I38*J38 -> 0 | L38: Colores | N38: 0.0501 | O38: =+M38*N38 -> 0 | P38: Colores | R38: 0.0501 | S38: =+Q38*R38 -> 0 | T38: Colores | V38: 0.0501 | W38: =+U38*V38 -> 0 | X38: Colores | Z38: 0.0501 | AA38: =+Y38*Z38 -> 0
B39: X3B7003609 | C39: Talento y Cultura | D39: B/N | F39: 0.0198 | G39: =+E39*F39 -> 0 | H39: B/N | J39: 0.0198 | K39: =+I39*J39 -> 0 | L39: B/N | N39: 0.0198 | O39: =+M39*N39 -> 0 | P39: B/N | R39: 0.0198 | S39: =+Q39*R39 -> 0 | T39: B/N | V39: 0.0198 | W39: =+U39*V39 -> 0 | X39: B/N | Z39: 0.0198 | AA39: =+Y39*Z39 -> 0
B40: X3B7003609 | C40: Talento y Cultura | D40: Colores | F40: 0.0501 | G40: =+E40*F40 -> 0 | H40: Colores | J40: 0.0501 | K40: =+I40*J40 -> 0 | L40: Colores | N40: 0.0501 | O40: =+M40*N40 -> 0 | P40: Colores | R40: 0.0501 | S40: =+Q40*R40 -> 0 | T40: Colores | V40: 0.0501 | W40: =+U40*V40 -> 0 | X40: Colores | Z40: 0.0501 | AA40: =+Y40*Z40 -> 0
B41: MXC300 45000119 | C41: AyB | D41: B/N | F41: 0.0136 | G41: =+E41*F41 -> 0 | H41: B/N | J41: 0.0136 | K41: =+I41*J41 -> 0 | L41: B/N | N41: 0.0136 | O41: =+M41*N41 -> 0 | P41: B/N | R41: 0.0136 | S41: =+Q41*R41 -> 0 | T41: B/N | V41: 0.0136 | W41: =+U41*V41 -> 0 | X41: B/N | Z41: 0.0136 | AA41: =+Y41*Z41 -> 0
B42: MXC300 45000119 | C42: AyB | D42: Colores | F42: 0.0601 | G42: =+E42*F42 -> 0 | H42: Colores | J42: 0.0601 | K42: =+I42*J42 -> 0 | L42: Colores | N42: 0.0601 | O42: =+M42*N42 -> 0 | P42: Colores | R42: 0.0601 | S42: =+Q42*R42 -> 0 | T42: Colores | V42: 0.0601 | W42: =+U42*V42 -> 0 | X42: Colores | Z42: 0.0601 | AA42: =+Y42*Z42 -> 0
B43: X3B2001312 | C43: Ventas - B&N | D43: B/N | F43: 0.0202 | G43: =+E43*F43 -> 0 | H43: B/N | J43: 0.0202 | K43: =+I43*J43 -> 0 | L43: B/N | N43: 0.0202 | O43: =+M43*N43 -> 0 | P43: B/N | R43: 0.0202 | S43: =+Q43*R43 -> 0 | T43: B/N | V43: 0.0202 | W43: =+U43*V43 -> 0 | X43: B/N | Z43: 0.0202 | AA43: =+Y43*Z43 -> 0
B44: X3B2001312 | C44: Ventas - B&N | D44: Colores | F44: 0.0519 | G44: =+E44*F44 -> 0 | H44: Colores | J44: 0.0519 | K44: =+I44*J44 -> 0 | L44: Colores | N44: 0.0519 | O44: =+M44*N44 -> 0 | P44: Colores | R44: 0.0519 | S44: =+Q44*R44 -> 0 | T44: Colores | V44: 0.0519 | W44: =+U44*V44 -> 0 | X44: Colores | Z44: 0.0519 | AA44: =+Y44*Z44 -> 0
B45: MF426QFX06113 | C45: FD 1,2 | D45: B/N | F45: 0.0198 | G45: =+E45*F45 -> 0 | H45: B/N | J45: 0.0198 | K45: =+I45*J45 -> 0 | L45: B/N | N45: 0.0198 | O45: =+M45*N45 -> 0 | P45: B/N | R45: 0.0198 | S45: =+Q45*R45 -> 0 | T45: B/N | V45: 0.0198 | W45: =+U45*V45 -> 0 | X45: B/N | Z45: 0.0198 | AA45: =+Y45*Z45 -> 0
B46: MF426QFX06113 | C46: FD 1,2 | D46: Colores | F46: 0.0501 | G46: =+E46*F46 -> 0 | H46: Colores | J46: 0.0501 | K46: =+I46*J46 -> 0 | L46: Colores | N46: 0.0501 | O46: =+M46*N46 -> 0 | P46: Colores | R46: 0.0501 | S46: =+Q46*R46 -> 0 | T46: Colores | V46: 0.0501 | W46: =+U46*V46 -> 0 | X46: Colores | Z46: 0.0501 | AA46: =+Y46*Z46 -> 0
... B52: MF426QFX06116 | C52: Auditor nocturno | D52: Colores | F52: 0.0545 | G52: =+E52*F52 -> 0 | H52: Colores | J52: 0.0545 | K52: =+I52*J52 -> 0 | L52: Colores | N52: 0.0545 | O52: =+M52*N52 -> 0 | P52: Colores | R52: 0.0545 | S52: =+Q52*R52 -> 0 | T52: Colores | V52: 0.0545 | W52: =+U52*V52 -> 0 | X52: Colores | Z52: 0.0545 | AA52: =+Y52*Z52 -> 0
D54: TOTAL COPIAS | G54: =SUM(G7:G52) -> 0 | H54: TOTAL COPIAS | K54: =SUM(K7:K52) -> 0 | L54: TOTAL COPIAS | O54: =SUM(O7:O52) -> 0 | P54: TOTAL COPIAS | S54: =SUM(S7:S52) -> 0 | T54: TOTAL COPIAS | W54: =SUM(W7:W52) -> 0 | X54: TOTAL COPIAS | AA54: =SUM(AA7:AA52) -> 0
D55: TOTAL RENTA | G55: 390.6 | H55: TOTAL RENTA | K55: 390.6 | L55: TOTAL RENTA | O55: 390.6 | P55: TOTAL RENTA | S55: 390.6 | T55: TOTAL RENTA | W55: 390.6 | X55: TOTAL RENTA | AA55: 390.6
D57: FACTURACION | G57: =+G54+G55 -> 390.6 | H57: FACTURACION | K57: =+K54+K55 -> 390.6 | L57: FACTURACION | O57: =+O54+O55 -> 390.6 | P57: FACTURACION | S57: =+S54+S55 -> 390.6 | T57: FACTURACION | W57: =+W54+W55 -> 390.6 | X57: FACTURACION | AA57: =+AA54+AA55 -> 390.6
D59: B/N | E59: 0.0198 | H59: B/N | I59: 0.0198 | L59: B/N | M59: 0.0198 | P59: B/N | Q59: 0.0198 | T59: B/N | U59: 0.0198 | X59: B/N | Y59: 0.0198
D60: Color | E60: 0.0545 | H60: Color | I60: 0.0545 | L60: Color | M60: 0.0545 | P60: Color | Q60: 0.0545 | T60: Color | U60: 0.0545 | X60: Color | Y60: 0.0545
K63: =+K57/G57-1 -> 0 | O63: =+O57/K57-1 -> 0 | S63: =+S57/O57-1 -> 0 | W63: =+W57/S57-1 -> 0 | AA63: =+AA57/W57-1 -> 0

Sheet SAP
A1: Datos | B1: Monto | C1: Modelo | D1: S/N | E1: IP | F1: CECO | G1: Monto USD | H1: Cuenta | I1: Cuenta de mayor/Nombre SN | J1: Cuenta asociada | K1: Débito (ME) | L1: Crédito (ME) | M1: Débito | N1: Crédito | O1: Débito (MS) | P1: Crédito (MS) | Q1: Comentarios | R1: Referencia 1 | S1: Referencia 2 | T1: Centro de Costo | U1: Posición del formulario principal | V1: Cuenta destino | W1: Cuenta patrimonial | X1: Comp. destino | Y1: Procesado DC | Z1: Info socio de negocios | AA1: Info de terceros | AB1: Tipo doc. - Serie - Numero | AC1: Socio Negocios | AD1: Fecha Registro Ventas
A2: 01-F020-00027840 | B2: 1085.32 | C2: {=_xlfn.LET(_xlpm.idx,INT((_xlfn.SEQUENCE(COUNTA('2026-3'!E2:E85)*8,1,0))/2)+1,_xlpm.datosC,INDEX('2026-3'!C2:C85,_xlpm.idx),_xlpm.datosD,INDEX('2026-3'!D2:D85,_xlpm.idx),_xlpm.datosE,INDEX('2026-3'!E2:E85,_xlpm.idx),_xlpm.datosT,INDEX('2026-3'!T2:T85,_xlpm.idx),_xlpm.datosQR,IF(MOD(_xlfn.SEQUENCE(COUNTA('2026-3'!E2:E85)*8,1,1),2)=1,INDEX('2026-3'!Q2:Q85,_xlpm.idx),INDEX('2026-3'!R2:R85,_xlpm.idx)),_xlpm.datosS,INDEX('2026-3'!S2:S85,_xlpm.idx),_xlpm.resultado,_xlfn._xlws.SORT(CHOOSE({1,2,3,4,5,6},_xlpm.datosC,_xlpm.datosD,_xlpm.datosE,_xlpm.datosT,_xlpm.datosQR,_xlpm.datosS),4),_xlfn._xlws.FILTER(_xlpm.resultado,INDEX(_xlpm.resultado,,3)<>0))} -> IR-1643 | D2: 35E33608 | E2: 10.72.8.211 | F2: 101 | G2: 51.681905 | H2: 931221108 | L2: =IF(G2>0,G2,0) -> 51.681905 | M2: =ABS(+IF(G2<0,G2,0)) -> 0 | Q2: ="FOTOCOPIAS POR ALQUILER EQUIPO MULTIFUNCIONAL DEL 01-"&TEXT(MONTH($B$3),"00")&"-"&YEAR($B$3)&" AL "&TEXT(DAY($B$3),"00")&"-"&TEXT(MONTH($B$3),"00")&"-"&YEAR($B$3) -> FOTOCOPIAS POR ALQUILER EQUIPO MULTIFUNCIONAL DEL 01-03-2026 AL 31-03-2026 | S2: ="Factura N° " & $A$2 -> Factura N° 01-F020-00027840 | T2: =F2 -> 101
A3: FECHA | B3: 46112 | C3: IR-1643 | D3: 35E33608 | E3: 10.72.8.211 | F3: 101 | G3: 346.3824 | H3: 931221108 | L3: =IF(G3>0,G3,0) -> 346.3824 | M3: =ABS(+IF(G3<0,G3,0)) -> 0 | Q3: ="CONSUMO DE COPIAS "&D3 -> CONSUMO DE COPIAS 35E33608 | S3: ="Factura N° " & $A$2 -> Factura N° 01-F020-00027840 | T3: =F3 -> 101
C4: IR-1643 | D4: 35E33607 | E4: 10.72.8.153 | F4: 101 | G4: 51.681905 | H4: 931221108 | L4: =IF(G4>0,G4,0) -> 51.681905 | M4: =ABS(+IF(G4<0,G4,0)) -> 0 | Q4: ="FOTOCOPIAS POR ALQUILER EQUIPO MULTIFUNCIONAL DEL 01-"&TEXT(MONTH($B$3),"00")&"-"&YEAR($B$3)&" AL "&TEXT(DAY($B$3),"00")&"-"&TEXT(MONTH($B$3),"00")&"-"&YEAR($B$3) -> FOTOCOPIAS POR ALQUILER EQUIPO MULTIFUNCIONAL DEL 01-03-2026 AL 31-03-2026 | S4: ="Factura N° " & $A$2 -> Factura N° 01-F020-00027840 | T4: =F4 -> 101
C5: IR-1643 | D5: 35E33607 | E5: 10.72.8.153 | F5: 101 | G5: 85.848 | H5: 931221108 | L5: =IF(G5>0,G5,0) -> 85.848 | M5: =ABS(+IF(G5<0,G5,0)) -> 0 | Q5: ="CONSUMO DE COPIAS "&D5 -> CONSUMO DE COPIAS 35E33607 | S5: ="Factura N° " & $A$2 -> Factura N° 01-F020-00027840 | T5: =F5 -> 101
C6: WF-C5790 | D6: X3B7003711 | E6: 10.72.8.205 | F6: 101 | G6: 51.681905 | H6: 931221108 | L6: =IF(G6>0,G6,0) -> 51.681905 | M6: =ABS(+IF(G6<0,G6,0)) -> 0 | Q6: ="FOTOCOPIAS POR ALQUILER EQUIPO MULTIFUNCIONAL DEL 01-"&TEXT(MONTH($B$3),"00")&"-"&YEAR($B$3)&" AL "&TEXT(DAY($B$3),"00")&"-"&TEXT(MONTH($B$3),"00")&"-"&YEAR($B$3) -> FOTOCOPIAS POR ALQUILER EQUIPO MULTIFUNCIONAL DEL 01-03-2026 AL 31-03-2026 | S6: ="Factura N° " & $A$2 -> Factura N° 01-F020-00027840 | T6: =F6 -> 101
C7: WF-C5790 | D7: X3B7003711 | E7: 10.72.8.205 | F7: 101 | G7: 44.7064 | H7: 931221108 | L7: =IF(G7>0,G7,0) -> 44.7064 | M7: =ABS(+IF(G7<0,G7,0)) -> 0 | Q7: ="CONSUMO DE COPIAS "&D7 -> CONSUMO DE COPIAS X3B7003711 | S7: ="Factura N° " & $A$2 -> Factura N° 01-F020-00027840 | T7: =F7 -> 101
C8: WF-C5890 | D8: XBJZ017266 | E8: 10.72.8.229 | F8: 102 | G8: 51.681905 | H8: 931221108 | L8: =IF(G8>0,G8,0) -> 51.681905 | M8: =ABS(+IF(G8<0,G8,0)) -> 0 | Q8: ="FOTOCOPIAS POR ALQUILER EQUIPO MULTIFUNCIONAL DEL 01-"&TEXT(MONTH($B$3),"00")&"-"&YEAR($B$3)&" AL "&TEXT(DAY($B$3),"00")&"-"&TEXT(MONTH($B$3),"00")&"-"&YEAR($B$3) -> FOTOCOPIAS POR ALQUILER EQUIPO MULTIFUNCIONAL DEL 01-03-2026 AL 31-03-2026 | S8: ="Factura N° " & $A$2 -> Factura N° 01-F020-00027840 | T8: =F8 -> 102
C9: WF-C5890 | D9: XBJZ017266 | E9: 10.72.8.229 | F9: 102 | G9: 192.6536 | H9: 931221108 | L9: =IF(G9>0,G9,0) -> 192.6536 | M9: =ABS(+IF(G9<0,G9,0)) -> 0 | Q9: ="CONSUMO DE COPIAS "&D9 -> CONSUMO DE COPIAS XBJZ017266 | S9: ="Factura N° " & $A$2 -> Factura N° 01-F020-00027840 | T9: =F9 -> 102
C10: WF-C5890 | D10: XBJZ017603 | E10: 10.72.8.196 | F10: 103 | G10: 51.681905 | H10: 931221108 | L10: =IF(G10>0,G10,0) -> 51.681905 | M10: =ABS(+IF(G10<0,G10,0)) -> 0 | Q10: ="FOTOCOPIAS POR ALQUILER EQUIPO MULTIFUNCIONAL DEL 01-"&TEXT(MONTH($B$3),"00")&"-"&YEAR($B$3)&" AL "&TEXT(DAY($B$3),"00")&"-"&TEXT(MONTH($B$3),"00")&"-"&YEAR($B$3) -> FOTOCOPIAS POR ALQUILER EQUIPO MULTIFUNCIONAL DEL 01-03-2026 AL 31-03-2026 | S10: ="Factura N° " & $A$2 -> Factura N° 01-F020-00027840 | T10: =F10 -> 103
C11: WF-C5890 | D11: XBJZ017603 | E11: 10.72.8.196 | F11: 103 | G11: -1.3192 | H11: 931221108 | L11: =IF(G11>0,G11,0) -> 0 | M11: =ABS(+IF(G11<0,G11,0)) -> 1.3192 | Q11: ="CONSUMO DE COPIAS "&D11 -> CONSUMO DE COPIAS XBJZ017603 | S11: ="Factura N° " & $A$2 -> Factura N° 01-F020-00027840 | T11: =F11 -> 103
C12: WF-C5790 | D12: X3B7003661 | E12: 10.72.8.132 | F12: 200 | G12: 51.681905 | H12: 932341308 | L12: =IF(G12>0,G12,0) -> 51.681905 | M12: =ABS(+IF(G12<0,G12,0)) -> 0 | Q12: ="FOTOCOPIAS POR ALQUILER EQUIPO MULTIFUNCIONAL DEL 01-"&TEXT(MONTH($B$3),"00")&"-"&YEAR($B$3)&" AL "&TEXT(DAY($B$3),"00")&"-"&TEXT(MONTH($B$3),"00")&"-"&YEAR($B$3) -> FOTOCOPIAS POR ALQUILER EQUIPO MULTIFUNCIONAL DEL 01-03-2026 AL 31-03-2026 | S12: ="Factura N° " & $A$2 -> Factura N° 01-F020-00027840 | T12: =F12 -> 200
C13: WF-C5790 | D13: X3B7003661 | E13: 10.72.8.132 | F13: 200 | G13: 437.3624 | H13: 932341308 | L13: =IF(G13>0,G13,0) -> 437.3624 | M13: =ABS(+IF(G13<0,G13,0)) -> 0 | Q13: ="CONSUMO DE COPIAS "&D13 -> CONSUMO DE COPIAS X3B7003661 | S13: ="Factura N° " & $A$2 -> Factura N° 01-F020-00027840 | T13: =F13 -> 200
C14: WF-C5790 | D14: X3B7003876 | E14: 10.72.8.220 | F14: 200 | G14: 51.681905 | H14: 932341308 | L14: =IF(G14>0,G14,0) -> 51.681905 | M14: =ABS(+IF(G14<0,G14,0)) -> 0 | Q14: ="FOTOCOPIAS POR ALQUILER EQUIPO MULTIFUNCIONAL DEL 01-"&TEXT(MONTH($B$3),"00")&"-"&YEAR($B$3)&" AL "&TEXT(DAY($B$3),"00")&"-"&TEXT(MONTH($B$3),"00")&"-"&YEAR($B$3) -> FOTOCOPIAS POR ALQUILER EQUIPO MULTIFUNCIONAL DEL 01-03-2026 AL 31-03-2026 | S14: ="Factura N° " & $A$2 -> Factura N° 01-F020-00027840 | T14: =F14 -> 200
C15: WF-C5790 | D15: X3B7003876 | E15: 10.72.8.220 | F15: 200 | G15: 7.5656 | H15: 932341308 | L15: =IF(G15>0,G15,0) -> 7.5656 | M15: =ABS(+IF(G15<0,G15,0)) -> 0 | Q15: ="CONSUMO DE COPIAS "&D15 -> CONSUMO DE COPIAS X3B7003876 | S15: ="Factura N° " & $A$2 -> Factura N° 01-F020-00027840 | T15: =F15 -> 200
C16: WF-C5890 | D16: XBJZ021745 | E16: 10.72.8.219 | F16: 200 | G16: 51.681905 | H16: 932341308 | L16: =IF(G16>0,G16,0) -> 51.681905 | M16: =ABS(+IF(G16<0,G16,0)) -> 0 | Q16: ="FOTOCOPIAS POR ALQUILER EQUIPO MULTIFUNCIONAL DEL 01-"&TEXT(MONTH($B$3),"00")&"-"&YEAR($B$3)&" AL "&TEXT(DAY($B$3),"00")&"-"&TEXT(MONTH($B$3),"00")&"-"&YEAR($B$3) -> FOTOCOPIAS POR ALQUILER EQUIPO MULTIFUNCIONAL DEL 01-03-2026 AL 31-03-2026 | S16: ="Factura N° " & $A$2 -> Factura N° 01-F020-00027840 | T16: =F16 -> 200
C17: WF-C5890 | D17: XBJZ021745 | E17: 10.72.8.219 | F17: 200 | G17: 167.1496 | H17: 932341308 | L17: =IF(G17>0,G17,0) -> 167.1496 | M17: =ABS(+IF(G17<0,G17,0)) -> 0 | Q17: ="CONSUMO DE COPIAS "&D17 -> CONSUMO DE COPIAS XBJZ021745 | S17: ="Factura N° " & $A$2 -> Factura N° 01-F020-00027840 | T17: =F17 -> 200
C18: WF-C5790 | D18: X3B7003671 | E18: 10.72.8.208 | F18: 204 | G18: 51.681905 | H18: 932341308 | L18: =IF(G18>0,G18,0) -> 51.681905 | M18: =ABS(+IF(G18<0,G18,0)) -> 0 | Q18: ="FOTOCOPIAS POR ALQUILER EQUIPO MULTIFUNCIONAL DEL 01-"&TEXT(MONTH($B$3),"00")&"-"&YEAR($B$3)&" AL "&TEXT(DAY($B$3),"00")&"-"&TEXT(MONTH($B$3),"00")&"-"&YEAR($B$3) -> FOTOCOPIAS POR ALQUILER EQUIPO MULTIFUNCIONAL DEL 01-03-2026 AL 31-03-2026 | S18: ="Factura N° " & $A$2 -> Factura N° 01-F020-00027840 | T18: =F18 -> 204
C19: WF-C5790 | D19: X3B7003671 | E19: 10.72.8.208 | F19: 204 | G19: 1.8696 | H19: 932341308 | L19: =IF(G19>0,G19,0) -> 1.8696 | M19: =ABS(+IF(G19<0,G19,0)) -> 0 | Q19: ="CONSUMO DE COPIAS "&D19 -> CONSUMO DE COPIAS X3B7003671 | S19: ="Factura N° " & $A$2 -> Factura N° 01-F020-00027840 | T19: =F19 -> 204
C20: WF-C5790 | D20: X3B7003660 | E20: 10.72.8.204 | F20: 206 | G20: 51.681905 | H20: 932341308 | L20: =IF(G20>0,G20,0) -> 51.681905 | M20: =ABS(+IF(G20<0,G20,0)) -> 0 | Q20: ="FOTOCOPIAS POR ALQUILER EQUIPO MULTIFUNCIONAL DEL 01-"&TEXT(MONTH($B$3),"00")&"-"&YEAR($B$3)&" AL "&TEXT(DAY($B$3),"00")&"-"&TEXT(MONTH($B$3),"00")&"-"&YEAR($B$3) -> FOTOCOPIAS POR ALQUILER EQUIPO MULTIFUNCIONAL DEL 01-03-2026 AL 31-03-2026 | S20: ="Factura N° " & $A$2 -> Factura N° 01-F020-00027840 | T20: =F20 -> 206
C21: WF-C5790 | D21: X3B7003660 | E21: 10.72.8.204 | F21: 206 | G21: 81.9776 | H21: 932341308 | L21: =IF(G21>0,G21,0) -> 81.9776 | M21: =ABS(+IF(G21<0,G21,0)) -> 0 | Q21: ="CONSUMO DE COPIAS "&D21 -> CONSUMO DE COPIAS X3B7003660 | S21: ="Factura N° " & $A$2 -> Factura N° 01-F020-00027840 | T21: =F21 -> 206
C22: WF-C5790 | D22: X3B7002433 | E22: 10.72.8.191 | F22: 207 | G22: 51.681905 | H22: 932341308 | L22: =IF(G22>0,G22,0) -> 51.681905 | M22: =ABS(+IF(G22<0,G22,0)) -> 0 | Q22: ="FOTOCOPIAS POR ALQUILER EQUIPO MULTIFUNCIONAL DEL 01-"&TEXT(MONTH($B$3),"00")&"-"&YEAR($B$3)&" AL "&TEXT(DAY($B$3),"00")&"-"&TEXT(MONTH($B$3),"00")&"-"&YEAR($B$3) -> FOTOCOPIAS POR ALQUILER EQUIPO MULTIFUNCIONAL DEL 01-03-2026 AL 31-03-2026 | S22: ="Factura N° " & $A$2 -> Factura N° 01-F020-00027840 | T22: =F22 -> 207
C23: WF-C5790 | D23: X3B7002433 | E23: 10.72.8.191 | F23: 207 | G23: 174.176 | H23: 932341308 | L23: =IF(G23>0,G23,0) -> 174.176 | M23: =ABS(+IF(G23<0,G23,0)) -> 0 | Q23: ="CONSUMO DE COPIAS "&D23 -> CONSUMO DE COPIAS X3B7002433 | S23: ="Factura N° " & $A$2 -> Factura N° 01-F020-00027840 | T23: =F23 -> 207
C24: WF-C5790 | D24: X3B7003703 | E24: 10.9.10.153 | F24: 304 | G24: 51.681905 | H24: 933441108 | L24: =IF(G24>0,G24,0) -> 51.681905 | M24: =ABS(+IF(G24<0,G24,0)) -> 0 | Q24: ="FOTOCOPIAS POR ALQUILER EQUIPO MULTIFUNCIONAL DEL 01-"&TEXT(MONTH($B$3),"00")&"-"&YEAR($B$3)&" AL "&TEXT(DAY($B$3),"00")&"-"&TEXT(MONTH($B$3),"00")&"-"&YEAR($B$3) -> FOTOCOPIAS POR ALQUILER EQUIPO MULTIFUNCIONAL DEL 01-03-2026 AL 31-03-2026 | S24: ="Factura N° " & $A$2 -> Factura N° 01-F020-00027840 | T24: =F24 -> 304
C25: WF-C5790 | D25: X3B7003703 | E25: 10.9.10.153 | F25: 304 | G25: 55.46 | H25: 933441108 | L25: =IF(G25>0,G25,0) -> 55.46 | M25: =ABS(+IF(G25<0,G25,0)) -> 0 | Q25: ="CONSUMO DE COPIAS "&D25 -> CONSUMO DE COPIAS X3B7003703 | S25: ="Factura N° " & $A$2 -> Factura N° 01-F020-00027840 | T25: =F25 -> 304
C26: WF-C5890 | D26: XBJZ021772 | E26: 10.72.8.151 | F26: 401 | G26: 51.681905 | H26: 941231308 | L26: =IF(G26>0,G26,0) -> 51.681905 | M26: =ABS(+IF(G26<0,G26,0)) -> 0 | Q26: ="FOTOCOPIAS POR ALQUILER EQUIPO MULTIFUNCIONAL DEL 01-"&TEXT(MONTH($B$3),"00")&"-"&YEAR($B$3)&" AL "&TEXT(DAY($B$3),"00")&"-"&TEXT(MONTH($B$3),"00")&"-"&YEAR($B$3) -> FOTOCOPIAS POR ALQUILER EQUIPO MULTIFUNCIONAL DEL 01-03-2026 AL 31-03-2026 | S26: ="Factura N° " & $A$2 -> Factura N° 01-F020-00027840 | T26: =F26 -> 401
C27: WF-C5890 | D27: XBJZ021772 | E27: 10.72.8.151 | F27: 401 | G27: 8.8456 | H27: 941231308 | L27: =IF(G27>0,G27,0) -> 8.8456 | M27: =ABS(+IF(G27<0,G27,0)) -> 0 | Q27: ="CONSUMO DE COPIAS "&D27 -> CONSUMO DE COPIAS XBJZ021772 | S27: ="Factura N° " & $A$2 -> Factura N° 01-F020-00027840 | T27: =F27 -> 401
C28: WF-C5790 | D28: X3B7003739 | E28: 10.72.10.43 | F28: 402 | G28: 51.681905 | H28: 941231308 | L28: =IF(G28>0,G28,0) -> 51.681905 | M28: =ABS(+IF(G28<0,G28,0)) -> 0 | Q28: ="FOTOCOPIAS POR ALQUILER EQUIPO MULTIFUNCIONAL DEL 01-"&TEXT(MONTH($B$3),"00")&"-"&YEAR($B$3)&" AL "&TEXT(DAY($B$3),"00")&"-"&TEXT(MONTH($B$3),"00")&"-"&YEAR($B$3) -> FOTOCOPIAS POR ALQUILER EQUIPO MULTIFUNCIONAL DEL 01-03-2026 AL 31-03-2026 | S28: ="Factura N° " & $A$2 -> Factura N° 01-F020-00027840 | T28: =F28 -> 402
C29: WF-C5790 | D29: X3B7003739 | E29: 10.72.10.43 | F29: 402 | G29: -13.9128 | H29: 941231308 | L29: =IF(G29>0,G29,0) -> 0 | M29: =ABS(+IF(G29<0,G29,0)) -> 13.9128 | Q29: ="CONSUMO DE COPIAS "&D29 -> CONSUMO DE COPIAS X3B7003739 | S29: ="Factura N° " & $A$2 -> Factura N° 01-F020-00027840 | T29: =F29 -> 402
C30: IR-1730 | D30: QFX06245 | E30: 10.72.8.215 | F30: 403 | G30: 51.681905 | H30: 941231308 | L30: =IF(G30>0,G30,0) -> 51.681905 | M30: =ABS(+IF(G30<0,G30,0)) -> 0 | Q30: ="FOTOCOPIAS POR ALQUILER EQUIPO MULTIFUNCIONAL DEL 01-"&TEXT(MONTH($B$3),"00")&"-"&YEAR($B$3)&" AL "&TEXT(DAY($B$3),"00")&"-"&TEXT(MONTH($B$3),"00")&"-"&YEAR($B$3) -> FOTOCOPIAS POR ALQUILER EQUIPO MULTIFUNCIONAL DEL 01-03-2026 AL 31-03-2026 | S30: ="Factura N° " & $A$2 -> Factura N° 01-F020-00027840 | T30: =F30 -> 403
C31: IR-1730 | D31: QFX06245 | E31: 10.72.8.215 | F31: 403 | G31: -14.0784 | H31: 941231308 | L31: =IF(G31>0,G31,0) -> 0 | M31: =ABS(+IF(G31<0,G31,0)) -> 14.0784 | Q31: ="CONSUMO DE COPIAS "&D31 -> CONSUMO DE COPIAS QFX06245 | S31: ="Factura N° " & $A$2 -> Factura N° 01-F020-00027840 | T31: =F31 -> 403
C32: WF-C5890 | D32: XBJZ017602 | E32: 10.72.8.206 | F32: 403 | G32: 51.681905 | H32: 941231308 | L32: =IF(G32>0,G32,0) -> 51.681905 | M32: =ABS(+IF(G32<0,G32,0)) -> 0 | Q32: ="FOTOCOPIAS POR ALQUILER EQUIPO MULTIFUNCIONAL DEL 01-"&TEXT(MONTH($B$3),"00")&"-"&YEAR($B$3)&" AL "&TEXT(DAY($B$3),"00")&"-"&TEXT(MONTH($B$3),"00")&"-"&YEAR($B$3) -> FOTOCOPIAS POR ALQUILER EQUIPO MULTIFUNCIONAL DEL 01-03-2026 AL 31-03-2026 | S32: ="Factura N° " & $A$2 -> Factura N° 01-F020-00027840 | T32: =F32 -> 403
C33: WF-C5890 | D33: XBJZ017602 | E33: 10.72.8.206 | F33: 403 | G33: 41.7968 | H33: 941231308 | L33: =IF(G33>0,G33,0) -> 41.7968 | M33: =ABS(+IF(G33<0,G33,0)) -> 0 | Q33: ="CONSUMO DE COPIAS "&D33 -> CONSUMO DE COPIAS XBJZ017602 | S33: ="Factura N° " & $A$2 -> Factura N° 01-F020-00027840 | T33: =F33 -> 403
C34: MX-M3070 | D34: 9502370Y | E34: 10.72.8.207 | F34: 403 | G34: 51.681905 | H34: 941231308 | L34: =IF(G34>0,G34,0) -> 51.681905 | M34: =ABS(+IF(G34<0,G34,0)) -> 0 | Q34: ="FOTOCOPIAS POR ALQUILER EQUIPO MULTIFUNCIONAL DEL 01-"&TEXT(MONTH($B$3),"00")&"-"&YEAR($B$3)&" AL "&TEXT(DAY($B$3),"00")&"-"&TEXT(MONTH($B$3),"00")&"-"&YEAR($B$3) -> FOTOCOPIAS POR ALQUILER EQUIPO MULTIFUNCIONAL DEL 01-03-2026 AL 31-03-2026 | S34: ="Factura N° " & $A$2 -> Factura N° 01-F020-00027840 | T34: =F34 -> 403
C35: MX-M3070 | D35: 9502370Y | E35: 10.72.8.207 | F35: 403 | G35: 89.4768 | H35: 941231308 | L35: =IF(G35>0,G35,0) -> 89.4768 | M35: =ABS(+IF(G35<0,G35,0)) -> 0 | Q35: ="CONSUMO DE COPIAS "&D35 -> CONSUMO DE COPIAS 9502370Y | S35: ="Factura N° " & $A$2 -> Factura N° 01-F020-00027840 | T35: =F35 -> 403
C36: MX-3070 | D36: 35009304 | E36: 10.72.8.200 | F36: 404 | G36: 51.681905 | H36: 942331307 | L36: =IF(G36>0,G36,0) -> 51.681905 | M36: =ABS(+IF(G36<0,G36,0)) -> 0 | Q36: ="FOTOCOPIAS POR ALQUILER EQUIPO MULTIFUNCIONAL DEL 01-"&TEXT(MONTH($B$3),"00")&"-"&YEAR($B$3)&" AL "&TEXT(DAY($B$3),"00")&"-"&TEXT(MONTH($B$3),"00")&"-"&YEAR($B$3) -> FOTOCOPIAS POR ALQUILER EQUIPO MULTIFUNCIONAL DEL 01-03-2026 AL 31-03-2026 | S36: ="Factura N° " & $A$2 -> Factura N° 01-F020-00027840 | T36: =F36 -> 404
C37: MX-3070 | D37: 35009304 | E37: 10.72.8.200 | F37: 404 | G37: 61.404 | H37: 942331307 | L37: =IF(G37>0,G37,0) -> 61.404 | M37: =ABS(+IF(G37<0,G37,0)) -> 0 | Q37: ="CONSUMO DE COPIAS "&D37 -> CONSUMO DE COPIAS 35009304 | S37: ="Factura N° " & $A$2 -> Factura N° 01-F020-00027840 | T37: =F37 -> 404
C38: WF-C5790 | D38: X3B7003659 | E38: 10.72.8.197 | F38: 406 | G38: 51.681905 | H38: 943331308 | L38: =IF(G38>0,G38,0) -> 51.681905 | M38: =ABS(+IF(G38<0,G38,0)) -> 0 | Q38: ="FOTOCOPIAS POR ALQUILER EQUIPO MULTIFUNCIONAL DEL 01-"&TEXT(MONTH($B$3),"00")&"-"&YEAR($B$3)&" AL "&TEXT(DAY($B$3),"00")&"-"&TEXT(MONTH($B$3),"00")&"-"&YEAR($B$3) -> FOTOCOPIAS POR ALQUILER EQUIPO MULTIFUNCIONAL DEL 01-03-2026 AL 31-03-2026 | S38: ="Factura N° " & $A$2 -> Factura N° 01-F020-00027840 | T38: =F38 -> 406
C39: WF-C5790 | D39: X3B7003659 | E39: 10.72.8.197 | F39: 406 | G39: 17.0672 | H39: 943331308 | L39: =IF(G39>0,G39,0) -> 17.0672 | M39: =ABS(+IF(G39<0,G39,0)) -> 0 | Q39: ="CONSUMO DE COPIAS "&D39 -> CONSUMO DE COPIAS X3B7003659 | S39: ="Factura N° " & $A$2 -> Factura N° 01-F020-00027840 | T39: =F39 -> 406
C40: WF-C5890 | D40: XBJZ027512 | E40: 10.72.8.210 | F40: 406 | G40: 51.681905 | H40: 943331308 | L40: =IF(G40>0,G40,0) -> 51.681905 | M40: =ABS(+IF(G40<0,G40,0)) -> 0 | Q40: ="FOTOCOPIAS POR ALQUILER EQUIPO MULTIFUNCIONAL DEL 01-"&TEXT(MONTH($B$3),"00")&"-"&YEAR($B$3)&" AL "&TEXT(DAY($B$3),"00")&"-"&TEXT(MONTH($B$3),"00")&"-"&YEAR($B$3) -> FOTOCOPIAS POR ALQUILER EQUIPO MULTIFUNCIONAL DEL 01-03-2026 AL 31-03-2026 | S40: ="Factura N° " & $A$2 -> Factura N° 01-F020-00027840 | T40: =F40 -> 406
C41: WF-C5890 | D41: XBJZ027512 | E41: 10.72.8.210 | F41: 406 | G41: 180.1424 | H41: 943331308 | L41: =IF(G41>0,G41,0) -> 180.1424 | M41: =ABS(+IF(G41<0,G41,0)) -> 0 | Q41: ="CONSUMO DE COPIAS "&D41 -> CONSUMO DE COPIAS XBJZ027512 | S41: ="Factura N° " & $A$2 -> Factura N° 01-F020-00027840 | T41: =F41 -> 406
C42: IR-C3330 | D42: RJQ00596 | E42: 10.72.8.203 | F42: 408 | G42: 51.681905 | H42: 941231308 | L42: =IF(G42>0,G42,0) -> 51.681905 | M42: =ABS(+IF(G42<0,G42,0)) -> 0 | Q42: ="FOTOCOPIAS POR ALQUILER EQUIPO MULTIFUNCIONAL DEL 01-"&TEXT(MONTH($B$3),"00")&"-"&YEAR($B$3)&" AL "&TEXT(DAY($B$3),"00")&"-"&TEXT(MONTH($B$3),"00")&"-"&YEAR($B$3) -> FOTOCOPIAS POR ALQUILER EQUIPO MULTIFUNCIONAL DEL 01-03-2026 AL 31-03-2026 | S42: ="Factura N° " & $A$2 -> Factura N° 01-F020-00027840 | T42: =F42 -> 408
C43: IR-C3330 | D43: RJQ00596 | E43: 10.72.8.203 | F43: 408 | G43: -2.0712 | H43: 941231308 | L43: =IF(G43>0,G43,0) -> 0 | M43: =ABS(+IF(G43<0,G43,0)) -> 2.0712 | Q43: ="CONSUMO DE COPIAS "&D43 -> CONSUMO DE COPIAS RJQ00596 | S43: ="Factura N° " & $A$2 -> Factura N° 01-F020-00027840 | T43: =F43 -> 408
L44: =SUM(L2:L43) -> 3079.204
L46: =+#REF! -> #REF! | M46: =+#REF! -> #REF!
L47: =+L46-L44 -> #REF!

Sheet Marzo
A1: 46112 | B1: Marca | C1: Modelo | D1: S/N | E1: IP | F1: Observación | G1: Cantidad Impresoras | H1: Bolsa | I1: Formatos | J1: Contador Inicial | K1: Contador Final | L1: Consumo del Mes | M1: Volumen Maximo Establecido | N1: Volumen Excedente | O1: Precio | P1: Total | Q1: alquiler fijo | T1: centro costo | V1: Bolsa | W1: Formatos | X1: Volumen Maximo
B2: Canon | C2: IR-C3330 | D2: RJQ00596 | E2: 10.72.8.203 | F2: 2do Piso - Seguridad | G2: 1 | H2: Bolsa 5 | I2: A4BN | J2: 130708 | K2: 131063 | L2: 355 | M2: 188 | N2: 167 | O2: 0.0168 | P2: 2.8056 | Q2: 51.681905 | R2: -2.0712 | S2: 941231308 | T2: 408 | U2: 1 | V2: Bolsa 1 | W2: A4BN | X2: 13000
I3: A3BN | J3: 6966 | K3: 6966 | L3: 0 | M3: 0 | N3: 0 | O3: 0.0301 | P3: 0 | V3: Bolsa 1 | W3: A3BN
I4: A4CL | J4: 187880 | K4: 188332 | L4: 452 | M4: 563 | N4: -111 | O4: 0.0472 | P4: -5.2392 | V4: Bolsa 1 | W4: A4CL
I5: A3CL | J5: 6966 | K5: 6970 | L5: 4 | M5: 0 | N5: 4 | O5: 0.0906 | P5: 0.3624 | V5: Bolsa 1 | W5: A3CL
C6: IR-1730 | D6: QFX06245 | E6: 10.72.8.215 | F6: 2do Piso - Oficina Auditor de Ingresos | G6: 1 | H6: Bolsa 1 | I6: A4BN | J6: 156715 | K6: 159127 | L6: 2412 | M6: 3250 | N6: -838 | O6: 0.0168 | P6: -14.0784 | Q6: 51.681905 | R6: -14.0784 | S6: 941231308 | T6: 403 | U6: 2 | V6: Bolsa 2 | W6: A4BN | X6: 1504 | Y6: 8
I7: A3BN | J7: 0 | K7: 0 | L7: 0 | N7: 0 | O7: 0.0301 | P7: 0 | V7: Bolsa 2 | W7: A3BN
I8: A4CL | J8: 0 | K8: 0 | L8: 0 | N8: 0 | O8: 0.0472 | P8: 0 | V8: Bolsa 2 | W8: A4CL | X8: 4504 | Y8: 188
I9: A3CL | J9: 0 | K9: 0 | L9: 0 | N9: 0 | O9: 0.0906 | P9: 0 | V9: Bolsa 2 | W9: A3CL
C10: IR-1643 | D10: 35E33608 | E10: 10.72.8.211 | F10: 1er Piso - Front Desk - Recepción | G10: 1 | H10: Bolsa 1 | I10: A4BN | J10: 36 | K10: 23904 | L10: 23868 | M10: 3250 | N10: 20618 | O10: 0.0168 | P10: 346.3824 | Q10: 51.681905 | R10: 346.3824 | S10: 931221108 | T10: 101 | U10: 1 | V10: Bolsa 3 | W10: A4BN | X10: 1128
I11: A3BN | J11: 0 | K11: 0 | L11: 0 | N11: 0 | O11: 0.0301 | P11: 0 | V11: Bolsa 3 | W11: A3BN
I12: A4CL | J12: 0 | K12: 0 | L12: 0 | N12: 0 | O12: 0.0472 | P12: 0 | V12: Bolsa 3 | W12: A4CL | X12: 3378
I13: A3CL | J13: 0 | K13: 0 | L13: 0 | N13: 0 | O13: 0.0906 | P13: 0 | V13: Bolsa 3 | W13: A3CL
C14: IR-1643 | D14: 35E33607 | E14: 10.72.8.153 | F14: 1er Piso - Front Desk - Recepción | G14: 1 | H14: Bolsa 1 | I14: A4BN | J14: 6528 | K14: 14888 | L14: 8360 | M14: 3250 | N14: 5110 | O14: 0.0168 | P14: 85.848 | Q14: 51.681905 | R14: 85.848 | S14: 931221108 | T14: 101 | U14: 1 | V14: Bolsa 4 | W14: A4BN | X14: 188
I15: A3BN | J15: 0 | K15: 0 | L15: 0 | N15: 0 | O15: 0.0301 | P15: 0 | V15: Bolsa 4 | W15: A3BN
I16: A4CL | J16: 0 | K16: 0 | L16: 0 | N16: 0 | O16: 0.0472 | P16: 0 | V16: Bolsa 4 | W16: A4CL | X16: 563
I17: A3CL | J17: 0 | K17: 0 | L17: 0 | N17: 0 | O17: 0.0906 | P17: 0 | V17: Bolsa 4 | W17: A3CL
B18: Epson | C18: WF-C5790 | D18: X3B7002433 | E18: 10.72.8.191 | F18: 2do Piso - Oficina Banquetes | G18: 1 | H18: Bolsa 2 | I18: A4BN | J18: 83734 | K18: 84608 | L18: 874 | M18: 188 | N18: 686 | O18: 0.0168 | P18: 11.5248 | Q18: 51.681905 | R18: 174.176 | S18: 932341308 | T18: 207 | U18: 2 | V18: Bolsa 5 | W18: A4BN | X18: 188
I19: A3BN | J19: 0 | K19: 0 | L19: 0 | N19: 0 | O19: 0.0301 | P19: 0 | V19: Bolsa 5 | W19: A3BN
I20: A4CL | J20: 21349 | K20: 25358 | L20: 4009 | M20: 563 | N20: 3446 | O20: 0.0472 | P20: 162.6512 | V20: Bolsa 5 | W20: A4CL | X20: 563
I21: A3CL | J21: 0 | K21: 0 | L21: 0 | N21: 0 | O21: 0.0906 | P21: 0 | V21: Bolsa 5 | W21: A3CL
C22: WF-C5790 | D22: X3B7003659 | E22: 10.72.8.197 | F22: 3er Piso - Reservas | G22: 1 | H22: Bolsa 2 | I22: A4BN | J22: 15527 | K22: 15992 | L22: 465 | M22: 188 | N22: 277 | O22: 0.0168 | P22: 4.6536 | Q22: 51.681905 | R22: 17.0672 | S22: 943331308 | T22: 406 | U22: 2
I23: A3BN | J23: 0 | K23: 0 | L23: 0 | N23: 0 | O23: 0.0301 | P23: 0
I24: A4CL | J24: 14379 | K24: 15205 | L24: 826 | M24: 563 | N24: 263 | O24: 0.0472 | P24: 12.4136
I25: A3CL | J25: 0 | K25: 0 | L25: 0 | N25: 0 | O25: 0.0906 | P25: 0
C26: WF-C5790 | D26: X3B7003660 | E26: 10.72.8.204 | F26: 1er Piso - Room Service | G26: 1 | H26: Bolsa 2 | I26: A4BN | J26: 83188 | K26: 83943 | L26: 755 | M26: 188 | N26: 567 | O26: 0.0168 | P26: 9.5256 | Q26: 51.681905 | R26: 81.9776 | S26: 932341308 | T26: 206 | U26: 2
I27: A3BN | J27: 0 | K27: 0 | L27: 0 | N27: 0 | O27: 0.0301 | P27: 0 | W27: X3B7003661 - WF-C5790
I28: A4CL | J28: 18110 | K28: 20208 | L28: 2098 | M28: 563 | N28: 1535 | O28: 0.0472 | P28: 72.452 | W28: X3B7003661 - WF-C5790 -
I29: A3CL | J29: 0 | K29: 0 | L29: 0 | N29: 0 | O29: 0.0906 | P29: 0
C30: WF-C5790 | D30: X3B7003661 | E30: 10.72.8.132 | F30: 1er Sotano - Steward - Limpieza | G30: 1 | I30: A4BN | J30: 13075 | K30: 20147 | L30: 7072 | O30: 0.0168 | P30: 118.8096 | Q30: 51.681905 | R30: 437.3624 | S30: 932341308 | T30: 200 | W30: FALSE
I31: A3BN | J31: 0 | K31: 0 | L31: 0 | N31: 0 | O31: 0.0301 | P31: 0
I32: A4CL | J32: 6457 | K32: 13206 | L32: 6749 | O32: 0.0472 | P32: 318.5528
I33: A3CL | J33: 0 | K33: 0 | L33: 0 | N33: 0 | O33: 0.0906 | P33: 0
C34: WF-C5790 | D34: X3B7003671 | E34: 10.72.8.208 | F34: 1er Piso - Caja Lobby Bar | G34: 1 | H34: Bolsa 2 | I34: A4BN | J34: 9497 | K34: 9830 | L34: 333 | M34: 188 | N34: 145 | O34: 0.0168 | P34: 2.436 | Q34: 51.681905 | R34: 1.8696 | S34: 932341308 | T34: 204
I35: A3BN | J35: 0 | K35: 0 | L35: 0 | N35: 0 | O35: 0.0301 | P35: 0
I36: A4CL | J36: 4511 | K36: 5062 | L36: 551 | M36: 563 | N36: -12 | O36: 0.0472 | P36: -0.5664
I37: A3CL | J37: 0 | K37: 0 | L37: 0 | N37: 0 | O37: 0.0906 | P37: 0
C38: WF-C5790 | D38: X3B7003703 | E38: 10.9.10.153 | F38: 1er Piso Gym | G38: 1 | H38: Bolsa 2 | I38: A4BN | J38: 85135 | K38: 88863 | L38: 3728 | M38: 188 | N38: 3540 | O38: 0.0168 | P38: 59.472 | Q38: 51.681905 | R38: 55.46 | S38: 933441108 | T38: 304
I39: A3BN | J39: 0 | K39: 0 | L39: 0 | N39: 0 | O39: 0.0301 | P39: 0
I40: A4CL | J40: 9094 | K40: 9572 | L40: 478 | M40: 563 | N40: -85 | O40: 0.0472 | P40: -4.012
I41: A3CL | J41: 0 | K41: 0 | L41: 0 | N41: 0 | O41: 0.0906 | P41: 0
C42: WF-C5790 | D42: X3B7003711 | E42: 10.72.8.205 | F42: 1er Piso - Recepción - Back Office | G42: 1 | H42: Bolsa 2 | I42: A4BN | J42: 129700 | K42: 131931 | L42: 2231 | M42: 188 | N42: 2043 | O42: 0.0168 | P42: 34.3224 | Q42: 51.681905 | R42: 44.7064 | S42: 931221108 | T42: 101 | U42: -7072
I43: A3BN | J43: 0 | K43: 0 | L43: 0 | N43: 0 | O43: 0.0301 | P43: 0
I44: A4CL | J44: 23452 | K44: 24235 | L44: 783 | M44: 563 | N44: 220 | O44: 0.0472 | P44: 10.384
I45: A3CL | J45: 0 | K45: 0 | L45: 0 | N45: 0 | O45: 0.0906 | P45: 0
C46: WF-C5790 | D46: X3B7003739 | E46: 10.72.10.43 | F46: 1er Piso Compras | G46: 1 | H46: Bolsa 2 | I46: A4BN | J46: 30199 | K46: 30545 | L46: 346 | M46: 188 | N46: 158 | O46: 0.0168 | P46: 2.6544 | Q46: 51.681905 | R46: -13.9128 | S46: 941231308 | T46: 402
I47: A3BN | J47: 0 | K47: 0 | L47: 0 | N47: 0 | O47: 0.0301 | P47: 0
I48: A4CL | J48: 34833 | K48: 35045 | L48: 212 | M48: 563 | N48: -351 | O48: 0.0472 | P48: -16.5672
I49: A3CL | J49: 0 | K49: 0 | L49: 0 | N49: 0 | O49: 0.0906 | P49: 0
C50: WF-C5790 | D50: X3B7003876 | E50: 10.72.8.220 | F50: 1er Piso - Oficina AyB | G50: 1 | H50: Bolsa 2 | I50: A4BN | J50: 58830 | K50: 59665 | L50: 835 | M50: 188 | N50: 647 | O50: 0.0168 | P50: 10.8696 | Q50: 51.681905 | R50: 7.5656 | S50: 932341308 | T50: 200
I51: A3BN | J51: 0 | K51: 0 | L51: 0 | N51: 0 | O51: 0.0301 | P51: 0
I52: A4CL | J52: 35550 | K52: 36043 | L52: 493 | M52: 563 | N52: -70 | O52: 0.0472 | P52: -3.304
I53: A3CL | J53: 0 | K53: 0 | L53: 0 | N53: 0 | O53: 0.0906 | P53: 0
C54: WF-C5890 | D54: XBJZ017266 | E54: 10.72.8.229 | F54: 1er Sotano - Housekeeping | G54: 1 | H54: Bolsa 3 | I54: A4BN | J54: 6445 | K54: 7222 | L54: 777 | M54: 188 | N54: 589 | O54: 0.0168 | P54: 9.8952 | Q54: 51.681905 | R54: 192.6536 | S54: 931221108 | T54: 102
I55: A3BN | J55: 0 | K55: 0 | L55: 0 | N55: 0 | O55: 0.0301 | P55: 0
I56: A4CL | J56: 24340 | K56: 28775 | L56: 4435 | M56: 563 | N56: 3872 | O56: 0.0472 | P56: 182.7584
I57: A3CL | J57: 0 | K57: 0 | L57: 0 | N57: 0 | O57: 0.0906 | P57: 0
C58: WF-C5890 | D58: XBJZ017602 | E58: 10.72.8.206 | F58: 1er Piso - Bodega | G58: 1 | H58: Bolsa 3 | I58: A4BN | J58: 28313 | K58: 28834 | L58: 521 | M58: 188 | N58: 333 | O58: 0.0168 | P58: 5.5944 | Q58: 51.681905 | R58: 41.7968 | S58: 941231308 | T58: 403
I59: A3BN | J59: 0 | K59: 0 | L59: 0 | N59: 0 | O59: 0.0301 | P59: 0
I60: A4CL | J60: 34374 | K60: 35704 | L60: 1330 | M60: 563 | N60: 767 | O60: 0.0472 | P60: 36.2024
I61: A3CL | J61: 0 | K61: 0 | L61: 0 | N61: 0 | O61: 0.0906 | P61: 0
C62: WF-C5890 | D62: XBJZ017603 | E62: 10.72.8.196 | F62: 1er Piso - Conserge | G62: 1 | H62: Bolsa 3 | I62: A4BN | J62: 3603 | K62: 4044 | L62: 441 | M62: 188 | N62: 253 | O62: 0.0168 | P62: 4.2504 | Q62: 51.681905 | R62: -1.3192 | S62: 931221108 | T62: 103
I63: A3BN | J63: 0 | K63: 0 | L63: 0 | N63: 0 | O63: 0.0301 | P63: 0
I64: A4CL | J64: 3848 | K64: 4293 | L64: 445 | M64: 563 | N64: -118 | O64: 0.0472 | P64: -5.5696
I65: A3CL | J65: 0 | K65: 0 | L65: 0 | N65: 0 | O65: 0.0906 | P65: 0
C66: WF-C5890 | D66: XBJZ021745 | E66: 10.72.8.219 | F66: 1er Piso - Oficina Chef | G66: 1 | H66: Bolsa 3 | I66: A4BN | J66: 4141 | K66: 4785 | L66: 644 | M66: 188 | N66: 456 | O66: 0.0168 | P66: 7.6608 | Q66: 51.681905 | R66: 167.1496 | S66: 932341308 | T66: 200 | U66: 1
I67: A3BN | J67: 0 | K67: 0 | L67: 0 | N67: 0 | O67: 0.0301 | P67: 0
I68: A4CL | J68: 23586 | K68: 27528 | L68: 3942 | M68: 563 | N68: 3379 | O68: 0.0472 | P68: 159.4888
I69: A3CL | J69: 0 | K69: 0 | L69: 0 | N69: 0 | O69: 0.0906 | P69: 0
C70: WF-C5890 | D70: XBJZ021772 | E70: 10.72.8.151 | F70: 3er Piso - Gerencia General | G70: 1 | H70: Bolsa 3 | I70: A4BN | J70: 1638 | K70: 2080 | L70: 442 | M70: 188 | N70: 254 | O70: 0.0168 | P70: 4.2672 | Q70: 51.681905 | R70: 8.8456 | S70: 941231308 | T70: 401
I71: A3BN | J71: 0 | K71: 0 | L71: 0 | N71: 0 | O71: 0.0301 | P71: 0
I72: A4CL | J72: 1473 | K72: 2133 | L72: 660 | M72: 563 | N72: 97 | O72: 0.0472 | P72: 4.5784
I73: A3CL | J73: 0 | K73: 0 | L73: 0 | N73: 0 | O73: 0.0906 | P73: 0
C74: WF-C5890 | D74: XBJZ027512 | E74: 10.72.8.210 | F74: 3er Piso - Ventas | G74: 1 | H74: Bolsa 3 | I74: A4BN | J74: 3883 | K74: 5188 | L74: 1305 | M74: 188 | N74: 1117 | O74: 0.0168 | P74: 18.7656 | Q74: 51.681905 | R74: 180.1424 | S74: 943331308 | T74: 406
I75: A3BN | J75: 0 | K75: 0 | L75: 0 | N75: 0 | O75: 0.0301 | P75: 0
I76: A4CL | J76: 11370 | K76: 15352 | L76: 3982 | M76: 563 | N76: 3419 | O76: 0.0472 | P76: 161.3768
I77: A3CL | J77: 0 | K77: 0 | L77: 0 | N77: 0 | O77: 0.0906 | P77: 0
B78: Sharp | C78: MX-3070 | D78: 35009304 | E78: 10.72.8.200 | F78: 1er Sotano - RRHH - Sistemas | G78: 1 | H78: Bolsa 4 | I78: A4BN | J78: 5 | K78: 3848 | L78: 3843 | M78: 188 | N78: 3655 | O78: 0.0168 | P78: 61.404 | Q78: 51.681905 | R78: 61.404 | S78: 942331307 | T78: 404
I79: A3BN | J79: 0 | K79: 0 | L79: 0 | N79: 0 | O79: 0.0301 | P79: 0
I80: A4CL | J80: 31 | K80: 340 | L80: 309 | M80: 563 | N80: 0 | O80: 0.0472 | P80: 0
I81: A3CL | J81: 0 | K81: 0 | L81: 0 | N81: 0 | O81: 0.0906 | P81: 0
C82: MX-M3070 | D82: 9502370Y | E82: 10.72.8.207 | F82: 3er Piso - Contabilidad | G82: 1 | H82: Bolsa 1 | I82: A4BN | J82: 57 | K82: 8633 | L82: 8576 | M82: 3250 | N82: 5326 | O82: 0.0168 | P82: 89.4768 | Q82: 51.681905 | R82: 89.4768 | S82: 941231308 | T82: 403
I83: A3BN | J83: 0 | K83: 0 | L83: 0 | N83: 0 | O83: 0.0301 | P83: 0
I84: A4CL | J84: 0 | K84: 0 | L84: 0 | M84: 0 | N84: 0 | O84: 0.0472 | P84: 0
I85: A3CL | J85: 0 | K85: 0 | L85: 0 | N85: 0 | O85: 0.0906 | P85: 0
B86: Total | G86: 21 | O86: A4BN | P86: 507.6288 | U86: Bolsa 1 | V86: ok
O87: A4BN | P87: 135.4584 | U87: Bolsa2 | V87: ok
O88: A4CL | P88: 233.4512 | U88: Bolsa2 | V88: ok
O89: A4BN | P89: 50.4336 | U89: Bolsa3 | V89: ok
O90: A4CL | P90: 538.8352 | U90: Bolsa3 | V90: ok
O91: A4BN | P91: 61.404 | U91: Bolsa4 | V91: ok | W91: 36679.522
O92: A4BN | P92: 2.8056 | U92: Bolsa5 | V92: ok
O93: A3CL | P93: 0.3624 | U93: Bolsa6 | V93: ok
P94: 1530.3792
P96: 1967.7416 | R96: 1962.5024
R97: -5.2392
